Workbook

Sheet invoice_test_data
A1: IVCE_DTL_UID | B1: IVCE_HDR_ID | C1: CMPY_DVSN_NUM | D1: IVCE_NUM | E1: Vender Lookup | F1: VNDR_ID | G1: IVCE_LNE_NUM | H1: ITM_LDSC | I1: ITM_QTY | J1: ITM_UOM_CD | K1: ITM_PRC_CD | L1: ITM_UNT_CST_AMT | M1: MFR_NM | N1: MFR_PRT_NUM | O1: VNDR_PRT_NUM | P1: AKS_PRT_NUM | Q1: UPC_CD | R1: XTNDD_CST_AMT | S1: REC_UPDD_DTTM | T1: REC_UPDD_BY_ID | U1: REC_CRTD_DTTM | V1: REC_CRTD_BY_ID | W1: PRCH_ORDR_DTL_UID | X1: PRCH_ORDR_LNE_NUM | Y1: LNE_ITM_STAT_CD | Z1: CVRTD_CTRT_PRC_AMT | AA1: CVRTD_PRCH_ORDR_PRC_AMT | AB1: CTRT_ID | AC1: CLN_MFR_NM | AD1: CLN_MFR_AI_NM | AE1: IVCE_LNE_STAT | AF1: UNSPSC_CD | AG1: WEBSITE Link | AH1: AI Consideration? | AI1: CLASSIFICATION | AJ1: CLASSIFICATION | AK1: Notes | AL1: ItemID | AM1: MfrPartNum | AN1: MfrName | AO1: UPC | AP1: UNSPSC | AQ1: AKPartNum | AR1: DescriptionID | AS1: ItemDescription | AT1: CleanName | AU1: UncleanName | AV1: MfrNameMatchType | AW1: DescriptionSimilarity | AX1: PartNumberConfidenceScore | AY1: ManufacturerNameConfidenceScore | AZ1: UNSPSCConfidenceScore | BA1: Semantic_MfrName | BB1: Semantic_MfrNameConfidenceScore | BC1: Semantic_UNSPSC | BD1: Semantic_UNSPSCConfidenceScore | BE1: Semantic_IsMfrClean
A2: 905679 | B2: 281619 | C2: NULL | D2: 6082907-0018 | F2: 14555 | G2: 1 | H2: YALE GP050VX 5,000# WAREHOUSE FORKLIFT | I2: 1 | J2: E | K2: E | L2: 975 | M2: YALE | N2: GP050VX | O2: NULL | P2: NULL | Q2: NULL | R2: 975 | S2: 45744.48 | T2: PA_SRDC | U2: 45744.264 | V2: PAUSER | W2: NULL | X2: 0 | Y2: 999 | Z2: NULL | AA2: NULL | AB2: NULL | AC2: RENTAL - UNDEFINED | AD2: RENTAL - UNDEFINED | AE2: AI | AF2: - | AG2: https://www.crescorent.com/equipment-rentals/5000-warehouse-forklift/ | AI2: MATERIAL | AJ2: =VLOOKUP(A2,'Classification Test Result'!$A$2:$D$2428,4,FALSE) -> #N/A | AL2: =_xlfn.XLOOKUP($A2,Results!$A$2:$A$2256,Results!G$2:G$2256,"") -> 0 | AM2: =_xlfn.XLOOKUP($A2,Results!$A$2:$A$2256,Results!H$2:H$2256,"") -> 0 | AN2: =_xlfn.XLOOKUP($A2,Results!$A$2:$A$2256,Results!I$2:I$2256,"") -> 0 | AO2: =_xlfn.XLOOKUP($A2,Results!$A$2:$A$2256,Results!J$2:J$2256,"") -> 0 | AP2: =_xlfn.XLOOKUP($A2,Results!$A$2:$A$2256,Results!K$2:K$2256,"") -> 0 | AQ2: =_xlfn.XLOOKUP($A2,Results!$A$2:$A$2256,Results!L$2:L$2256,"") -> 0 | AR2: =_xlfn.XLOOKUP($A2,Results!$A$2:$A$2256,Results!M$2:M$2256,"") -> 0 | AS2: =_xlfn.XLOOKUP($A2,Results!$A$2:$A$2256,Results!N$2:N$2256,"") -> 0 | ... BE2: =_xlfn.XLOOKUP($A2,Results!$A$2:$A$2256,Results!Z$2:Z$2256,"") -> 0
A3: 905680 | B3: 281389 | C3: NULL | D3: 9341431319 | E3: =VLOOKUP(F3,'RPA Vendor Data '!F1:$G$2418,2) -> GRAYBAR ELECTRIC CO. INC. | F3: 11471 | G3: 2 | H3: X7 COOPER CROUSE-HINDS DIVISION CHICO CHICO X FIBER 1 LB AK10289128 | I3: 1 | J3: 1 | K3: E | L3: 117.85 | M3: CROUSE-HINDS | N3: CHICO X7 | O3: NULL | P3: AK10289128 | Q3: NULL | R3: 117.85 | S3: 45744.272 | T3: PA_SRDC | U3: 45744.053 | V3: PAUSER | W3: NULL | X3: 2 | Y3: 201,0,0 | Z3: NULL | AA3: 117.85 | AB3: NULL | AC3: EATON DISTRIBUTION EQUIP | AD3: EATON DISTRIBUTION EQUIP | AE3: AI | AF3: 39121337 | AG3: https://www.graybar.com/chico174-x-fiber-1-lb-box/p/88069549 | AI3: MATERIAL | AJ3: =VLOOKUP(A3,'Classification Test Result'!$A$2:$D$2428,4,FALSE) -> #N/A | AL3: =_xlfn.XLOOKUP($A3,Results!$A$2:$A$2256,Results!G$2:G$2256,"") -> 0 | AM3: =_xlfn.XLOOKUP($A3,Results!$A$2:$A$2256,Results!H$2:H$2256,"") -> 0 | AN3: =_xlfn.XLOOKUP($A3,Results!$A$2:$A$2256,Results!I$2:I$2256,"") -> 0 | AO3: =_xlfn.XLOOKUP($A3,Results!$A$2:$A$2256,Results!J$2:J$2256,"") -> 0 | AP3: =_xlfn.XLOOKUP($A3,Results!$A$2:$A$2256,Results!K$2:K$2256,"") -> 0 | AQ3: =_xlfn.XLOOKUP($A3,Results!$A$2:$A$2256,Results!L$2:L$2256,"") -> 0 | AR3: =_xlfn.XLOOKUP($A3,Results!$A$2:$A$2256,Results!M$2:M$2256,"") -> 0 | AS3: =_xlfn.XLOOKUP($A3,Results!$A$2:$A$2256,Results!N$2:N$2256,"") -> 0 | ... BE3: =_xlfn.XLOOKUP($A3,Results!$A$2:$A$2256,Results!Z$2:Z$2256,"") -> 0
A4: 905681 | B4: 281955 | C4: NULL | D4: 9341430837 | E4: =VLOOKUP(F4,'RPA Vendor Data '!F2:$G$2418,2) -> GRAYBAR ELECTRIC CO. INC. | F4: 11471 | G4: 1 | H4: X CLOSE GENERIC VENDOR-TUBPA 3/4 3/4 X CLOSE-GALVANIZED CONDUIT NIPPLE | I4: 12 | J4: C | K4: C | L4: 148.05 | M4: GENERIC CONDUIT/CONDUIT FITTINGS | N4: 3/4 X CLOSE | O4: NULL | P4: AK10432182 | Q4: NULL | R4: 17.77 | S4: 45744.834 | T4: PA_SRDC | U4: 45744.619 | V4: PAUSER | W4: NULL | X4: 0 | Y4: 201 | Z4: NULL | AA4: NULL | AB4: NULL | AC4: GENERIC CONDUIT/CONDUIT FITTINGS | AD4: GENERIC CONDUIT/CONDUIT FITTINGS | AE4: AI | AF4: 39131718 | AG4: https://www.graybar.com/conduit-nipple-rigid-imc-galvanized-steel-3-4-x-close/p/88273326 | AI4: MATERIAL | AJ4: =VLOOKUP(A4,'Classification Test Result'!$A$2:$D$2428,4,FALSE) -> #N/A | AL4: =_xlfn.XLOOKUP($A4,Results!$A$2:$A$2256,Results!G$2:G$2256,"") -> 0 | AM4: =_xlfn.XLOOKUP($A4,Results!$A$2:$A$2256,Results!H$2:H$2256,"") -> 0 | AN4: =_xlfn.XLOOKUP($A4,Results!$A$2:$A$2256,Results!I$2:I$2256,"") -> 0 | AO4: =_xlfn.XLOOKUP($A4,Results!$A$2:$A$2256,Results!J$2:J$2256,"") -> 0 | AP4: =_xlfn.XLOOKUP($A4,Results!$A$2:$A$2256,Results!K$2:K$2256,"") -> 0 | AQ4: =_xlfn.XLOOKUP($A4,Results!$A$2:$A$2256,Results!L$2:L$2256,"") -> 0 | AR4: =_xlfn.XLOOKUP($A4,Results!$A$2:$A$2256,Results!M$2:M$2256,"") -> 0 | AS4: =_xlfn.XLOOKUP($A4,Results!$A$2:$A$2256,Results!N$2:N$2256,"") -> 0 | ... BE4: =_xlfn.XLOOKUP($A4,Results!$A$2:$A$2256,Results!Z$2:Z$2256,"") -> TRUE
A5: 905682 | B5: 281420 | C5: NULL | D5: S142066793.001 | E5: =VLOOKUP(F5,'RPA Vendor Data '!F3:$G$2418,2) -> REXEL USA, INC. | F5: 12873 | G5: 1 | H5: WS LMRC-211 770734 DIGITAL V.2 SGLE RELAY RM CONTROLLER ON/OFF 0-10V DIMM | I5: 2 | J5: EA | K5: E | L5: 209.816 | M5: WATTSTOPPER | N5: LMRC-211 | O5: 770734 | P5: NULL | Q5: NULL | R5: 419.63 | S5: 45744.271 | T5: PA_SRDC | U5: 45744.061 | V5: PAUSER | W5: NULL | X5: 0 | Y5: 201 | Z5: NULL | AA5: NULL | AB5: NULL | AC5: WATTSTOPPER | AD5: WATTSTOPPER | AE5: AI | AF5: - | AG5: https://www.rexelusa.com/p/770734/wattstopper/digital-room-controller-dimmer-single/754182929030/lmrc-211 | AI5: MATERIAL | AJ5: =VLOOKUP(A5,'Classification Test Result'!$A$2:$D$2428,4,FALSE) -> #N/A | AL5: =_xlfn.XLOOKUP($A5,Results!$A$2:$A$2256,Results!G$2:G$2256,"") -> 735909 | AM5: =_xlfn.XLOOKUP($A5,Results!$A$2:$A$2256,Results!H$2:H$2256,"") -> LMRC211 | AN5: =_xlfn.XLOOKUP($A5,Results!$A$2:$A$2256,Results!I$2:I$2256,"") -> WATTSTOPPER | AO5: =_xlfn.XLOOKUP($A5,Results!$A$2:$A$2256,Results!J$2:J$2256,"") -> 754182929030 | AP5: =_xlfn.XLOOKUP($A5,Results!$A$2:$A$2256,Results!K$2:K$2256,"") -> 45111808 | AQ5: =_xlfn.XLOOKUP($A5,Results!$A$2:$A$2256,Results!L$2:L$2256,"") -> 0 | AR5: =_xlfn.XLOOKUP($A5,Results!$A$2:$A$2256,Results!M$2:M$2256,"") -> 480852 | AS5: =_xlfn.XLOOKUP($A5,Results!$A$2:$A$2256,Results!N$2:N$2256,"") -> WATT LMRC-211 ROOM CTRLR | ... BE5: =_xlfn.XLOOKUP($A5,Results!$A$2:$A$2256,Results!Z$2:Z$2256,"") -> TRUE
A6: 905683 | B6: 281440 | C6: NULL | D6: S104532279.001 | E6: =VLOOKUP(F6,'RPA Vendor Data '!F4:$G$2418,2) -> DAKOTA SUPPLY GROUP | F6: 10942 | G6: 1 | H6: WRMLD LOT 729287 * Item not returnable without RGA * (4) WD10W350-60 (8) CP10-S30 (8) WD10W350-ECS | I6: 1 | J6: EA | K6: E | L6: 2182.031 | M6: WIREMOLD | N6: LOT | O6: 729287 | P6: NULL | Q6: NULL | R6: 2182.03 | S6: 45744.313 | T6: PA_SRDC | U6: 45744.088 | V6: PAUSER | W6: NULL | X6: 0 | Y6: 999 | Z6: NULL | AA6: NULL | AB6: NULL | AC6: UNDEFINED | AD6: UNDEFINED | AE6: AI | AF6: - | AG6: LOT | AH6: No | AI6: MATERIAL | AJ6: =VLOOKUP(A6,'Classification Test Result'!$A$2:$D$2428,4,FALSE) -> #N/A | AL6: =_xlfn.XLOOKUP($A6,Results!$A$2:$A$2256,Results!G$2:G$2256,"") -> 0 | AM6: =_xlfn.XLOOKUP($A6,Results!$A$2:$A$2256,Results!H$2:H$2256,"") -> 0 | AN6: =_xlfn.XLOOKUP($A6,Results!$A$2:$A$2256,Results!I$2:I$2256,"") -> 0 | AO6: =_xlfn.XLOOKUP($A6,Results!$A$2:$A$2256,Results!J$2:J$2256,"") -> 0 | AP6: =_xlfn.XLOOKUP($A6,Results!$A$2:$A$2256,Results!K$2:K$2256,"") -> 0 | AQ6: =_xlfn.XLOOKUP($A6,Results!$A$2:$A$2256,Results!L$2:L$2256,"") -> 0 | AR6: =_xlfn.XLOOKUP($A6,Results!$A$2:$A$2256,Results!M$2:M$2256,"") -> 0 | AS6: =_xlfn.XLOOKUP($A6,Results!$A$2:$A$2256,Results!N$2:N$2256,"") -> 0 | ... BE6: =_xlfn.XLOOKUP($A6,Results!$A$2:$A$2256,Results!Z$2:Z$2256,"") -> 0
A7: 905684 | B7: 281988 | C7: NULL | D7: S4741526.001 | E7: =VLOOKUP(F7,'RPA Vendor Data '!F5:$G$2418,2) -> FROST ELECTRIC SUPPLY CO | F7: 11364 | G7: 6 | H7: Wright 311 10PC Hex Bit Socket Set with 3/8 Drive Sizes 1/8 5/32 3/16 7/32 1/4 5/16 & 3/8, and 1/2 Drive Sizes 1/2 9/16 5/8 On Rail w/ 10 Clips | I7: 1 | J7: EA | K7: E | L7: 203.74 | M7: WRIGHT TOOL | N7: 311 | O7: NULL | P7: NULL | Q7: 76799003119 | R7: 203.74 | S7: 45744.897 | T7: PA_SRDC | U7: 45744.668 | V7: PAUSER | W7: NULL | X7: 10 | Y7: 201,0,0 | Z7: NULL | AA7: 203.74 | AB7: NULL | AC7: WRIGHT TOOL | AD7: WRIGHT TOOL | AE7: AI | AF7: - | AG7: https://www.zoro.com/wright-tool-38-drive-hex-bit-socket-set-sae-10-pcs-311/i/G2133618/?utm_source=google&utm_medium=surfaces&utm_campaign=shopping%20feed&utm_content=free%20google%20shopping%20clicks&campaignid=21528295865&productid=G2133618&v=&gad_source=1&gclid=EAIaIQobChMIo_uPm_rJjAMVkjEIBR0D7R-eEAQYASABEgLil_D_BwE&gclsrc=aw.ds | AI7: MATERIAL | AJ7: =VLOOKUP(A7,'Classification Test Result'!$A$2:$D$2428,4,FALSE) -> #N/A | AL7: =_xlfn.XLOOKUP($A7,Results!$A$2:$A$2256,Results!G$2:G$2256,"") -> 0 | AM7: =_xlfn.XLOOKUP($A7,Results!$A$2:$A$2256,Results!H$2:H$2256,"") -> 0 | AN7: =_xlfn.XLOOKUP($A7,Results!$A$2:$A$2256,Results!I$2:I$2256,"") -> 0 | AO7: =_xlfn.XLOOKUP($A7,Results!$A$2:$A$2256,Results!J$2:J$2256,"") -> 0 | AP7: =_xlfn.XLOOKUP($A7,Results!$A$2:$A$2256,Results!K$2:K$2256,"") -> 0 | AQ7: =_xlfn.XLOOKUP($A7,Results!$A$2:$A$2256,Results!L$2:L$2256,"") -> 0 | AR7: =_xlfn.XLOOKUP($A7,Results!$A$2:$A$2256,Results!M$2:M$2256,"") -> 0 | AS7: =_xlfn.XLOOKUP($A7,Results!$A$2:$A$2256,Results!N$2:N$2256,"") -> 0 | ... BE7: =_xlfn.XLOOKUP($A7,Results!$A$2:$A$2256,Results!Z$2:Z$2256,"") -> 0
A8: 905685 | B8: 281941 | C8: NULL | D8: 9341425462 | E8: =VLOOKUP(F8,'RPA Vendor Data '!F6:$G$2418,2) -> GRAYBAR ELECTRIC CO. INC. | F8: 11471 | G8: 2 | H8: WIREMOLD CO SGC2-RT SINGLE GANG COMM PLATE ORTRONICS | I8: 12 | J8: E | K8: E | L8: 9.05 | M8: WIREMOLD | N8: SGC2-RT | O8: NULL | P8: NULL | Q8: NULL | R8: 108.6 | S8: 45744.834 | T8: PA_SRDC | U8: 45744.617 | V8: PAUSER | W8: NULL | X8: 4 | Y8: 201,0,0 | Z8: NULL | AA8: 9.05 | AB8: NULL | AC8: WIREMOLD | AD8: WIREMOLD | AE8: AI | AF8: 39121307 | AG8: https://www.graybar.com/saf2-1-2-series-communication-plate/p/22044847?pcode=22044847 | AI8: MATERIAL | AJ8: =VLOOKUP(A8,'Classification Test Result'!$A$2:$D$2428,4,FALSE) -> #N/A | AL8: =_xlfn.XLOOKUP($A8,Results!$A$2:$A$2256,Results!G$2:G$2256,"") -> 0 | AM8: =_xlfn.XLOOKUP($A8,Results!$A$2:$A$2256,Results!H$2:H$2256,"") -> 0 | AN8: =_xlfn.XLOOKUP($A8,Results!$A$2:$A$2256,Results!I$2:I$2256,"") -> 0 | AO8: =_xlfn.XLOOKUP($A8,Results!$A$2:$A$2256,Results!J$2:J$2256,"") -> 0 | AP8: =_xlfn.XLOOKUP($A8,Results!$A$2:$A$2256,Results!K$2:K$2256,"") -> 0 | AQ8: =_xlfn.XLOOKUP($A8,Results!$A$2:$A$2256,Results!L$2:L$2256,"") -> 0 | AR8: =_xlfn.XLOOKUP($A8,Results!$A$2:$A$2256,Results!M$2:M$2256,"") -> 0 | AS8: =_xlfn.XLOOKUP($A8,Results!$A$2:$A$2256,Results!N$2:N$2256,"") -> 0 | ... BE8: =_xlfn.XLOOKUP($A8,Results!$A$2:$A$2256,Results!Z$2:Z$2256,"") -> TRUE
A9: 905686 | B9: 281941 | C9: NULL | D9: 9341425462 | E9: =VLOOKUP(F9,'RPA Vendor Data '!F7:$G$2418,2) -> GRAYBAR ELECTRIC CO. INC. | F9: 11471 | G9: 1 | H9: WIREMOLD CO SGC2-ACT SINGLE GANG COMM PLT ACTIVATE | I9: 12 | J9: E | K9: E | L9: 8.32 | M9: WIREMOLD | N9: SGC2-ACT | O9: NULL | P9: NULL | Q9: NULL | R9: 99.84 | S9: 45744.834 | T9: PA_SRDC | U9: 45744.617 | V9: PAUSER | W9: NULL | X9: 3 | Y9: 201,0,0 | Z9: NULL | AA9: 8.32 | AB9: NULL | AC9: WIREMOLD | AD9: WIREMOLD | AE9: AI | AF9: 39121307 | AG9: https://www.graybar.com/saf2-1-2-series-communication-plate-1-gang/p/22044849 | AI9: MATERIAL | AJ9: =VLOOKUP(A9,'Classification Test Result'!$A$2:$D$2428,4,FALSE) -> #N/A | AL9: =_xlfn.XLOOKUP($A9,Results!$A$2:$A$2256,Results!G$2:G$2256,"") -> 0 | AM9: =_xlfn.XLOOKUP($A9,Results!$A$2:$A$2256,Results!H$2:H$2256,"") -> 0 | AN9: =_xlfn.XLOOKUP($A9,Results!$A$2:$A$2256,Results!I$2:I$2256,"") -> 0 | AO9: =_xlfn.XLOOKUP($A9,Results!$A$2:$A$2256,Results!J$2:J$2256,"") -> 0 | AP9: =_xlfn.XLOOKUP($A9,Results!$A$2:$A$2256,Results!K$2:K$2256,"") -> 0 | AQ9: =_xlfn.XLOOKUP($A9,Results!$A$2:$A$2256,Results!L$2:L$2256,"") -> 0 | AR9: =_xlfn.XLOOKUP($A9,Results!$A$2:$A$2256,Results!M$2:M$2256,"") -> 0 | AS9: =_xlfn.XLOOKUP($A9,Results!$A$2:$A$2256,Results!N$2:N$2256,"") -> 0 | ... BE9: =_xlfn.XLOOKUP($A9,Results!$A$2:$A$2256,Results!Z$2:Z$2256,"") -> 0
A10: 905687 | B10: 281391 | C10: NULL | D10: 9341431311 | E10: =VLOOKUP(F10,'RPA Vendor Data '!F8:$G$2418,2) -> GRAYBAR ELECTRIC CO. INC. | F10: 11471 | G10: 1 | H10: WIREMOLD CO NP800C-10-2B NP800 ANOD POLE 10FT.2IN.L WBOX END | I10: 4 | J10: E | K10: E | L10: 708.15 | M10: WIREMOLD | N10: NP800C-10-2B | O10: NULL | P10: NULL | Q10: NULL | R10: 2832.6 | S10: 45744.272 | T10: PA_SRDC | U10: 45744.053 | V10: PAUSER | W10: NULL | X10: 0 | Y10: 201,0,0 | Z10: NULL | AA10: 708.15 | AB10: NULL | AC10: WIREMOLD | AD10: WIREMOLD | AE10: AI | AF10: 39131713 | AG10: https://www.graybar.com/power-pole-aluminum-np800-tele-power-10-ft-2-in/p/25872612?pcode=25872612 | AI10: MATERIAL | AJ10: =VLOOKUP(A10,'Classification Test Result'!$A$2:$D$2428,4,FALSE) -> #N/A | AL10: =_xlfn.XLOOKUP($A10,Results!$A$2:$A$2256,Results!G$2:G$2256,"") -> 0 | AM10: =_xlfn.XLOOKUP($A10,Results!$A$2:$A$2256,Results!H$2:H$2256,"") -> 0 | AN10: =_xlfn.XLOOKUP($A10,Results!$A$2:$A$2256,Results!I$2:I$2256,"") -> 0 | AO10: =_xlfn.XLOOKUP($A10,Results!$A$2:$A$2256,Results!J$2:J$2256,"") -> 0 | AP10: =_xlfn.XLOOKUP($A10,Results!$A$2:$A$2256,Results!K$2:K$2256,"") -> 0 | AQ10: =_xlfn.XLOOKUP($A10,Results!$A$2:$A$2256,Results!L$2:L$2256,"") -> 0 | AR10: =_xlfn.XLOOKUP($A10,Results!$A$2:$A$2256,Results!M$2:M$2256,"") -> 0 | AS10: =_xlfn.XLOOKUP($A10,Results!$A$2:$A$2256,Results!N$2:N$2256,"") -> 0 | ... BE10: =_xlfn.XLOOKUP($A10,Results!$A$2:$A$2256,Results!Z$2:Z$2256,"") -> 0
A11: 905688 | B11: 281931 | C11: NULL | D11: 27MAR2025-109766 | F11: 16374 | G11: 2 | H11: WS (Winter Service Charge - Nov 1 - Mar 31) | I11: 40 | J11: E | K11: E | L11: 10 | M11: NULL | N11: NULL | O11: NULL | P11: NULL | Q11: NULL | R11: 400 | S11: 45744.813 | T11: PA_SRDC | U11: 45744.595 | V11: PAUSER | W11: NULL | X11: 0 | Y11: 999 | Z11: NULL | AA11: NULL | AB11: NULL | AC11: UNDEFINED | AD11: UNDEFINED | AE11: AI | AI11: FEE | AJ11: =VLOOKUP(A11,'Classification Test Result'!$A$2:$D$2428,4,FALSE) -> #N/A | AL11: =_xlfn.XLOOKUP($A11,Results!$A$2:$A$2256,Results!G$2:G$2256,"") -> 0 | AM11: =_xlfn.XLOOKUP($A11,Results!$A$2:$A$2256,Results!H$2:H$2256,"") -> 0 | AN11: =_xlfn.XLOOKUP($A11,Results!$A$2:$A$2256,Results!I$2:I$2256,"") -> 0 | AO11: =_xlfn.XLOOKUP($A11,Results!$A$2:$A$2256,Results!J$2:J$2256,"") -> 0 | AP11: =_xlfn.XLOOKUP($A11,Results!$A$2:$A$2256,Results!K$2:K$2256,"") -> 0 | AQ11: =_xlfn.XLOOKUP($A11,Results!$A$2:$A$2256,Results!L$2:L$2256,"") -> 0 | AR11: =_xlfn.XLOOKUP($A11,Results!$A$2:$A$2256,Results!M$2:M$2256,"") -> 0 | AS11: =_xlfn.XLOOKUP($A11,Results!$A$2:$A$2256,Results!N$2:N$2256,"") -> 0 | ... BE11: =_xlfn.XLOOKUP($A11,Results!$A$2:$A$2256,Results!Z$2:Z$2256,"") -> 0
A12: 905689 | B12: 281813 | C12: NULL | D12: 25MAR2025-109577 | F12: 16374 | G12: 2 | H12: WS (Winter Service Charge - Nov 1 - Mar 31) | I12: 30 | J12: E | K12: E | L12: 10 | M12: NULL | N12: NULL | O12: NULL | P12: NULL | Q12: NULL | R12: 300 | S12: 45744.605 | T12: PA_SRDC | U12: 45744.385 | V12: PAUSER | W12: NULL | X12: 0 | Y12: 999 | Z12: NULL | AA12: NULL | AB12: NULL | AC12: UNDEFINED | AD12: UNDEFINED | AE12: AI | AI12: FEE | AJ12: =VLOOKUP(A12,'Classification Test Result'!$A$2:$D$2428,4,FALSE) -> #N/A | AL12: =_xlfn.XLOOKUP($A12,Results!$A$2:$A$2256,Results!G$2:G$2256,"") -> 0 | AM12: =_xlfn.XLOOKUP($A12,Results!$A$2:$A$2256,Results!H$2:H$2256,"") -> 0 | AN12: =_xlfn.XLOOKUP($A12,Results!$A$2:$A$2256,Results!I$2:I$2256,"") -> 0 | AO12: =_xlfn.XLOOKUP($A12,Results!$A$2:$A$2256,Results!J$2:J$2256,"") -> 0 | AP12: =_xlfn.XLOOKUP($A12,Results!$A$2:$A$2256,Results!K$2:K$2256,"") -> 0 | AQ12: =_xlfn.XLOOKUP($A12,Results!$A$2:$A$2256,Results!L$2:L$2256,"") -> 0 | AR12: =_xlfn.XLOOKUP($A12,Results!$A$2:$A$2256,Results!M$2:M$2256,"") -> 0 | AS12: =_xlfn.XLOOKUP($A12,Results!$A$2:$A$2256,Results!N$2:N$2256,"") -> 0 | ... BE12: =_xlfn.XLOOKUP($A12,Results!$A$2:$A$2256,Results!Z$2:Z$2256,"") -> 0
A13: 905690 | B13: 281815 | C13: NULL | D13: 26MAR2025-109682 | F13: 16374 | G13: 2 | H13: WS (Winter Service Charge - Nov 1 - Mar 31) | I13: 50 | J13: E | K13: E | L13: 10 | M13: NULL | N13: NULL | O13: NULL | P13: NULL | Q13: NULL | R13: 500 | S13: 45744.605 | T13: PA_SRDC | U13: 45744.387 | V13: PAUSER | W13: NULL | X13: 0 | Y13: 999 | Z13: NULL | AA13: NULL | AB13: NULL | AC13: UNDEFINED | AD13: UNDEFINED | AE13: AI | AI13: FEE | AJ13: =VLOOKUP(A13,'Classification Test Result'!$A$2:$D$2428,4,FALSE) -> #N/A | AL13: =_xlfn.XLOOKUP($A13,Results!$A$2:$A$2256,Results!G$2:G$2256,"") -> 0 | AM13: =_xlfn.XLOOKUP($A13,Results!$A$2:$A$2256,Results!H$2:H$2256,"") -> 0 | AN13: =_xlfn.XLOOKUP($A13,Results!$A$2:$A$2256,Results!I$2:I$2256,"") -> 0 | AO13: =_xlfn.XLOOKUP($A13,Results!$A$2:$A$2256,Results!J$2:J$2256,"") -> 0 | AP13: =_xlfn.XLOOKUP($A13,Results!$A$2:$A$2256,Results!K$2:K$2256,"") -> 0 | AQ13: =_xlfn.XLOOKUP($A13,Results!$A$2:$A$2256,Results!L$2:L$2256,"") -> 0 | AR13: =_xlfn.XLOOKUP($A13,Results!$A$2:$A$2256,Results!M$2:M$2256,"") -> 0 | AS13: =_xlfn.XLOOKUP($A13,Results!$A$2:$A$2256,Results!N$2:N$2256,"") -> 0 | ... BE13: =_xlfn.XLOOKUP($A13,Results!$A$2:$A$2256,Results!Z$2:Z$2256,"") -> 0
A14: 905691 | B14: 281666 | C14: NULL | D14: S013772528.001 | E14: =VLOOKUP(F14,'RPA Vendor Data '!F9:$G$2418,2) -> VAN METER, INC. | F14: 13513 | G14: 1 | H14: WIRE-LINE 12550 1/2 STAPLE 500/BAG | I14: 500 | J14: m | K14: M | L14: 46.784 | M14: WIRE-LINE | N14: 12550 | O14: NULL | P14: NULL | Q14: 60550512550 | R14: 23.39 | S14: 45744.501 | T14: PA_SRDC | U14: 45744.282 | V14: PAUSER | W14: NULL | X14: 0 | Y14: 999 | Z14: NULL | AA14: NULL | AB14: NULL | AC14: UNDEFINED | AD14: UNDEFINED | AE14: AI | AF14: - | AG14: https://www.arcasupply.com/e27-7303/?srsltid=AfmBOor6FL2JUJCWR6beBKVWtuMh4c-5BwEaSyXlOWdR0cQ1Zajc6J8Q | AI14: MATERIAL | AJ14: =VLOOKUP(A14,'Classification Test Result'!$A$2:$D$2428,4,FALSE) -> #N/A | AK14: I can't find this item | AL14: =_xlfn.XLOOKUP($A14,Results!$A$2:$A$2256,Results!G$2:G$2256,"") -> 0 | AM14: =_xlfn.XLOOKUP($A14,Results!$A$2:$A$2256,Results!H$2:H$2256,"") -> 0 | AN14: =_xlfn.XLOOKUP($A14,Results!$A$2:$A$2256,Results!I$2:I$2256,"") -> 0 | AO14: =_xlfn.XLOOKUP($A14,Results!$A$2:$A$2256,Results!J$2:J$2256,"") -> 0 | AP14: =_xlfn.XLOOKUP($A14,Results!$A$2:$A$2256,Results!K$2:K$2256,"") -> 0 | AQ14: =_xlfn.XLOOKUP($A14,Results!$A$2:$A$2256,Results!L$2:L$2256,"") -> 0 | AR14: =_xlfn.XLOOKUP($A14,Results!$A$2:$A$2256,Results!M$2:M$2256,"") -> 0 | AS14: =_xlfn.XLOOKUP($A14,Results!$A$2:$A$2256,Results!N$2:N$2256,"") -> 0 | ... BE14: =_xlfn.XLOOKUP($A14,Results!$A$2:$A$2256,Results!Z$2:Z$2256,"") -> 0
A15: 905692 | B15: 281597 | C15: NULL | D15: S013772528.001 | E15: =VLOOKUP(F15,'RPA Vendor Data '!F10:$G$2418,2) -> VAN METER, INC. | F15: 13513 | G15: 1 | H15: WIRE-LINE 12550 1/2 STAPLE 500/BAG | I15: 500 | J15: m | K15: M | L15: 46.784 | M15: WIRE-LINE | N15: 12550 | O15: NULL | P15: NULL | Q15: 60550512550 | R15: 23.39 | S15: 45744.481 | T15: PA_SRDC | U15: 45744.251 | V15: PAUSER | W15: NULL | X15: 0 | Y15: 201,0,0 | Z15: NULL | AA15: 46.8 | AB15: NULL | AC15: UNDEFINED | AD15: UNDEFINED | AE15: AI | AF15: - | AG15: https://www.arcasupply.com/e27-7303/?srsltid=AfmBOor6FL2JUJCWR6beBKVWtuMh4c-5BwEaSyXlOWdR0cQ1Zajc6J8Q | AI15: MATERIAL | AJ15: =VLOOKUP(A15,'Classification Test Result'!$A$2:$D$2428,4,FALSE) -> #N/A | AK15: I can't find this item | AL15: =_xlfn.XLOOKUP($A15,Results!$A$2:$A$2256,Results!G$2:G$2256,"") -> 0 | AM15: =_xlfn.XLOOKUP($A15,Results!$A$2:$A$2256,Results!H$2:H$2256,"") -> 0 | AN15: =_xlfn.XLOOKUP($A15,Results!$A$2:$A$2256,Results!I$2:I$2256,"") -> 0 | AO15: =_xlfn.XLOOKUP($A15,Results!$A$2:$A$2256,Results!J$2:J$2256,"") -> 0 | AP15: =_xlfn.XLOOKUP($A15,Results!$A$2:$A$2256,Results!K$2:K$2256,"") -> 0 | AQ15: =_xlfn.XLOOKUP($A15,Results!$A$2:$A$2256,Results!L$2:L$2256,"") -> 0 | AR15: =_xlfn.XLOOKUP($A15,Results!$A$2:$A$2256,Results!M$2:M$2256,"") -> 0 | AS15: =_xlfn.XLOOKUP($A15,Results!$A$2:$A$2256,Results!N$2:N$2256,"") -> 0 | ... BE15: =_xlfn.XLOOKUP($A15,Results!$A$2:$A$2256,Results!Z$2:Z$2256,"") -> 0
A16: 905693 | B16: 281609 | C16: NULL | D16: S013772528.001 | E16: =VLOOKUP(F16,'RPA Vendor Data '!F11:$G$2418,2) -> VAN METER, INC. | F16: 13513 | G16: 1 | H16: WIRE-LINE 12550 1/2 STAPLE 500/BAG | I16: 500 | J16: m | K16: M | L16: 46.784 | M16: WIRE-LINE | N16: 12550 | O16: NULL | P16: NULL | Q16: 60550512550 | R16: 23.39 | S16: 45744.481 | T16: PA_SRDC | U16: 45744.253 | V16: PAUSER | W16: NULL | X16: 0 | Y16: 999 | Z16: NULL | AA16: NULL | AB16: NULL | AC16: UNDEFINED | AD16: UNDEFINED | AE16: AI | AF16: - | AG16: https://www.arcasupply.com/e27-7303/?srsltid=AfmBOor6FL2JUJCWR6beBKVWtuMh4c-5BwEaSyXlOWdR0cQ1Zajc6J8Q | AI16: MATERIAL | AJ16: =VLOOKUP(A16,'Classification Test Result'!$A$2:$D$2428,4,FALSE) -> #N/A | AK16: I can't find this item | AL16: =_xlfn.XLOOKUP($A16,Results!$A$2:$A$2256,Results!G$2:G$2256,"") -> 0 | AM16: =_xlfn.XLOOKUP($A16,Results!$A$2:$A$2256,Results!H$2:H$2256,"") -> 0 | AN16: =_xlfn.XLOOKUP($A16,Results!$A$2:$A$2256,Results!I$2:I$2256,"") -> 0 | AO16: =_xlfn.XLOOKUP($A16,Results!$A$2:$A$2256,Results!J$2:J$2256,"") -> 0 | AP16: =_xlfn.XLOOKUP($A16,Results!$A$2:$A$2256,Results!K$2:K$2256,"") -> 0 | AQ16: =_xlfn.XLOOKUP($A16,Results!$A$2:$A$2256,Results!L$2:L$2256,"") -> 0 | AR16: =_xlfn.XLOOKUP($A16,Results!$A$2:$A$2256,Results!M$2:M$2256,"") -> 0 | AS16: =_xlfn.XLOOKUP($A16,Results!$A$2:$A$2256,Results!N$2:N$2256,"") -> 0 | ... BE16: =_xlfn.XLOOKUP($A16,Results!$A$2:$A$2256,Results!Z$2:Z$2256,"") -> 0
A17: 905694 | B17: 281618 | C17: NULL | D17: S013772528.001 | E17: =VLOOKUP(F17,'RPA Vendor Data '!F12:$G$2418,2) -> VAN METER, INC. | F17: 13513 | G17: 1 | H17: WIRE-LINE 12550 1/2 STAPLE 500/BAG | I17: 500 | J17: m | K17: M | L17: 46.784 | M17: WIRE-LINE | N17: 12550 | O17: NULL | P17: NULL | Q17: 60550512550 | R17: 23.39 | S17: 45744.48 | T17: PA_SRDC | U17: 45744.263 | V17: PAUSER | W17: NULL | X17: 0 | Y17: 999 | Z17: NULL | AA17: NULL | AB17: NULL | AC17: UNDEFINED | AD17: UNDEFINED | AE17: AI | AF17: - | AG17: https://www.arcasupply.com/e27-7303/?srsltid=AfmBOor6FL2JUJCWR6beBKVWtuMh4c-5BwEaSyXlOWdR0cQ1Zajc6J8Q | AI17: MATERIAL | AJ17: =VLOOKUP(A17,'Classification Test Result'!$A$2:$D$2428,4,FALSE) -> #N/A | AK17: I can't find this item | AL17: =_xlfn.XLOOKUP($A17,Results!$A$2:$A$2256,Results!G$2:G$2256,"") -> 0 | AM17: =_xlfn.XLOOKUP($A17,Results!$A$2:$A$2256,Results!H$2:H$2256,"") -> 0 | AN17: =_xlfn.XLOOKUP($A17,Results!$A$2:$A$2256,Results!I$2:I$2256,"") -> 0 | AO17: =_xlfn.XLOOKUP($A17,Results!$A$2:$A$2256,Results!J$2:J$2256,"") -> 0 | AP17: =_xlfn.XLOOKUP($A17,Results!$A$2:$A$2256,Results!K$2:K$2256,"") -> 0 | AQ17: =_xlfn.XLOOKUP($A17,Results!$A$2:$A$2256,Results!L$2:L$2256,"") -> 0 | AR17: =_xlfn.XLOOKUP($A17,Results!$A$2:$A$2256,Results!M$2:M$2256,"") -> 0 | AS17: =_xlfn.XLOOKUP($A17,Results!$A$2:$A$2256,Results!N$2:N$2256,"") -> 0 | ... BE17: =_xlfn.XLOOKUP($A17,Results!$A$2:$A$2256,Results!Z$2:Z$2256,"") -> 0
A18: 905695 | B18: 282041 | C18: NULL | D18: S6404142.001 | E18: =VLOOKUP(F18,'RPA Vendor Data '!F13:$G$2418,2) -> EDGES ELECTRICAL GROUP | F18: 16768 | G18: 1 | H18: WIRE THHN4-GRY-STR-CU CUT | I18: 115 | J18: M | K18: M | L18: 1190 | M18: GENERIC WIRE | N18: THHN-4-STR19-GRY-CU | O18: NULL | P18: NULL | Q18: NULL | R18: 136.85 | S18: 45744.938 | T18: PA_SRDC | U18: 45744.71 | V18: PAUSER | W18: NULL | X18: 0 | Y18: 201 | Z18: NULL | AA18: NULL | AB18: NULL | AC18: GENERIC WIRE | AD18: GENERIC WIRE | AE18: AI | AF18: 26121614 | AG18: https://www.edgesgroup.com/buy/product/wire-thhn4-gry-str-cu-cut/1793558 | AI18: MATERIAL | AJ18: =VLOOKUP(A18,'Classification Test Result'!$A$2:$D$2428,4,FALSE) -> #N/A | AK18: No specified Wire manufcaturer | AL18: =_xlfn.XLOOKUP($A18,Results!$A$2:$A$2256,Results!G$2:G$2256,"") -> 0 | AM18: =_xlfn.XLOOKUP($A18,Results!$A$2:$A$2256,Results!H$2:H$2256,"") -> 0 | AN18: =_xlfn.XLOOKUP($A18,Results!$A$2:$A$2256,Results!I$2:I$2256,"") -> 0 | AO18: =_xlfn.XLOOKUP($A18,Results!$A$2:$A$2256,Results!J$2:J$2256,"") -> 0 | AP18: =_xlfn.XLOOKUP($A18,Results!$A$2:$A$2256,Results!K$2:K$2256,"") -> 0 | AQ18: =_xlfn.XLOOKUP($A18,Results!$A$2:$A$2256,Results!L$2:L$2256,"") -> 0 | AR18: =_xlfn.XLOOKUP($A18,Results!$A$2:$A$2256,Results!M$2:M$2256,"") -> 0 | AS18: =_xlfn.XLOOKUP($A18,Results!$A$2:$A$2256,Results!N$2:N$2256,"") -> 0 | ... BE18: =_xlfn.XLOOKUP($A18,Results!$A$2:$A$2256,Results!Z$2:Z$2256,"") -> TRUE
A19: 905696 | B19: 281779 | C19: NULL | D19: S103407780.001 | E19: =VLOOKUP(F19,'RPA Vendor Data '!F14:$G$2418,2) -> LOEB ELECTRIC | F19: 12062 | G19: 1 | H19: WIRE BARE-SD-6-SOL-CU-5000MSTR Cuts: 5 @ 1000 ft | I19: 5000 | J19: m | K19: M | L19: 696.374 | M19: GENERIC WIRE | N19: BARE-CU-SD-6-SOL-CUT REEL | O19: NULL | P19: NULL | Q19: NULL | R19: 3481.87 | S19: 45744.565 | T19: PA_SRDC | U19: 45744.35 | V19: PAUSER | W19: NULL | X19: 0 | Y19: 999 | Z19: NULL | AA19: NULL | AB19: NULL | AC19: GENERIC WIRE | AD19: GENERIC WIRE | AE19: AI | AF19: 26121645 | AG19: https://www.graybar.com/bare-copper-wire-cut-reel-copper-solid-6-awg/p/22061327 | AI19: MATERIAL | AJ19: =VLOOKUP(A19,'Classification Test Result'!$A$2:$D$2428,4,FALSE) -> #N/A | AL19: =_xlfn.XLOOKUP($A19,Results!$A$2:$A$2256,Results!G$2:G$2256,"") -> 0 | AM19: =_xlfn.XLOOKUP($A19,Results!$A$2:$A$2256,Results!H$2:H$2256,"") -> 0 | AN19: =_xlfn.XLOOKUP($A19,Results!$A$2:$A$2256,Results!I$2:I$2256,"") -> 0 | AO19: =_xlfn.XLOOKUP($A19,Results!$A$2:$A$2256,Results!J$2:J$2256,"") -> 0 | AP19: =_xlfn.XLOOKUP($A19,Results!$A$2:$A$2256,Results!K$2:K$2256,"") -> 0 | AQ19: =_xlfn.XLOOKUP($A19,Results!$A$2:$A$2256,Results!L$2:L$2256,"") -> 0 | AR19: =_xlfn.XLOOKUP($A19,Results!$A$2:$A$2256,Results!M$2:M$2256,"") -> 0 | AS19: =_xlfn.XLOOKUP($A19,Results!$A$2:$A$2256,Results!N$2:N$2256,"") -> 0 | ... BE19: =_xlfn.XLOOKUP($A19,Results!$A$2:$A$2256,Results!Z$2:Z$2256,"") -> TRUE
A20: 905697 | B20: 281986 | C20: NULL | D20: S4743676.001 | E20: =VLOOKUP(F20,'RPA Vendor Data '!F17:$G$2418,2) -> FROST ELECTRIC SUPPLY CO | F20: 11364 | G20: 3 | H20: Wire 8 AWG Yellow THHN Stranded 500 Foot Reel 600 Volt Copper Wire | I20: 500 | J20: M | K20: M | L20: 547.2 | M20: GENERIC WIRE | N20: THHN-8-STR19-YEL-CU-500S/R | O20: NULL | P20: AK10439071 | Q20: 98010023125 | R20: 273.6 | S20: 45744.897 | T20: PA_SRDC | U20: 45744.667 | V20: PAUSER | W20: NULL | X20: 0 | Y20: 201,0,0 | Z20: NULL | AA20: 547.2 | AB20: NULL | AC20: GENERIC WIRE | AD20: GENERIC WIRE | AE20: AI | AF20: - | AG20: https://www.frostelectric.com/buy/product/wire-8/625880?text=Wire+8+AWG+Yellow+THHN+Stranded+500+Foot+Reel+600+Volt+Copper+Wire | AI20: MATERIAL | AJ20: =VLOOKUP(A20,'Classification Test Result'!$A$2:$D$2428,4,FALSE) -> #N/A | AL20: =_xlfn.XLOOKUP($A20,Results!$A$2:$A$2256,Results!G$2:G$2256,"") -> 0 | AM20: =_xlfn.XLOOKUP($A20,Results!$A$2:$A$2256,Results!H$2:H$2256,"") -> 0 | AN20: =_xlfn.XLOOKUP($A20,Results!$A$2:$A$2256,Results!I$2:I$2256,"") -> 0 | AO20: =_xlfn.XLOOKUP($A20,Results!$A$2:$A$2256,Results!J$2:J$2256,"") -> 0 | AP20: =_xlfn.XLOOKUP($A20,Results!$A$2:$A$2256,Results!K$2:K$2256,"") -> 0 | AQ20: =_xlfn.XLOOKUP($A20,Results!$A$2:$A$2256,Results!L$2:L$2256,"") -> 0 | AR20: =_xlfn.XLOOKUP($A20,Results!$A$2:$A$2256,Results!M$2:M$2256,"") -> 0 | AS20: =_xlfn.XLOOKUP($A20,Results!$A$2:$A$2256,Results!N$2:N$2256,"") -> 0 | ... BE20: =_xlfn.XLOOKUP($A20,Results!$A$2:$A$2256,Results!Z$2:Z$2256,"") -> 0
A21: 905698 | B21: 281986 | C21: NULL | D21: S4743676.001 | E21: =VLOOKUP(F21,'RPA Vendor Data '!F18:$G$2418,2) -> FROST ELECTRIC SUPPLY CO | F21: 11364 | G21: 2 | H21: Wire 8 AWG Orange THHN Stranded 500 Foot Reel 600 Volt Copper Wire | I21: 500 | J21: M | K21: M | L21: 547.2 | M21: GENERIC WIRE | N21: THHN-8-STR19-ORN-CU-500S/R | O21: NULL | P21: AK10439058 | Q21: 98010023145 | R21: 273.6 | S21: 45744.897 | T21: PA_SRDC | U21: 45744.667 | V21: PAUSER | W21: NULL | X21: 0 | Y21: 201,0,0 | Z21: NULL | AA21: 547.2 | AB21: NULL | AC21: GENERIC WIRE | AD21: GENERIC WIRE | AE21: AI | AF21: - | AG21: https://www.frostelectric.com/buy/product/wire-8/625872?text=Wire+8+AWG+Orange+THHN+Stranded+500+Foot+Reel+600+Volt+Copper+Wire | AI21: MATERIAL | AJ21: =VLOOKUP(A21,'Classification Test Result'!$A$2:$D$2428,4,FALSE) -> #N/A | AL21: =_xlfn.XLOOKUP($A21,Results!$A$2:$A$2256,Results!G$2:G$2256,"") -> 0 | AM21: =_xlfn.XLOOKUP($A21,Results!$A$2:$A$2256,Results!H$2:H$2256,"") -> 0 | AN21: =_xlfn.XLOOKUP($A21,Results!$A$2:$A$2256,Results!I$2:I$2256,"") -> 0 | AO21: =_xlfn.XLOOKUP($A21,Results!$A$2:$A$2256,Results!J$2:J$2256,"") -> 0 | AP21: =_xlfn.XLOOKUP($A21,Results!$A$2:$A$2256,Results!K$2:K$2256,"") -> 0 | AQ21: =_xlfn.XLOOKUP($A21,Results!$A$2:$A$2256,Results!L$2:L$2256,"") -> 0 | AR21: =_xlfn.XLOOKUP($A21,Results!$A$2:$A$2256,Results!M$2:M$2256,"") -> 0 | AS21: =_xlfn.XLOOKUP($A21,Results!$A$2:$A$2256,Results!N$2:N$2256,"") -> 0 | ... BE21: =_xlfn.XLOOKUP($A21,Results!$A$2:$A$2256,Results!Z$2:Z$2256,"") -> 0
A22: 905699 | B22: 281986 | C22: NULL | D22: S4743676.001 | E22: =VLOOKUP(F22,'RPA Vendor Data '!F19:$G$2418,2) -> FROST ELECTRIC SUPPLY CO | F22: 11364 | G22: 1 | H22: Wire 8 AWG Brown THHN Stranded 500 Foot Reel 600 Volt Copper Wire | I22: 500 | J22: M | K22: M | L22: 547.2 | M22: GENERIC WIRE | N22: THHN-8-STR19-BRN-CU-500S/R | O22: NULL | P22: AK10439049 | Q22: 98010023115 | R22: 273.6 | S22: 45744.897 | T22: PA_SRDC | U22: 45744.667 | V22: PAUSER | W22: NULL | X22: 0 | Y22: 201,0,0 | Z22: NULL | AA22: 547.2 | AB22: NULL | AC22: GENERIC WIRE | AD22: GENERIC WIRE | AE22: AI | AF22: - | AG22: https://www.frostelectric.com/buy/product/wire-8/369661?text=Wire+8+AWG+Brown+THHN+Stranded+500+Foot+Reel+600+Volt+Copper+Wire | AI22: MATERIAL | AJ22: =VLOOKUP(A22,'Classification Test Result'!$A$2:$D$2428,4,FALSE) -> #N/A | AL22: =_xlfn.XLOOKUP($A22,Results!$A$2:$A$2256,Results!G$2:G$2256,"") -> 0 | AM22: =_xlfn.XLOOKUP($A22,Results!$A$2:$A$2256,Results!H$2:H$2256,"") -> 0 | AN22: =_xlfn.XLOOKUP($A22,Results!$A$2:$A$2256,Results!I$2:I$2256,"") -> 0 | AO22: =_xlfn.XLOOKUP($A22,Results!$A$2:$A$2256,Results!J$2:J$2256,"") -> 0 | AP22: =_xlfn.XLOOKUP($A22,Results!$A$2:$A$2256,Results!K$2:K$2256,"") -> 0 | AQ22: =_xlfn.XLOOKUP($A22,Results!$A$2:$A$2256,Results!L$2:L$2256,"") -> 0 | AR22: =_xlfn.XLOOKUP($A22,Results!$A$2:$A$2256,Results!M$2:M$2256,"") -> 0 | AS22: =_xlfn.XLOOKUP($A22,Results!$A$2:$A$2256,Results!N$2:N$2256,"") -> 0 | ... BE22: =_xlfn.XLOOKUP($A22,Results!$A$2:$A$2256,Results!Z$2:Z$2256,"") -> TRUE
A23: 905700 | B23: 281962 | C23: NULL | D23: S4742832.001 | E23: =VLOOKUP(F23,'RPA Vendor Data '!F20:$G$2418,2) -> FROST ELECTRIC SUPPLY CO | F23: 11364 | G23: 1 | H23: Wire 12 AWG White THHN Stranded 500 Foot Reel 600 Volt Copper Wire | I23: 1000 | J23: M | K23: M | L23: 175.98 | M23: GENERIC WIRE | N23: THHN-12-STR19-WHT-CU-500S/R | O23: NULL | P23: NULL | Q23: NULL | R23: 175.98 | S23: 45744.876 | T23: PA_SRDC | U23: 45744.662 | V23: PAUSER | W23: NULL | X23: 0 | Y23: 201 | Z23: NULL | AA23: NULL | AB23: NULL | AC23: GENERIC WIRE | AD23: GENERIC WIRE | AE23: AI | AF23: - | AG23: https://www.frostelectric.com/buy/product/wire-12/12001?text=Wire+12+AWG+White+THHN+Stranded+500+Foot+Reel+600+Volt+Copper+Wire | AI23: MATERIAL | AJ23: =VLOOKUP(A23,'Classification Test Result'!$A$2:$D$2428,4,FALSE) -> #N/A | AL23: =_xlfn.XLOOKUP($A23,Results!$A$2:$A$2256,Results!G$2:G$2256,"") -> 0 | AM23: =_xlfn.XLOOKUP($A23,Results!$A$2:$A$2256,Results!H$2:H$2256,"") -> 0 | AN23: =_xlfn.XLOOKUP($A23,Results!$A$2:$A$2256,Results!I$2:I$2256,"") -> 0 | AO23: =_xlfn.XLOOKUP($A23,Results!$A$2:$A$2256,Results!J$2:J$2256,"") -> 0 | AP23: =_xlfn.XLOOKUP($A23,Results!$A$2:$A$2256,Results!K$2:K$2256,"") -> 0 | AQ23: =_xlfn.XLOOKUP($A23,Results!$A$2:$A$2256,Results!L$2:L$2256,"") -> 0 | AR23: =_xlfn.XLOOKUP($A23,Results!$A$2:$A$2256,Results!M$2:M$2256,"") -> 0 | AS23: =_xlfn.XLOOKUP($A23,Results!$A$2:$A$2256,Results!N$2:N$2256,"") -> 0 | ... BE23: =_xlfn.XLOOKUP($A23,Results!$A$2:$A$2256,Results!Z$2:Z$2256,"") -> 0
A24: 905701 | B24: 281670 | C24: NULL | D24: S4741948.001 | E24: =VLOOKUP(F24,'RPA Vendor Data '!F21:$G$2418,2) -> FROST ELECTRIC SUPPLY CO | F24: 11364 | G24: 4 | H24: Wire 12 AWG White THHN Stranded 500 Foot Reel 600 Volt Copper Wire | I24: 1000 | J24: M | K24: M | L24: 175.98 | M24: GENERIC WIRE | N24: THHN-12-STR19-WHT-CU-500S/R | O24: NULL | P24: AK10438370 | Q24: 98010022910 | R24: 175.98 | S24: 45744.501 | T24: PA_SRDC | U24: 45744.287 | V24: PAUSER | W24: NULL | X24: 4 | Y24: 201,0,0 | Z24: NULL | AA24: 175.98 | AB24: NULL | AC24: GENERIC WIRE | AD24: GENERIC WIRE | AE24: AI | AF24: - | AG24: https://www.frostelectric.com/buy/product/wire-12/12001?text=Wire+12+AWG+White+THHN+Stranded+500+Foot+Reel+600+Volt+Copper+Wire | AI24: MATERIAL | AJ24: =VLOOKUP(A24,'Classification Test Result'!$A$2:$D$2428,4,FALSE) -> #N/A | AL24: =_xlfn.XLOOKUP($A24,Results!$A$2:$A$2256,Results!G$2:G$2256,"") -> 0 | AM24: =_xlfn.XLOOKUP($A24,Results!$A$2:$A$2256,Results!H$2:H$2256,"") -> 0 | AN24: =_xlfn.XLOOKUP($A24,Results!$A$2:$A$2256,Results!I$2:I$2256,"") -> 0 | AO24: =_xlfn.XLOOKUP($A24,Results!$A$2:$A$2256,Results!J$2:J$2256,"") -> 0 | AP24: =_xlfn.XLOOKUP($A24,Results!$A$2:$A$2256,Results!K$2:K$2256,"") -> 0 | AQ24: =_xlfn.XLOOKUP($A24,Results!$A$2:$A$2256,Results!L$2:L$2256,"") -> 0 | AR24: =_xlfn.XLOOKUP($A24,Results!$A$2:$A$2256,Results!M$2:M$2256,"") -> 0 | AS24: =_xlfn.XLOOKUP($A24,Results!$A$2:$A$2256,Results!N$2:N$2256,"") -> 0 | ... BE24: =_xlfn.XLOOKUP($A24,Results!$A$2:$A$2256,Results!Z$2:Z$2256,"") -> 0
A25: 905702 | B25: 281962 | C25: NULL | D25: S4742832.001 | E25: =VLOOKUP(F25,'RPA Vendor Data '!F22:$G$2418,2) -> FROST ELECTRIC SUPPLY CO | F25: 11364 | G25: 2 | H25: Wire 12 AWG Green THHN Stranded 500 Foot Reel 600 Volt Copper Wire | I25: 500 | J25: M | K25: M | L25: 175.98 | M25: GENERIC WIRE | N25: THHN-12-STR19-GRN-CU-500S/R | O25: NULL | P25: AK10438370 | Q25: 98010022910 | R25: 87.99 | S25: 45744.876 | T25: PA_SRDC | U25: 45744.662 | V25: PAUSER | W25: NULL | X25: 0 | Y25: 201 | Z25: NULL | AA25: NULL | AB25: NULL | AC25: GENERIC WIRE | AD25: GENERIC WIRE | AE25: AI | AF25: - | AG25: https://www.frostelectric.com/buy/product/wire-12/11990?text=Wire+12+AWG+Green+THHN+Stranded+500+Foot+Reel+600+Volt+Copper+Wire | AI25: MATERIAL | AJ25: =VLOOKUP(A25,'Classification Test Result'!$A$2:$D$2428,4,FALSE) -> #N/A | AL25: =_xlfn.XLOOKUP($A25,Results!$A$2:$A$2256,Results!G$2:G$2256,"") -> 0 | AM25: =_xlfn.XLOOKUP($A25,Results!$A$2:$A$2256,Results!H$2:H$2256,"") -> 0 | AN25: =_xlfn.XLOOKUP($A25,Results!$A$2:$A$2256,Results!I$2:I$2256,"") -> 0 | AO25: =_xlfn.XLOOKUP($A25,Results!$A$2:$A$2256,Results!J$2:J$2256,"") -> 0 | AP25: =_xlfn.XLOOKUP($A25,Results!$A$2:$A$2256,Results!K$2:K$2256,"") -> 0 | AQ25: =_xlfn.XLOOKUP($A25,Results!$A$2:$A$2256,Results!L$2:L$2256,"") -> 0 | AR25: =_xlfn.XLOOKUP($A25,Results!$A$2:$A$2256,Results!M$2:M$2256,"") -> 0 | AS25: =_xlfn.XLOOKUP($A25,Results!$A$2:$A$2256,Results!N$2:N$2256,"") -> 0 | ... BE25: =_xlfn.XLOOKUP($A25,Results!$A$2:$A$2256,Results!Z$2:Z$2256,"") -> 0
A26: 905703 | B26: 281670 | C26: NULL | D26: S4741948.001 | E26: =VLOOKUP(F26,'RPA Vendor Data '!F23:$G$2418,2) -> FROST ELECTRIC SUPPLY CO | F26: 11364 | G26: 3 | H26: Wire 12 AWG Green THHN Stranded 500 Foot Reel 600 Volt Copper Wire | I26: 1000 | J26: M | K26: M | L26: 175.98 | M26: GENERIC WIRE | N26: THHN-12-STR19-GRN-CU-500S/R | O26: NULL | P26: AK10438354 | Q26: 98010022940 | R26: 175.98 | S26: 45744.501 | T26: PA_SRDC | U26: 45744.287 | V26: PAUSER | W26: NULL | X26: 3 | Y26: 201,0,0 | Z26: NULL | AA26: 175.98 | AB26: NULL | AC26: GENERIC WIRE | AD26: GENERIC WIRE | AE26: AI | AF26: - | AG26: https://www.frostelectric.com/buy/product/wire-12/11990?text=Wire+12+AWG+Green+THHN+Stranded+500+Foot+Reel+600+Volt+Copper+Wire | AI26: MATERIAL | AJ26: =VLOOKUP(A26,'Classification Test Result'!$A$2:$D$2428,4,FALSE) -> #N/A | AL26: =_xlfn.XLOOKUP($A26,Results!$A$2:$A$2256,Results!G$2:G$2256,"") -> 0 | AM26: =_xlfn.XLOOKUP($A26,Results!$A$2:$A$2256,Results!H$2:H$2256,"") -> 0 | AN26: =_xlfn.XLOOKUP($A26,Results!$A$2:$A$2256,Results!I$2:I$2256,"") -> 0 | AO26: =_xlfn.XLOOKUP($A26,Results!$A$2:$A$2256,Results!J$2:J$2256,"") -> 0 | AP26: =_xlfn.XLOOKUP($A26,Results!$A$2:$A$2256,Results!K$2:K$2256,"") -> 0 | AQ26: =_xlfn.XLOOKUP($A26,Results!$A$2:$A$2256,Results!L$2:L$2256,"") -> 0 | AR26: =_xlfn.XLOOKUP($A26,Results!$A$2:$A$2256,Results!M$2:M$2256,"") -> 0 | AS26: =_xlfn.XLOOKUP($A26,Results!$A$2:$A$2256,Results!N$2:N$2256,"") -> 0 | ... BE26: =_xlfn.XLOOKUP($A26,Results!$A$2:$A$2256,Results!Z$2:Z$2256,"") -> 0
A27: 905704 | B27: 281670 | C27: NULL | D27: S4741948.001 | E27: =VLOOKUP(F27,'RPA Vendor Data '!F24:$G$2418,2) -> FROST ELECTRIC SUPPLY CO | F27: 11364 | G27: 5 | H27: Wire 12 AWG Blue THHN Stranded 500 Foot Reel 600 Volt Copper Wire | I27: 1000 | J27: M | K27: M | L27: 175.98 | M27: GENERIC WIRE | N27: THHN-12-STR19-BLU-CU-500S/R | O27: NULL | P27: AK10438350 | Q27: 98010022930 | R27: 175.98 | S27: 45744.501 | T27: PA_SRDC | U27: 45744.287 | V27: PAUSER | W27: NULL | X27: 5 | Y27: 201,0,0 | Z27: NULL | AA27: 175.98 | AB27: NULL | AC27: GENERIC WIRE | AD27: GENERIC WIRE | AE27: AI | AF27: - | AG27: https://www.frostelectric.com/buy/product/wire-12/11986?text=Wire+12+AWG+Blue+THHN+Stranded+500+Foot+Reel+600+Volt+Copper+Wire | AI27: MATERIAL | AJ27: =VLOOKUP(A27,'Classification Test Result'!$A$2:$D$2428,4,FALSE) -> #N/A | AL27: =_xlfn.XLOOKUP($A27,Results!$A$2:$A$2256,Results!G$2:G$2256,"") -> 0 | AM27: =_xlfn.XLOOKUP($A27,Results!$A$2:$A$2256,Results!H$2:H$2256,"") -> 0 | AN27: =_xlfn.XLOOKUP($A27,Results!$A$2:$A$2256,Results!I$2:I$2256,"") -> 0 | AO27: =_xlfn.XLOOKUP($A27,Results!$A$2:$A$2256,Results!J$2:J$2256,"") -> 0 | AP27: =_xlfn.XLOOKUP($A27,Results!$A$2:$A$2256,Results!K$2:K$2256,"") -> 0 | AQ27: =_xlfn.XLOOKUP($A27,Results!$A$2:$A$2256,Results!L$2:L$2256,"") -> 0 | AR27: =_xlfn.XLOOKUP($A27,Results!$A$2:$A$2256,Results!M$2:M$2256,"") -> 0 | AS27: =_xlfn.XLOOKUP($A27,Results!$A$2:$A$2256,Results!N$2:N$2256,"") -> 0 | ... BE27: =_xlfn.XLOOKUP($A27,Results!$A$2:$A$2256,Results!Z$2:Z$2256,"") -> TRUE
A28: 905705 | B28: 281670 | C28: NULL | D28: S4741948.001 | E28: =VLOOKUP(F28,'RPA Vendor Data '!F25:$G$2418,2) -> FROST ELECTRIC SUPPLY CO | F28: 11364 | G28: 2 | H28: Wire 12 AWG Black THHN Stranded 500 Foot Reel 600 Volt Copper Wire | I28: 1000 | J28: M | K28: M | L28: 175.98 | M28: GENERIC WIRE | N28: THHN-12-STR19-BLK-CU-500S/R | O28: NULL | P28: AK10438348 | Q28: 98010022900 | R28: 175.98 | S28: 45744.501 | T28: PA_SRDC | U28: 45744.287 | V28: PAUSER | W28: NULL | X28: 2 | Y28: 201,0,0 | Z28: NULL | AA28: 175.98 | AB28: NULL | AC28: GENERIC WIRE | AD28: GENERIC WIRE | AE28: AI | AF28: - | AG28: https://www.frostelectric.com/buy/product/wire-12/11984?text=Wire+12+AWG+Black+THHN+Stranded+500+Foot+Reel+600+Volt+Copper+Wire | AI28: MATERIAL | AJ28: =VLOOKUP(A28,'Classification Test Result'!$A$2:$D$2428,4,FALSE) -> #N/A | AL28: =_xlfn.XLOOKUP($A28,Results!$A$2:$A$2256,Results!G$2:G$2256,"") -> 0 | AM28: =_xlfn.XLOOKUP($A28,Results!$A$2:$A$2256,Results!H$2:H$2256,"") -> 0 | AN28: =_xlfn.XLOOKUP($A28,Results!$A$2:$A$2256,Results!I$2:I$2256,"") -> 0 | AO28: =_xlfn.XLOOKUP($A28,Results!$A$2:$A$2256,Results!J$2:J$2256,"") -> 0 | AP28: =_xlfn.XLOOKUP($A28,Results!$A$2:$A$2256,Results!K$2:K$2256,"") -> 0 | AQ28: =_xlfn.XLOOKUP($A28,Results!$A$2:$A$2256,Results!L$2:L$2256,"") -> 0 | AR28: =_xlfn.XLOOKUP($A28,Results!$A$2:$A$2256,Results!M$2:M$2256,"") -> 0 | AS28: =_xlfn.XLOOKUP($A28,Results!$A$2:$A$2256,Results!N$2:N$2256,"") -> 0 | ... BE28: =_xlfn.XLOOKUP($A28,Results!$A$2:$A$2256,Results!Z$2:Z$2256,"") -> 0
A29: 905706 | B29: 281986 | C29: NULL | D29: S4743676.001 | E29: =VLOOKUP(F29,'RPA Vendor Data '!F26:$G$2418,2) -> FROST ELECTRIC SUPPLY CO | F29: 11364 | G29: 4 | H29: Wire 10 AWG Green THHN Stranded 500 Foot Reel 600 Volt Copper Wire | I29: 500 | J29: M | K29: M | L29: 295.52 | M29: GENERIC WIRE | N29: THHN-10-STR19-GRN-CU-500S/R | O29: NULL | P29: AK10438157 | Q29: 98010023040 | R29: 147.76 | S29: 45744.897 | T29: PA_SRDC | U29: 45744.667 | V29: PAUSER | W29: NULL | X29: 0 | Y29: 201,0,0 | Z29: NULL | AA29: 295.52 | AB29: NULL | AC29: GENERIC WIRE | AD29: GENERIC WIRE | AE29: AI | AF29: - | AG29: https://www.frostelectric.com/buy/product/wire-10/11950?text=Wire+10+AWG+Green+THHN+Stranded+500+Foot+Reel+600+Volt+Copper+Wire | AI29: MATERIAL | AJ29: =VLOOKUP(A29,'Classification Test Result'!$A$2:$D$2428,4,FALSE) -> #N/A | AL29: =_xlfn.XLOOKUP($A29,Results!$A$2:$A$2256,Results!G$2:G$2256,"") -> 0 | AM29: =_xlfn.XLOOKUP($A29,Results!$A$2:$A$2256,Results!H$2:H$2256,"") -> 0 | AN29: =_xlfn.XLOOKUP($A29,Results!$A$2:$A$2256,Results!I$2:I$2256,"") -> 0 | AO29: =_xlfn.XLOOKUP($A29,Results!$A$2:$A$2256,Results!J$2:J$2256,"") -> 0 | AP29: =_xlfn.XLOOKUP($A29,Results!$A$2:$A$2256,Results!K$2:K$2256,"") -> 0 | AQ29: =_xlfn.XLOOKUP($A29,Results!$A$2:$A$2256,Results!L$2:L$2256,"") -> 0 | AR29: =_xlfn.XLOOKUP($A29,Results!$A$2:$A$2256,Results!M$2:M$2256,"") -> 0 | AS29: =_xlfn.XLOOKUP($A29,Results!$A$2:$A$2256,Results!N$2:N$2256,"") -> 0 | ... BE29: =_xlfn.XLOOKUP($A29,Results!$A$2:$A$2256,Results!Z$2:Z$2256,"") -> 0
A30: 905707 | B30: 281967 | C30: NULL | D30: S4743296.001 | E30: =VLOOKUP(F30,'RPA Vendor Data '!F27:$G$2418,2) -> FROST ELECTRIC SUPPLY CO | F30: 11364 | G30: 3 | H30: Wire 10 AWG Green THHN Stranded 500 Foot Reel 600 Volt Copper Wire | I30: 500 | J30: M | K30: M | L30: 295.52 | M30: GENERIC WIRE | N30: THHN-10-STR19-GRN-CU-500S/R | O30: NULL | P30: AK10438157 | Q30: 98010023040 | R30: 147.76 | S30: 45744.876 | T30: PA_SRDC | U30: 45744.662 | V30: PAUSER | W30: NULL | X30: 0 | Y30: 201 | Z30: NULL | AA30: NULL | AB30: NULL | AC30: GENERIC WIRE | AD30: GENERIC WIRE | AE30: AI | AF30: - | AG30: https://www.frostelectric.com/buy/product/wire-10/11950?text=Wire+10+AWG+Green+THHN+Stranded+500+Foot+Reel+600+Volt+Copper+Wire | AI30: MATERIAL | AJ30: =VLOOKUP(A30,'Classification Test Result'!$A$2:$D$2428,4,FALSE) -> #N/A | AL30: =_xlfn.XLOOKUP($A30,Results!$A$2:$A$2256,Results!G$2:G$2256,"") -> 0 | AM30: =_xlfn.XLOOKUP($A30,Results!$A$2:$A$2256,Results!H$2:H$2256,"") -> 0 | AN30: =_xlfn.XLOOKUP($A30,Results!$A$2:$A$2256,Results!I$2:I$2256,"") -> 0 | AO30: =_xlfn.XLOOKUP($A30,Results!$A$2:$A$2256,Results!J$2:J$2256,"") -> 0 | AP30: =_xlfn.XLOOKUP($A30,Results!$A$2:$A$2256,Results!K$2:K$2256,"") -> 0 | AQ30: =_xlfn.XLOOKUP($A30,Results!$A$2:$A$2256,Results!L$2:L$2256,"") -> 0 | AR30: =_xlfn.XLOOKUP($A30,Results!$A$2:$A$2256,Results!M$2:M$2256,"") -> 0 | AS30: =_xlfn.XLOOKUP($A30,Results!$A$2:$A$2256,Results!N$2:N$2256,"") -> 0 | ... BE30: =_xlfn.XLOOKUP($A30,Results!$A$2:$A$2256,Results!Z$2:Z$2256,"") -> 0
A31: 905708 | B31: 281966 | C31: NULL | D31: S4743353.001 | E31: =VLOOKUP(F31,'RPA Vendor Data '!F28:$G$2418,2) -> FROST ELECTRIC SUPPLY CO | F31: 11364 | G31: 2 | H31: Wire 10 AWG Blue THHN Stranded 500 Foot Reel 600 Volt Copper Wire | I31: 500 | J31: M | K31: M | L31: 295.52 | M31: GENERIC WIRE | N31: THHN-10-STR19-BLU-CU-500S/R | O31: NULL | P31: AK10438148 | Q31: 98010023030 | R31: 147.76 | S31: 45744.876 | T31: PA_SRDC | U31: 45744.662 | V31: PAUSER | W31: NULL | X31: 2 | Y31: 201,0,0 | Z31: NULL | AA31: 295.52 | AB31: NULL | AC31: GENERIC WIRE | AD31: GENERIC WIRE | AE31: AI | AF31: - | AG31: https://www.frostelectric.com/buy/product/wire-10/11946?text=Wire+10+AWG+Blue+THHN+Stranded+500+Foot+Reel+600+Volt+Copper+Wire | AI31: MATERIAL | AJ31: =VLOOKUP(A31,'Classification Test Result'!$A$2:$D$2428,4,FALSE) -> #N/A | AL31: =_xlfn.XLOOKUP($A31,Results!$A$2:$A$2256,Results!G$2:G$2256,"") -> 0 | AM31: =_xlfn.XLOOKUP($A31,Results!$A$2:$A$2256,Results!H$2:H$2256,"") -> 0 | AN31: =_xlfn.XLOOKUP($A31,Results!$A$2:$A$2256,Results!I$2:I$2256,"") -> 0 | AO31: =_xlfn.XLOOKUP($A31,Results!$A$2:$A$2256,Results!J$2:J$2256,"") -> 0 | AP31: =_xlfn.XLOOKUP($A31,Results!$A$2:$A$2256,Results!K$2:K$2256,"") -> 0 | AQ31: =_xlfn.XLOOKUP($A31,Results!$A$2:$A$2256,Results!L$2:L$2256,"") -> 0 | AR31: =_xlfn.XLOOKUP($A31,Results!$A$2:$A$2256,Results!M$2:M$2256,"") -> 0 | AS31: =_xlfn.XLOOKUP($A31,Results!$A$2:$A$2256,Results!N$2:N$2256,"") -> 0 | ... BE31: =_xlfn.XLOOKUP($A31,Results!$A$2:$A$2256,Results!Z$2:Z$2256,"") -> 0
A32: 905709 | B32: 281428 | C32: NULL | D32: S142052017.001 | E32: =VLOOKUP(F32,'RPA Vendor Data '!F29:$G$2418,2) -> REXEL USA, INC. | F32: 12873 | G32: 1 | H32: WIR FPBTCBK 234591 FLOORPORT FLANGED BLANK TOP BK | I32: 1 | J32: EA | K32: E | L32: 119.098 | M32: WIREMOLD | N32: FPBTCBK | O32: 234591 | P32: AK10565407 | Q32: 78677615201 | R32: 119.1 | S32: 45744.292 | T32: PA_SRDC | U32: 45744.063 | V32: PAUSER | W32: NULL | X32: 1 | Y32: 0,0,0 | Z32: 119.098 | AA32: 119.098 | AB32: 195 | AC32: WIREMOLD | AD32: WIREMOLD | AE32: AI | AF32: - | AG32: https://www.rexelusa.com/p/234591/wiremold/blank-flanged-cover-assembly-black-die-cast-aluminum/786776152012/fpbtcbk | AI32: MATERIAL | AJ32: =VLOOKUP(A32,'Classification Test Result'!$A$2:$D$2428,4,FALSE) -> #N/A | AL32: =_xlfn.XLOOKUP($A32,Results!$A$2:$A$2256,Results!G$2:G$2256,"") -> 0 | AM32: =_xlfn.XLOOKUP($A32,Results!$A$2:$A$2256,Results!H$2:H$2256,"") -> 0 | AN32: =_xlfn.XLOOKUP($A32,Results!$A$2:$A$2256,Results!I$2:I$2256,"") -> 0 | AO32: =_xlfn.XLOOKUP($A32,Results!$A$2:$A$2256,Results!J$2:J$2256,"") -> 0 | AP32: =_xlfn.XLOOKUP($A32,Results!$A$2:$A$2256,Results!K$2:K$2256,"") -> 0 | AQ32: =_xlfn.XLOOKUP($A32,Results!$A$2:$A$2256,Results!L$2:L$2256,"") -> 0 | AR32: =_xlfn.XLOOKUP($A32,Results!$A$2:$A$2256,Results!M$2:M$2256,"") -> 0 | AS32: =_xlfn.XLOOKUP($A32,Results!$A$2:$A$2256,Results!N$2:N$2256,"") -> 0 | ... BE32: =_xlfn.XLOOKUP($A32,Results!$A$2:$A$2256,Results!Z$2:Z$2256,"") -> 0
A33: 905710 | B33: 281742 | C33: NULL | D33: 7701018 | F33: 10567 | G33: 3 | H33: WINTER SERVICE CHARGE | I33: 4 | J33: Yard | K33: E | L33: 12 | M33: NULL | N33: NULL | O33: NULL | P33: NULL | Q33: NULL | R33: 54 | S33: 45744.543 | T33: PA_SRDC | U33: 45744.321 | V33: PAUSER | W33: NULL | X33: 0 | Y33: 999 | Z33: NULL | AA33: NULL | AB33: NULL | AC33: FEE | AD33: FEE | AE33: AI | AI33: =IF(COUNTIF(Classification!$A$2:$A$338, H33)>0,"FEE", " ") -> FEE | AJ33: =VLOOKUP(A33,'Classification Test Result'!$A$2:$D$2428,4,FALSE) -> #N/A | AL33: =_xlfn.XLOOKUP($A33,Results!$A$2:$A$2256,Results!G$2:G$2256,"") -> 0 | AM33: =_xlfn.XLOOKUP($A33,Results!$A$2:$A$2256,Results!H$2:H$2256,"") -> 0 | AN33: =_xlfn.XLOOKUP($A33,Results!$A$2:$A$2256,Results!I$2:I$2256,"") -> 0 | AO33: =_xlfn.XLOOKUP($A33,Results!$A$2:$A$2256,Results!J$2:J$2256,"") -> 0 | AP33: =_xlfn.XLOOKUP($A33,Results!$A$2:$A$2256,Results!K$2:K$2256,"") -> 0 | AQ33: =_xlfn.XLOOKUP($A33,Results!$A$2:$A$2256,Results!L$2:L$2256,"") -> 0 | AR33: =_xlfn.XLOOKUP($A33,Results!$A$2:$A$2256,Results!M$2:M$2256,"") -> 0 | AS33: =_xlfn.XLOOKUP($A33,Results!$A$2:$A$2256,Results!N$2:N$2256,"") -> 0 | ... BE33: =_xlfn.XLOOKUP($A33,Results!$A$2:$A$2256,Results!Z$2:Z$2256,"") -> 0
A34: 905711 | B34: 281887 | C34: NULL | D34: 15586 | F34: 10441 | G34: 14 | H34: WINTER SERVICE | I34: 10 | J34: YQ/ + YDC | K34: E | L34: 6 | M34: NULL | N34: NULL | O34: NULL | P34: NULL | Q34: NULL | R34: 60 | S34: 45744.668 | T34: PA_SRDC | U34: 45744.449 | V34: PAUSER | W34: NULL | X34: 0 | Y34: 999 | Z34: NULL | AA34: NULL | AB34: NULL | AC34: UNDEFINED | AD34: UNDEFINED | AE34: AI | AI34: FEE | AJ34: =VLOOKUP(A34,'Classification Test Result'!$A$2:$D$2428,4,FALSE) -> #N/A | AL34: =_xlfn.XLOOKUP($A34,Results!$A$2:$A$2256,Results!G$2:G$2256,"") -> 0 | AM34: =_xlfn.XLOOKUP($A34,Results!$A$2:$A$2256,Results!H$2:H$2256,"") -> 0 | AN34: =_xlfn.XLOOKUP($A34,Results!$A$2:$A$2256,Results!I$2:I$2256,"") -> 0 | AO34: =_xlfn.XLOOKUP($A34,Results!$A$2:$A$2256,Results!J$2:J$2256,"") -> 0 | AP34: =_xlfn.XLOOKUP($A34,Results!$A$2:$A$2256,Results!K$2:K$2256,"") -> 0 | AQ34: =_xlfn.XLOOKUP($A34,Results!$A$2:$A$2256,Results!L$2:L$2256,"") -> 0 | AR34: =_xlfn.XLOOKUP($A34,Results!$A$2:$A$2256,Results!M$2:M$2256,"") -> 0 | AS34: =_xlfn.XLOOKUP($A34,Results!$A$2:$A$2256,Results!N$2:N$2256,"") -> 0 | ... BE34: =_xlfn.XLOOKUP($A34,Results!$A$2:$A$2256,Results!Z$2:Z$2256,"") -> 0
A35: 905712 | B35: 281887 | C35: NULL | D35: 15586 | F35: 10441 | G35: 2 | H35: WINTER SERVICE | I35: 10 | J35: YQ/ + YDC | K35: E | L35: 6 | M35: NULL | N35: NULL | O35: NULL | P35: NULL | Q35: NULL | R35: 60 | S35: 45744.668 | T35: PA_SRDC | U35: 45744.449 | V35: PAUSER | W35: NULL | X35: 0 | Y35: 999 | Z35: NULL | AA35: NULL | AB35: NULL | AC35: UNDEFINED | AD35: UNDEFINED | AE35: AI | AI35: FEE | AJ35: =VLOOKUP(A35,'Classification Test Result'!$A$2:$D$2428,4,FALSE) -> #N/A | AL35: =_xlfn.XLOOKUP($A35,Results!$A$2:$A$2256,Results!G$2:G$2256,"") -> 0 | AM35: =_xlfn.XLOOKUP($A35,Results!$A$2:$A$2256,Results!H$2:H$2256,"") -> 0 | AN35: =_xlfn.XLOOKUP($A35,Results!$A$2:$A$2256,Results!I$2:I$2256,"") -> 0 | AO35: =_xlfn.XLOOKUP($A35,Results!$A$2:$A$2256,Results!J$2:J$2256,"") -> 0 | AP35: =_xlfn.XLOOKUP($A35,Results!$A$2:$A$2256,Results!K$2:K$2256,"") -> 0 | AQ35: =_xlfn.XLOOKUP($A35,Results!$A$2:$A$2256,Results!L$2:L$2256,"") -> 0 | AR35: =_xlfn.XLOOKUP($A35,Results!$A$2:$A$2256,Results!M$2:M$2256,"") -> 0 | AS35: =_xlfn.XLOOKUP($A35,Results!$A$2:$A$2256,Results!N$2:N$2256,"") -> 0 | ... BE35: =_xlfn.XLOOKUP($A35,Results!$A$2:$A$2256,Results!Z$2:Z$2256,"") -> 0
A36: 905713 | B36: 281887 | C36: NULL | D36: 15586 | F36: 10441 | G36: 18 | H36: WINTER SERVICE | I36: 10 | J36: YQ/ + YDC | K36: E | L36: 6 | M36: NULL | N36: NULL | O36: NULL | P36: NULL | Q36: NULL | R36: 60 | S36: 45744.668 | T36: PA_SRDC | U36: 45744.449 | V36: PAUSER | W36: NULL | X36: 0 | Y36: 999 | Z36: NULL | AA36: NULL | AB36: NULL | AC36: UNDEFINED | AD36: UNDEFINED | AE36: AI | AI36: FEE | AJ36: =VLOOKUP(A36,'Classification Test Result'!$A$2:$D$2428,4,FALSE) -> #N/A | AL36: =_xlfn.XLOOKUP($A36,Results!$A$2:$A$2256,Results!G$2:G$2256,"") -> 0 | AM36: =_xlfn.XLOOKUP($A36,Results!$A$2:$A$2256,Results!H$2:H$2256,"") -> 0 | AN36: =_xlfn.XLOOKUP($A36,Results!$A$2:$A$2256,Results!I$2:I$2256,"") -> 0 | AO36: =_xlfn.XLOOKUP($A36,Results!$A$2:$A$2256,Results!J$2:J$2256,"") -> 0 | AP36: =_xlfn.XLOOKUP($A36,Results!$A$2:$A$2256,Results!K$2:K$2256,"") -> 0 | AQ36: =_xlfn.XLOOKUP($A36,Results!$A$2:$A$2256,Results!L$2:L$2256,"") -> 0 | AR36: =_xlfn.XLOOKUP($A36,Results!$A$2:$A$2256,Results!M$2:M$2256,"") -> 0 | AS36: =_xlfn.XLOOKUP($A36,Results!$A$2:$A$2256,Results!N$2:N$2256,"") -> 0 | ... BE36: =_xlfn.XLOOKUP($A36,Results!$A$2:$A$2256,Results!Z$2:Z$2256,"") -> 0
A37: 905714 | B37: 281887 | C37: NULL | D37: 15586 | F37: 10441 | G37: 10 | H37: WINTER SERVICE | I37: 10 | J37: YQ/ + YDC | K37: E | L37: 6 | M37: NULL | N37: NULL | O37: NULL | P37: NULL | Q37: NULL | R37: 60 | S37: 45744.668 | T37: PA_SRDC | U37: 45744.449 | V37: PAUSER | W37: NULL | X37: 0 | Y37: 999 | Z37: NULL | AA37: NULL | AB37: NULL | AC37: UNDEFINED | AD37: UNDEFINED | AE37: AI | AI37: FEE | AJ37: =VLOOKUP(A37,'Classification Test Result'!$A$2:$D$2428,4,FALSE) -> #N/A | AL37: =_xlfn.XLOOKUP($A37,Results!$A$2:$A$2256,Results!G$2:G$2256,"") -> 0 | AM37: =_xlfn.XLOOKUP($A37,Results!$A$2:$A$2256,Results!H$2:H$2256,"") -> 0 | AN37: =_xlfn.XLOOKUP($A37,Results!$A$2:$A$2256,Results!I$2:I$2256,"") -> 0 | AO37: =_xlfn.XLOOKUP($A37,Results!$A$2:$A$2256,Results!J$2:J$2256,"") -> 0 | AP37: =_xlfn.XLOOKUP($A37,Results!$A$2:$A$2256,Results!K$2:K$2256,"") -> 0 | AQ37: =_xlfn.XLOOKUP($A37,Results!$A$2:$A$2256,Results!L$2:L$2256,"") -> 0 | AR37: =_xlfn.XLOOKUP($A37,Results!$A$2:$A$2256,Results!M$2:M$2256,"") -> 0 | AS37: =_xlfn.XLOOKUP($A37,Results!$A$2:$A$2256,Results!N$2:N$2256,"") -> 0 | ... BE37: =_xlfn.XLOOKUP($A37,Results!$A$2:$A$2256,Results!Z$2:Z$2256,"") -> 0
A38: 905715 | B38: 281887 | C38: NULL | D38: 15586 | F38: 10441 | G38: 6 | H38: WINTER SERVICE | I38: 10 | J38: YQ/ + YDC | K38: E | L38: 6 | M38: NULL | N38: NULL | O38: NULL | P38: NULL | Q38: NULL | R38: 60 | S38: 45744.668 | T38: PA_SRDC | U38: 45744.449 | V38: PAUSER | W38: NULL | X38: 0 | Y38: 999 | Z38: NULL | AA38: NULL | AB38: NULL | AC38: UNDEFINED | AD38: UNDEFINED | AE38: AI | AI38: FEE | AJ38: =VLOOKUP(A38,'Classification Test Result'!$A$2:$D$2428,4,FALSE) -> #N/A | AL38: =_xlfn.XLOOKUP($A38,Results!$A$2:$A$2256,Results!G$2:G$2256,"") -> 0 | AM38: =_xlfn.XLOOKUP($A38,Results!$A$2:$A$2256,Results!H$2:H$2256,"") -> 0 | AN38: =_xlfn.XLOOKUP($A38,Results!$A$2:$A$2256,Results!I$2:I$2256,"") -> 0 | AO38: =_xlfn.XLOOKUP($A38,Results!$A$2:$A$2256,Results!J$2:J$2256,"") -> 0 | AP38: =_xlfn.XLOOKUP($A38,Results!$A$2:$A$2256,Results!K$2:K$2256,"") -> 0 | AQ38: =_xlfn.XLOOKUP($A38,Results!$A$2:$A$2256,Results!L$2:L$2256,"") -> 0 | AR38: =_xlfn.XLOOKUP($A38,Results!$A$2:$A$2256,Results!M$2:M$2256,"") -> 0 | AS38: =_xlfn.XLOOKUP($A38,Results!$A$2:$A$2256,Results!N$2:N$2256,"") -> 0 | ... BE38: =_xlfn.XLOOKUP($A38,Results!$A$2:$A$2256,Results!Z$2:Z$2256,"") -> 0
A39: 905716 | B39: 281963 | C39: NULL | D39: S4742551.002 | E39: =VLOOKUP(F39,'RPA Vendor Data '!F30:$G$2418,2) -> FROST ELECTRIC SUPPLY CO | F39: 11364 | G39: 1 | H39: WIEGMANN SCF1010 FLUSH SCREW COVER ONLY PAINTED N1 | I39: 1 | J39: EA | K39: E | L39: 28.39 | M39: WIEGMANN | N39: SCF1010 | O39: NULL | P39: NULL | Q39: 78672531352 | R39: 28.39 | S39: 45744.876 | T39: PA_SRDC | U39: 45744.662 | V39: PAUSER | W39: NULL | X39: 0 | Y39: 201 | Z39: NULL | AA39: NULL | AB39: NULL | AC39: WIEGMANN | AD39: WIEGMANN | AE39: AI | AF39: 39121324 | AG39: https://www.gordonelectricsupply.com/p/Wiegmann-Scf1010-Nm1-Flush-Cover-F-Sc-Bx/5598417?srsltid=AfmBOopMbRU8j_p2qB4ADUlZKRPJIelbFkNwfj0nAwlofMtU0rnNdVtk | AI39: MATERIAL | AJ39: =VLOOKUP(A39,'Classification Test Result'!$A$2:$D$2428,4,FALSE) -> #N/A | AL39: =_xlfn.XLOOKUP($A39,Results!$A$2:$A$2256,Results!G$2:G$2256,"") -> 1112794 | AM39: =_xlfn.XLOOKUP($A39,Results!$A$2:$A$2256,Results!H$2:H$2256,"") -> SCF1010 | AN39: =_xlfn.XLOOKUP($A39,Results!$A$2:$A$2256,Results!I$2:I$2256,"") -> WIEGMANN | AO39: =_xlfn.XLOOKUP($A39,Results!$A$2:$A$2256,Results!J$2:J$2256,"") -> 786725313525 | AP39: =_xlfn.XLOOKUP($A39,Results!$A$2:$A$2256,Results!K$2:K$2256,"") -> 39121302 | AQ39: =_xlfn.XLOOKUP($A39,Results!$A$2:$A$2256,Results!L$2:L$2256,"") -> 0 | AR39: =_xlfn.XLOOKUP($A39,Results!$A$2:$A$2256,Results!M$2:M$2256,"") -> 101789 | AS39: =_xlfn.XLOOKUP($A39,Results!$A$2:$A$2256,Results!N$2:N$2256,"") -> WIEG SCF1010 NM1 FLUSH CVR F/SC BX | ... BE39: =_xlfn.XLOOKUP($A39,Results!$A$2:$A$2256,Results!Z$2:Z$2256,"") -> TRUE
A40: 905717 | B40: 281318 | C40: NULL | D40: S009000673.002 | E40: =VLOOKUP(F40,'RPA Vendor Data '!F31:$G$2418,2) -> VIKING ELECTRIC | F40: 13536 | G40: 4 | H40: WIEG SC121204NK SCPB 12X12X4 NO KO | I40: 1 | J40: EA | K40: E | L40: 33.76 | M40: WIEGMANN | N40: SC121204NK | O40: NULL | P40: AK10519466 | Q40: NULL | R40: 33.76 | S40: 45744.189 | T40: PA_SRDC | U40: 45743.967 | V40: PAUSER | W40: NULL | X40: 5 | Y40: 0,0,0 | Z40: 33.76 | AA40: 33.76 | AB40: 136 | AC40: WIEGMANN | AD40: WIEGMANN | AE40: AI | AF40: 39121324 | AG40: https://www.gordonelectricsupply.com/p/Wiegmann-Sc121204Nk-Nema1-Screw-Cover-Box-No-Ko/5597206?srsltid=AfmBOoqo76wvggJp1fnuGjEo0zcawRubQuW4LDgIpJrMUGxLPT1JgIwW | AI40: MATERIAL | AJ40: =VLOOKUP(A40,'Classification Test Result'!$A$2:$D$2428,4,FALSE) -> #N/A | AL40: =_xlfn.XLOOKUP($A40,Results!$A$2:$A$2256,Results!G$2:G$2256,"") -> 341754 | AM40: =_xlfn.XLOOKUP($A40,Results!$A$2:$A$2256,Results!H$2:H$2256,"") -> SC121204NK | AN40: =_xlfn.XLOOKUP($A40,Results!$A$2:$A$2256,Results!I$2:I$2256,"") -> WIEGMANN | AO40: =_xlfn.XLOOKUP($A40,Results!$A$2:$A$2256,Results!J$2:J$2256,"") -> 786725313914 | AP40: =_xlfn.XLOOKUP($A40,Results!$A$2:$A$2256,Results!K$2:K$2256,"") -> 39121332 | AQ40: =_xlfn.XLOOKUP($A40,Results!$A$2:$A$2256,Results!L$2:L$2256,"") -> AK10519466 | AR40: =_xlfn.XLOOKUP($A40,Results!$A$2:$A$2256,Results!M$2:M$2256,"") -> 387559 | AS40: =_xlfn.XLOOKUP($A40,Results!$A$2:$A$2256,Results!N$2:N$2256,"") -> WIEG SC121204NK NEMA1 SC BOX-NO KO | ... BE40: =_xlfn.XLOOKUP($A40,Results!$A$2:$A$2256,Results!Z$2:Z$2256,"") -> TRUE
A41: 905718 | B41: 281307 | C41: NULL | D41: S008997171.002 | E41: =VLOOKUP(F41,'RPA Vendor Data '!F32:$G$2418,2) -> VIKING ELECTRIC | F41: 13536 | G41: 2 | H41: WIEG SC080804NK SCPB 8X8X4 NO KO | I41: 1 | J41: EA | K41: E | L41: 19.94 | M41: WIEGMANN | N41: SC080804NK | O41: NULL | P41: AK10519457 | Q41: NULL | R41: 19.94 | S41: 45744.189 | T41: PA_SRDC | U41: 45743.965 | V41: PAUSER | W41: NULL | X41: 3 | Y41: 0,0,0 | Z41: 19.94 | AA41: 19.94 | AB41: 136 | AC41: WIEGMANN | AD41: WIEGMANN | AE41: AI | AF41: 39121324 | AG41: https://www.gordonelectricsupply.com/p/Wiegmann-Sc080804Nk-Nema1-Screw-Cover-Box-No-Ko/5599503?srsltid=AfmBOoofxW6318sfqi1SpW-rzl2lWGKKM_DoUEaNJZf4338TUNyhRUJa | AI41: MATERIAL | AJ41: =VLOOKUP(A41,'Classification Test Result'!$A$2:$D$2428,4,FALSE) -> #N/A | AL41: =_xlfn.XLOOKUP($A41,Results!$A$2:$A$2256,Results!G$2:G$2256,"") -> 341749 | AM41: =_xlfn.XLOOKUP($A41,Results!$A$2:$A$2256,Results!H$2:H$2256,"") -> SC080804NK | AN41: =_xlfn.XLOOKUP($A41,Results!$A$2:$A$2256,Results!I$2:I$2256,"") -> WIEGMANN | AO41: =_xlfn.XLOOKUP($A41,Results!$A$2:$A$2256,Results!J$2:J$2256,"") -> 786725312917 | AP41: =_xlfn.XLOOKUP($A41,Results!$A$2:$A$2256,Results!K$2:K$2256,"") -> 39121332 | AQ41: =_xlfn.XLOOKUP($A41,Results!$A$2:$A$2256,Results!L$2:L$2256,"") -> AK10519457 | AR41: =_xlfn.XLOOKUP($A41,Results!$A$2:$A$2256,Results!M$2:M$2256,"") -> 597551 | AS41: =_xlfn.XLOOKUP($A41,Results!$A$2:$A$2256,Results!N$2:N$2256,"") -> WIEG SC080804NK NEMA1 SC BOX-NO KO | ... BE41: =_xlfn.XLOOKUP($A41,Results!$A$2:$A$2256,Results!Z$2:Z$2256,"") -> TRUE
A42: 905719 | B42: 281325 | C42: NULL | D42: S008999664.005 | E42: =VLOOKUP(F42,'RPA Vendor Data '!F33:$G$2418,2) -> VIKING ELECTRIC | F42: 13536 | G42: 11 | H42: WIEG SC060604NK SCPB 6X6X4 NO KO | I42: 7 | J42: EA | K42: E | L42: 10.59 | M42: WIEGMANN | N42: SC060604NK | O42: NULL | P42: AK10519452 | Q42: NULL | R42: 74.13 | S42: 45744.189 | T42: PA_SRDC | U42: 45743.969 | V42: PAUSER | W42: NULL | X42: 0 | Y42: 0 | Z42: 10.59 | AA42: NULL | AB42: 166 | AC42: WIEGMANN | AD42: WIEGMANN | AE42: AI | AF42: 39121324 | AG42: https://www.gordonelectricsupply.com/p/Wiegmann-Sc060604Nk-Nema1-Screw-Cover-Box-No-Ko/5603460?srsltid=AfmBOoqN8HPLxcZYFyKtXn0E5E3qH-wBXQpIRxull33VZuzi8oFLaDxB | AI42: MATERIAL | AJ42: =VLOOKUP(A42,'Classification Test Result'!$A$2:$D$2428,4,FALSE) -> #N/A | AL42: =_xlfn.XLOOKUP($A42,Results!$A$2:$A$2256,Results!G$2:G$2256,"") -> 341746 | AM42: =_xlfn.XLOOKUP($A42,Results!$A$2:$A$2256,Results!H$2:H$2256,"") -> SC060604NK | AN42: =_xlfn.XLOOKUP($A42,Results!$A$2:$A$2256,Results!I$2:I$2256,"") -> WIEGMANN | AO42: =_xlfn.XLOOKUP($A42,Results!$A$2:$A$2256,Results!J$2:J$2256,"") -> 786725312313 | AP42: =_xlfn.XLOOKUP($A42,Results!$A$2:$A$2256,Results!K$2:K$2256,"") -> 39121332 | AQ42: =_xlfn.XLOOKUP($A42,Results!$A$2:$A$2256,Results!L$2:L$2256,"") -> AK10519452 | AR42: =_xlfn.XLOOKUP($A42,Results!$A$2:$A$2256,Results!M$2:M$2256,"") -> 169683 | AS42: =_xlfn.XLOOKUP($A42,Results!$A$2:$A$2256,Results!N$2:N$2256,"") -> WIEG SC060604NK NEMA1 SC BOX-NO KO | ... BE42: =_xlfn.XLOOKUP($A42,Results!$A$2:$A$2256,Results!Z$2:Z$2256,"") -> TRUE
A43: 905720 | B43: 281325 | C43: NULL | D43: S008999664.005 | E43: =VLOOKUP(F43,'RPA Vendor Data '!F34:$G$2418,2) -> VIKING ELECTRIC | F43: 13536 | G43: 3 | H43: WIEG HS882NK N1 WIREWAY 8X8X2FT NO KO | I43: 1 | J43: EA | K43: E | L43: 118.91 | M43: WIEGMANN | N43: HS882NK | O43: NULL | P43: NULL | Q43: NULL | R43: 118.91 | S43: 45744.189 | T43: PA_SRDC | U43: 45743.969 | V43: PAUSER | W43: NULL | X43: 0 | Y43: 201 | Z43: NULL | AA43: NULL | AB43: NULL | AC43: WIEGMANN | AD43: WIEGMANN | AE43: AI | AF43: 39131714 | AG43: https://www.gordonelectricsupply.com/p/Wiegmann-Hs882Nk-Nm1-Hng-Sc-Wwy-No-Ko/5751081?srsltid=AfmBOooDtBSoghUAlQ2t50C6iazkLKz-b1dxs65rRl5ZfAekzzACFbIc | AI43: MATERIAL | AJ43: =VLOOKUP(A43,'Classification Test Result'!$A$2:$D$2428,4,FALSE) -> #N/A | AL43: =_xlfn.XLOOKUP($A43,Results!$A$2:$A$2256,Results!G$2:G$2256,"") -> 745686 | AM43: =_xlfn.XLOOKUP($A43,Results!$A$2:$A$2256,Results!H$2:H$2256,"") -> HS882NK | AN43: =_xlfn.XLOOKUP($A43,Results!$A$2:$A$2256,Results!I$2:I$2256,"") -> WIEGMANN | AO43: =_xlfn.XLOOKUP($A43,Results!$A$2:$A$2256,Results!J$2:J$2256,"") -> 786725610754 | AP43: =_xlfn.XLOOKUP($A43,Results!$A$2:$A$2256,Results!K$2:K$2256,"") -> 39131710 | AQ43: =_xlfn.XLOOKUP($A43,Results!$A$2:$A$2256,Results!L$2:L$2256,"") -> 0 | AR43: =_xlfn.XLOOKUP($A43,Results!$A$2:$A$2256,Results!M$2:M$2256,"") -> 341557 | AS43: =_xlfn.XLOOKUP($A43,Results!$A$2:$A$2256,Results!N$2:N$2256,"") -> WIEG HS882NK NM1 HNG/SC WWY-NO KO | ... BE43: =_xlfn.XLOOKUP($A43,Results!$A$2:$A$2256,Results!Z$2:Z$2256,"") -> TRUE
A44: 905721 | B44: 281325 | C44: NULL | D44: S008999664.005 | E44: =VLOOKUP(F44,'RPA Vendor Data '!F35:$G$2418,2) -> VIKING ELECTRIC | F44: 13536 | G44: 4 | H44: WIEG E0808NK N1 WIREWAY ENDCAP 8IN NO KO | I44: 2 | J44: EA | K44: E | L44: 12.11 | M44: WIEGMANN | N44: E0808NK | O44: NULL | P44: AK10519193 | Q44: NULL | R44: 24.22 | S44: 45744.189 | T44: PA_SRDC | U44: 45743.969 | V44: PAUSER | W44: NULL | X44: 0 | Y44: 0 | Z44: 12.11 | AA44: NULL | AB44: 136 | AC44: WIEGMANN | AD44: WIEGMANN | AE44: AI | AF44: 39131714 | AG44: https://www.gordonelectricsupply.com/p/Wiegmann-E0808Nk-Nk-N18X8-Cap-End/5750927?srsltid=AfmBOopaoXkdkZwDpDaowDzImKHI1aWRjyFNmWmJLubZAiQIZpPqxKsK | AI44: MATERIAL | AJ44: =VLOOKUP(A44,'Classification Test Result'!$A$2:$D$2428,4,FALSE) -> #N/A | AL44: =_xlfn.XLOOKUP($A44,Results!$A$2:$A$2256,Results!G$2:G$2256,"") -> 341710 | AM44: =_xlfn.XLOOKUP($A44,Results!$A$2:$A$2256,Results!H$2:H$2256,"") -> E0808NK | AN44: =_xlfn.XLOOKUP($A44,Results!$A$2:$A$2256,Results!I$2:I$2256,"") -> WIEGMANN | AO44: =_xlfn.XLOOKUP($A44,Results!$A$2:$A$2256,Results!J$2:J$2256,"") -> 786725860906 | AP44: =_xlfn.XLOOKUP($A44,Results!$A$2:$A$2256,Results!K$2:K$2256,"") -> 39131711 | AQ44: =_xlfn.XLOOKUP($A44,Results!$A$2:$A$2256,Results!L$2:L$2256,"") -> AK10519193 | AR44: =_xlfn.XLOOKUP($A44,Results!$A$2:$A$2256,Results!M$2:M$2256,"") -> 234588 | AS44: =_xlfn.XLOOKUP($A44,Results!$A$2:$A$2256,Results!N$2:N$2256,"") -> WIEG E0808NK NK N18X8 CAP END | ... BE44: =_xlfn.XLOOKUP($A44,Results!$A$2:$A$2256,Results!Z$2:Z$2256,"") -> TRUE
A45: 905722 | B45: 281313 | C45: NULL | D45: S009000748.002 | E45: =VLOOKUP(F45,'RPA Vendor Data '!F36:$G$2418,2) -> VIKING ELECTRIC | F45: 13536 | G45: 11 | H45: WIC. THHN 6 STR GRN MR | I45: 10 | J45: m | K45: M | L45: 846.44 | M45: GENERIC WIRE | N45: THHN 6 STR GRN MR | O45: NULL | P45: AK10438977 | Q45: NULL | R45: 8.46 | S45: 45744.189 | T45: PA_SRDC | U45: 45743.965 | V45: PAUSER | W45: NULL | X45: 0 | Y45: 201,0,0 | Z45: NULL | AA45: 846.44 | AB45: NULL | AC45: GENERIC WIRE | AD45: GENERIC WIRE | AE45: AI | AF45: - | AG45: https://www.vikingelectric.com/product/detail/66176/thhn-copper-thhn-6-str-grn-mr | AI45: MATERIAL | AJ45: =VLOOKUP(A45,'Classification Test Result'!$A$2:$D$2428,4,FALSE) -> #N/A | AL45: =_xlfn.XLOOKUP($A45,Results!$A$2:$A$2256,Results!G$2:G$2256,"") | AM45: =_xlfn.XLOOKUP($A45,Results!$A$2:$A$2256,Results!H$2:H$2256,"") | AN45: =_xlfn.XLOOKUP($A45,Results!$A$2:$A$2256,Results!I$2:I$2256,"") | AO45: =_xlfn.XLOOKUP($A45,Results!$A$2:$A$2256,Results!J$2:J$2256,"") | AP45: =_xlfn.XLOOKUP($A45,Results!$A$2:$A$2256,Results!K$2:K$2256,"") | AQ45: =_xlfn.XLOOKUP($A45,Results!$A$2:$A$2256,Results!L$2:L$2256,"") | AR45: =_xlfn.XLOOKUP($A45,Results!$A$2:$A$2256,Results!M$2:M$2256,"") | AS45: =_xlfn.XLOOKUP($A45,Results!$A$2:$A$2256,Results!N$2:N$2256,"") | ... BE45: =_xlfn.XLOOKUP($A45,Results!$A$2:$A$2256,Results!Z$2:Z$2256,"")
A46: 905723 | B46: 281322 | C46: NULL | D46: S008998485.001 | E46: =VLOOKUP(F46,'RPA Vendor Data '!F37:$G$2418,2) -> VIKING ELECTRIC | F46: 13536 | G46: 3 | H46: WIC. THHN 3/0 STR YEL MR | I46: 20 | J46: m | K46: M | L46: 4337.15 | M46: GENERIC WIRE | N46: THHN 3/0 STR YEL MR | O46: NULL | P46: NULL | Q46: NULL | R46: 86.74 | S46: 45744.189 | T46: PA_SRDC | U46: 45743.967 | V46: PAUSER | W46: NULL | X46: 0 | Y46: 201,0,0 | Z46: NULL | AA46: 4337.15 | AB46: NULL | AC46: GENERIC WIRE | AD46: GENERIC WIRE | AE46: AI | AF46: - | AG46: https://www.vikingelectric.com/product/detail/66137/thhn-copper-thhn-3-0-str-yel-mr | AI46: MATERIAL | AJ46: =VLOOKUP(A46,'Classification Test Result'!$A$2:$D$2428,4,FALSE) -> #N/A | AL46: =_xlfn.XLOOKUP($A46,Results!$A$2:$A$2256,Results!G$2:G$2256,"") -> 0 | AM46: =_xlfn.XLOOKUP($A46,Results!$A$2:$A$2256,Results!H$2:H$2256,"") -> 0 | AN46: =_xlfn.XLOOKUP($A46,Results!$A$2:$A$2256,Results!I$2:I$2256,"") -> 0 | AO46: =_xlfn.XLOOKUP($A46,Results!$A$2:$A$2256,Results!J$2:J$2256,"") -> 0 | AP46: =_xlfn.XLOOKUP($A46,Results!$A$2:$A$2256,Results!K$2:K$2256,"") -> 0 | AQ46: =_xlfn.XLOOKUP($A46,Results!$A$2:$A$2256,Results!L$2:L$2256,"") -> 0 | AR46: =_xlfn.XLOOKUP($A46,Results!$A$2:$A$2256,Results!M$2:M$2256,"") -> 0 | AS46: =_xlfn.XLOOKUP($A46,Results!$A$2:$A$2256,Results!N$2:N$2256,"") -> 0 | ... BE46: =_xlfn.XLOOKUP($A46,Results!$A$2:$A$2256,Results!Z$2:Z$2256,"") -> TRUE
A47: 905724 | B47: 281322 | C47: NULL | D47: S008998485.001 | E47: =VLOOKUP(F47,'RPA Vendor Data '!F38:$G$2418,2) -> VIKING ELECTRIC | F47: 13536 | G47: 2 | H47: WIC. THHN 3/0 STR ORG MR | I47: 20 | J47: m | K47: M | L47: 4337.15 | M47: GENERIC WIRE | N47: THHN 3/0 STR ORG MR | O47: NULL | P47: NULL | Q47: NULL | R47: 86.74 | S47: 45744.189 | T47: PA_SRDC | U47: 45743.967 | V47: PAUSER | W47: NULL | X47: 0 | Y47: 201,0,0 | Z47: NULL | AA47: 4337.15 | AB47: NULL | AC47: GENERIC WIRE | AD47: GENERIC WIRE | AE47: AI | AF47: - | AG47: https://www.vikingelectric.com/product/detail/66134/thhn-copper-thhn-3-0-str-org-mr | AI47: MATERIAL | AJ47: =VLOOKUP(A47,'Classification Test Result'!$A$2:$D$2428,4,FALSE) -> #N/A | AL47: =_xlfn.XLOOKUP($A47,Results!$A$2:$A$2256,Results!G$2:G$2256,"") -> 0 | AM47: =_xlfn.XLOOKUP($A47,Results!$A$2:$A$2256,Results!H$2:H$2256,"") -> 0 | AN47: =_xlfn.XLOOKUP($A47,Results!$A$2:$A$2256,Results!I$2:I$2256,"") -> 0 | AO47: =_xlfn.XLOOKUP($A47,Results!$A$2:$A$2256,Results!J$2:J$2256,"") -> 0 | AP47: =_xlfn.XLOOKUP($A47,Results!$A$2:$A$2256,Results!K$2:K$2256,"") -> 0 | AQ47: =_xlfn.XLOOKUP($A47,Results!$A$2:$A$2256,Results!L$2:L$2256,"") -> 0 | AR47: =_xlfn.XLOOKUP($A47,Results!$A$2:$A$2256,Results!M$2:M$2256,"") -> 0 | AS47: =_xlfn.XLOOKUP($A47,Results!$A$2:$A$2256,Results!N$2:N$2256,"") -> 0 | ... BE47: =_xlfn.XLOOKUP($A47,Results!$A$2:$A$2256,Results!Z$2:Z$2256,"") -> TRUE
A48: 905725 | B48: 281322 | C48: NULL | D48: S008998485.001 | E48: =VLOOKUP(F48,'RPA Vendor Data '!F39:$G$2418,2) -> VIKING ELECTRIC | F48: 13536 | G48: 1 | H48: WIC. THHN 3/0 STR BRN MR | I48: 20 | J48: m | K48: M | L48: 4337.15 | M48: GENERIC WIRE | N48: THHN 3/0 STR BRN MR | O48: NULL | P48: NULL | Q48: NULL | R48: 86.74 | S48: 45744.189 | T48: PA_SRDC | U48: 45743.967 | V48: PAUSER | W48: NULL | X48: 0 | Y48: 201,0,0 | Z48: NULL | AA48: 4337.15 | AB48: NULL | AC48: GENERIC WIRE | AD48: GENERIC WIRE | AE48: AI | AF48: - | AG48: https://www.vikingelectric.com/product/detail/66132/thhn-copper-thhn-3-0-str-brn-mr | AI48: MATERIAL | AJ48: =VLOOKUP(A48,'Classification Test Result'!$A$2:$D$2428,4,FALSE) -> #N/A | AL48: =_xlfn.XLOOKUP($A48,Results!$A$2:$A$2256,Results!G$2:G$2256,"") -> 0 | AM48: =_xlfn.XLOOKUP($A48,Results!$A$2:$A$2256,Results!H$2:H$2256,"") -> 0 | AN48: =_xlfn.XLOOKUP($A48,Results!$A$2:$A$2256,Results!I$2:I$2256,"") -> 0 | AO48: =_xlfn.XLOOKUP($A48,Results!$A$2:$A$2256,Results!J$2:J$2256,"") -> 0 | AP48: =_xlfn.XLOOKUP($A48,Results!$A$2:$A$2256,Results!K$2:K$2256,"") -> 0 | AQ48: =_xlfn.XLOOKUP($A48,Results!$A$2:$A$2256,Results!L$2:L$2256,"") -> 0 | AR48: =_xlfn.XLOOKUP($A48,Results!$A$2:$A$2256,Results!M$2:M$2256,"") -> 0 | AS48: =_xlfn.XLOOKUP($A48,Results!$A$2:$A$2256,Results!N$2:N$2256,"") -> 0 | ... BE48: =_xlfn.XLOOKUP($A48,Results!$A$2:$A$2256,Results!Z$2:Z$2256,"") -> TRUE
A49: 905726 | B49: 281885 | C49: NULL | D49: S058019923.002 | E49: =VLOOKUP(F49,'RPA Vendor Data '!F40:$G$2418,2) -> CAPITAL ELECTRIC | F49: 10512 | G49: 1 | H49: WIC. THHN 3/0 STR BLK MR | I49: 90 | J49: m | K49: M | L49: 3629.63 | M49: GENERIC WIRE | N49: WIC. THHN 3/0 STR BLK MR | O49: NULL | P49: NULL | Q49: 98010063411 | R49: 326.67 | S49: 45744.668 | T49: PA_SRDC | U49: 45744.444 | V49: PAUSER | W49: NULL | X49: 0 | Y49: 201,0 | Z49: NULL | AA49: 3629.63 | AB49: NULL | AC49: GENERIC WIRE | AD49: GENERIC WIRE | AE49: AI | AF49: - | AG49: https://www.cooper-electric.com/product/detail/30483/thhn-copper-wic-thhn-3-0-str-blk-mr | AI49: MATERIAL | AJ49: =VLOOKUP(A49,'Classification Test Result'!$A$2:$D$2428,4,FALSE) -> #N/A | AL49: =_xlfn.XLOOKUP($A49,Results!$A$2:$A$2256,Results!G$2:G$2256,"") -> 0 | AM49: =_xlfn.XLOOKUP($A49,Results!$A$2:$A$2256,Results!H$2:H$2256,"") -> 0 | AN49: =_xlfn.XLOOKUP($A49,Results!$A$2:$A$2256,Results!I$2:I$2256,"") -> 0 | AO49: =_xlfn.XLOOKUP($A49,Results!$A$2:$A$2256,Results!J$2:J$2256,"") -> 0 | AP49: =_xlfn.XLOOKUP($A49,Results!$A$2:$A$2256,Results!K$2:K$2256,"") -> 0 | AQ49: =_xlfn.XLOOKUP($A49,Results!$A$2:$A$2256,Results!L$2:L$2256,"") -> 0 | AR49: =_xlfn.XLOOKUP($A49,Results!$A$2:$A$2256,Results!M$2:M$2256,"") -> 0 | AS49: =_xlfn.XLOOKUP($A49,Results!$A$2:$A$2256,Results!N$2:N$2256,"") -> 0 | ... BE49: =_xlfn.XLOOKUP($A49,Results!$A$2:$A$2256,Results!Z$2:Z$2256,"") -> TRUE
A50: 905727 | B50: 281313 | C50: NULL | D50: S009000748.002 | E50: =VLOOKUP(F50,'RPA Vendor Data '!F41:$G$2418,2) -> VIKING ELECTRIC | F50: 13536 | G50: 10 | H50: WIC. THHN 1 STR WHT MR | I50: 10 | J50: m | K50: M | L50: 2278.72 | M50: GENERIC WIRE | N50: THHN 1 STR WHT MR | O50: NULL | P50: NULL | Q50: NULL | R50: 22.79 | S50: 45744.189 | T50: PA_SRDC | U50: 45743.965 | V50: PAUSER | W50: NULL | X50: 0 | Y50: 201,0,0 | Z50: NULL | AA50: 2278.72 | AB50: NULL | AC50: GENERIC WIRE | AD50: GENERIC WIRE | AE50: AI | AF50: - | AG50: https://www.vikingelectric.com/product/detail/80947/thhn-copper-thhn-1-str-wht-mr | AI50: MATERIAL | AJ50: =VLOOKUP(A50,'Classification Test Result'!$A$2:$D$2428,4,FALSE) -> #N/A | AL50: =_xlfn.XLOOKUP($A50,Results!$A$2:$A$2256,Results!G$2:G$2256,"") -> 0 | AM50: =_xlfn.XLOOKUP($A50,Results!$A$2:$A$2256,Results!H$2:H$2256,"") -> 0 | AN50: =_xlfn.XLOOKUP($A50,Results!$A$2:$A$2256,Results!I$2:I$2256,"") -> 0 | AO50: =_xlfn.XLOOKUP($A50,Results!$A$2:$A$2256,Results!J$2:J$2256,"") -> 0 | AP50: =_xlfn.XLOOKUP($A50,Results!$A$2:$A$2256,Results!K$2:K$2256,"") -> 0 | AQ50: =_xlfn.XLOOKUP($A50,Results!$A$2:$A$2256,Results!L$2:L$2256,"") -> 0 | AR50: =_xlfn.XLOOKUP($A50,Results!$A$2:$A$2256,Results!M$2:M$2256,"") -> 0 | AS50: =_xlfn.XLOOKUP($A50,Results!$A$2:$A$2256,Results!N$2:N$2256,"") -> 0 | ... BE50: =_xlfn.XLOOKUP($A50,Results!$A$2:$A$2256,Results!Z$2:Z$2256,"") -> TRUE
A51: 905728 | B51: 281313 | C51: NULL | D51: S009000748.002 | E51: =VLOOKUP(F51,'RPA Vendor Data '!F42:$G$2418,2) -> VIKING ELECTRIC | F51: 13536 | G51: 8 | H51: WIC. THHN 1 STR RED MR | I51: 10 | J51: m | K51: M | L51: 2278.72 | M51: GENERIC WIRE | N51: THHN 1 STR RED MR | O51: NULL | P51: NULL | Q51: NULL | R51: 22.79 | S51: 45744.189 | T51: PA_SRDC | U51: 45743.965 | V51: PAUSER | W51: NULL | X51: 0 | Y51: 201,0,0 | Z51: NULL | AA51: 2278.72 | AB51: NULL | AC51: GENERIC WIRE | AD51: GENERIC WIRE | AE51: AI | AF51: - | AG51: https://www.vikingelectric.com/product/detail/80946/thhn-copper-thhn-1-str-red-mr | AI51: MATERIAL | AJ51: =VLOOKUP(A51,'Classification Test Result'!$A$2:$D$2428,4,FALSE) -> #N/A | AL51: =_xlfn.XLOOKUP($A51,Results!$A$2:$A$2256,Results!G$2:G$2256,"") -> 0 | AM51: =_xlfn.XLOOKUP($A51,Results!$A$2:$A$2256,Results!H$2:H$2256,"") -> 0 | AN51: =_xlfn.XLOOKUP($A51,Results!$A$2:$A$2256,Results!I$2:I$2256,"") -> 0 | AO51: =_xlfn.XLOOKUP($A51,Results!$A$2:$A$2256,Results!J$2:J$2256,"") -> 0 | AP51: =_xlfn.XLOOKUP($A51,Results!$A$2:$A$2256,Results!K$2:K$2256,"") -> 0 | AQ51: =_xlfn.XLOOKUP($A51,Results!$A$2:$A$2256,Results!L$2:L$2256,"") -> 0 | AR51: =_xlfn.XLOOKUP($A51,Results!$A$2:$A$2256,Results!M$2:M$2256,"") -> 0 | AS51: =_xlfn.XLOOKUP($A51,Results!$A$2:$A$2256,Results!N$2:N$2256,"") -> 0 | ... BE51: =_xlfn.XLOOKUP($A51,Results!$A$2:$A$2256,Results!Z$2:Z$2256,"") -> 0
A52: 905729 | B52: 281313 | C52: NULL | D52: S009000748.002 | E52: =VLOOKUP(F52,'RPA Vendor Data '!F43:$G$2418,2) -> VIKING ELECTRIC | F52: 13536 | G52: 9 | H52: WIC. THHN 1 STR BLU MR | I52: 10 | J52: m | K52: M | L52: 2278.72 | M52: GENERIC WIRE | N52: THHN 1 STR BLU MR | O52: NULL | P52: NULL | Q52: NULL | R52: 22.79 | S52: 45744.189 | T52: PA_SRDC | U52: 45743.965 | V52: PAUSER | W52: NULL | X52: 0 | Y52: 201,0,0 | Z52: NULL | AA52: 2278.72 | AB52: NULL | AC52: GENERIC WIRE | AD52: GENERIC WIRE | AE52: AI | AF52: - | AG52: https://www.vikingelectric.com/product/detail/80934/thhn-copper-thhn-1-str-blu-mr | AI52: MATERIAL | AJ52: =VLOOKUP(A52,'Classification Test Result'!$A$2:$D$2428,4,FALSE) -> #N/A | AL52: =_xlfn.XLOOKUP($A52,Results!$A$2:$A$2256,Results!G$2:G$2256,"") -> 0 | AM52: =_xlfn.XLOOKUP($A52,Results!$A$2:$A$2256,Results!H$2:H$2256,"") -> 0 | AN52: =_xlfn.XLOOKUP($A52,Results!$A$2:$A$2256,Results!I$2:I$2256,"") -> 0 | AO52: =_xlfn.XLOOKUP($A52,Results!$A$2:$A$2256,Results!J$2:J$2256,"") -> 0 | AP52: =_xlfn.XLOOKUP($A52,Results!$A$2:$A$2256,Results!K$2:K$2256,"") -> 0 | AQ52: =_xlfn.XLOOKUP($A52,Results!$A$2:$A$2256,Results!L$2:L$2256,"") -> 0 | AR52: =_xlfn.XLOOKUP($A52,Results!$A$2:$A$2256,Results!M$2:M$2256,"") -> 0 | AS52: =_xlfn.XLOOKUP($A52,Results!$A$2:$A$2256,Results!N$2:N$2256,"") -> 0 | ... BE52: =_xlfn.XLOOKUP($A52,Results!$A$2:$A$2256,Results!Z$2:Z$2256,"") -> TRUE
A53: 905730 | B53: 281313 | C53: NULL | D53: S009000748.002 | E53: =VLOOKUP(F53,'RPA Vendor Data '!F44:$G$2418,2) -> VIKING ELECTRIC | F53: 13536 | G53: 7 | H53: WIC. THHN 1 STR BLK MR | I53: 10 | J53: m | K53: M | L53: 2278.72 | M53: GENERIC WIRE | N53: THHN 1 STR BLK MR | O53: NULL | P53: AK10438561 | Q53: NULL | R53: 22.79 | S53: 45744.189 | T53: PA_SRDC | U53: 45743.965 | V53: PAUSER | W53: NULL | X53: 0 | Y53: 201,0,0 | Z53: NULL | AA53: 2278.72 | AB53: NULL | AC53: GENERIC WIRE | AD53: GENERIC WIRE | AE53: AI | AF53: - | AG53: https://www.vikingelectric.com/product/detail/66087/thhn-copper-thhn-1-str-blk-mr | AI53: MATERIAL | AJ53: =VLOOKUP(A53,'Classification Test Result'!$A$2:$D$2428,4,FALSE) -> #N/A | AL53: =_xlfn.XLOOKUP($A53,Results!$A$2:$A$2256,Results!G$2:G$2256,"") -> 0 | AM53: =_xlfn.XLOOKUP($A53,Results!$A$2:$A$2256,Results!H$2:H$2256,"") -> 0 | AN53: =_xlfn.XLOOKUP($A53,Results!$A$2:$A$2256,Results!I$2:I$2256,"") -> 0 | AO53: =_xlfn.XLOOKUP($A53,Results!$A$2:$A$2256,Results!J$2:J$2256,"") -> 0 | AP53: =_xlfn.XLOOKUP($A53,Results!$A$2:$A$2256,Results!K$2:K$2256,"") -> 0 | AQ53: =_xlfn.XLOOKUP($A53,Results!$A$2:$A$2256,Results!L$2:L$2256,"") -> 0 | AR53: =_xlfn.XLOOKUP($A53,Results!$A$2:$A$2256,Results!M$2:M$2256,"") -> 0 | AS53: =_xlfn.XLOOKUP($A53,Results!$A$2:$A$2256,Results!N$2:N$2256,"") -> 0 | ... BE53: =_xlfn.XLOOKUP($A53,Results!$A$2:$A$2256,Results!Z$2:Z$2256,"") -> TRUE
A54: 905731 | B54: 281324 | C54: NULL | D54: S009000143.001 | E54: =VLOOKUP(F54,'RPA Vendor Data '!F45:$G$2418,2) -> VIKING ELECTRIC | F54: 13536 | G54: 1 | H54: WIC. MCHVA 12/2 STR BRN GRY 250C HV ALU ARM BRN GRY GRN | I54: 500 | J54: m | K54: M | L54: 756.47 | M54: GENERIC WIRE | N54: MCHVA 12/2 STR BRN GRY 250C | O54: NULL | P54: NULL | Q54: NULL | R54: 378.24 | S54: 45744.189 | T54: PA_SRDC | U54: 45743.969 | V54: PAUSER | W54: NULL | X54: 1 | Y54: 201,0,0 | Z54: NULL | AA54: 756.47 | AB54: NULL | AC54: GENERIC WIRE | AD54: GENERIC WIRE | AE54: AI | AF54: - | AG54: https://www.vikingelectric.com/product/detail/65955/miscellaneous-mc-cable-mchva-12-2-str-brn-gry-250c | AI54: MATERIAL | AJ54: =VLOOKUP(A54,'Classification Test Result'!$A$2:$D$2428,4,FALSE) -> #N/A | AL54: =_xlfn.XLOOKUP($A54,Results!$A$2:$A$2256,Results!G$2:G$2256,"") | AM54: =_xlfn.XLOOKUP($A54,Results!$A$2:$A$2256,Results!H$2:H$2256,"") | AN54: =_xlfn.XLOOKUP($A54,Results!$A$2:$A$2256,Results!I$2:I$2256,"") | AO54: =_xlfn.XLOOKUP($A54,Results!$A$2:$A$2256,Results!J$2:J$2256,"") | AP54: =_xlfn.XLOOKUP($A54,Results!$A$2:$A$2256,Results!K$2:K$2256,"") | AQ54: =_xlfn.XLOOKUP($A54,Results!$A$2:$A$2256,Results!L$2:L$2256,"") | AR54: =_xlfn.XLOOKUP($A54,Results!$A$2:$A$2256,Results!M$2:M$2256,"") | AS54: =_xlfn.XLOOKUP($A54,Results!$A$2:$A$2256,Results!N$2:N$2256,"") | ... BE54: =_xlfn.XLOOKUP($A54,Results!$A$2:$A$2256,Results!Z$2:Z$2256,"")
A55: 905732 | B55: 281709 | C55: NULL | D55: S007852512.001 | E55: =VLOOKUP(F55,'RPA Vendor Data '!F46:$G$2418,2) -> ONESOURCE DISTRIBUTORS | F55: 16089 | G55: 1 | H55: WIC. MCA 12/2 STR HV 16/2 250C ALU ARM BRN GRY GRN LV PUR PNK | I55: 1000 | J55: M | K55: M | L55: 1728.1 | M55: GENERIC WIRE | N55: WIC MCA 12/2 STR HV 16/2 250C | O55: NULL | P55: NULL | Q55: NULL | R55: 1728.1 | S55: 45744.544 | T55: PA_SRDC | U55: 45744.312 | V55: PAUSER | W55: NULL | X55: 1 | Y55: 201,0,0 | Z55: NULL | AA55: 1728.1 | AB55: NULL | AC55: GENERIC WIRE | AD55: GENERIC WIRE | AE55: AI | AF55: - | AG55: https://www.1sourcedist.com/product/detail/5556434/mccable-wic-mca-12-2-str-hv-16-2-250c | AI55: MATERIAL | AJ55: =VLOOKUP(A55,'Classification Test Result'!$A$2:$D$2428,4,FALSE) -> #N/A | AL55: =_xlfn.XLOOKUP($A55,Results!$A$2:$A$2256,Results!G$2:G$2256,"") | AM55: =_xlfn.XLOOKUP($A55,Results!$A$2:$A$2256,Results!H$2:H$2256,"") | AN55: =_xlfn.XLOOKUP($A55,Results!$A$2:$A$2256,Results!I$2:I$2256,"") | AO55: =_xlfn.XLOOKUP($A55,Results!$A$2:$A$2256,Results!J$2:J$2256,"") | AP55: =_xlfn.XLOOKUP($A55,Results!$A$2:$A$2256,Results!K$2:K$2256,"") | AQ55: =_xlfn.XLOOKUP($A55,Results!$A$2:$A$2256,Results!L$2:L$2256,"") | AR55: =_xlfn.XLOOKUP($A55,Results!$A$2:$A$2256,Results!M$2:M$2256,"") | AS55: =_xlfn.XLOOKUP($A55,Results!$A$2:$A$2256,Results!N$2:N$2256,"") | ... BE55: =_xlfn.XLOOKUP($A55,Results!$A$2:$A$2256,Results!Z$2:Z$2256,"")
A56: 905733 | B56: 281726 | C56: NULL | D56: S007852002.001 | E56: =VLOOKUP(F56,'RPA Vendor Data '!F47:$G$2418,2) -> INDEPENDENT ELECTRIC | F56: 14376 | G56: 3 | H56: WIC. MCA 12/2 SOL HV 16/2 250C ALU ARM BRN GRY GRN / LV PUR PNK | I56: 250 | J56: M | K56: M | L56: 1443.45 | M56: GENERIC WIRE | N56: MCA | O56: NULL | P56: NULL | Q56: NULL | R56: 360.86 | S56: 45744.543 | T56: PA_SRDC | U56: 45744.318 | V56: PAUSER | W56: NULL | X56: 0 | Y56: 201 | Z56: NULL | AA56: NULL | AB56: NULL | AC56: GENERIC WIRE | AD56: GENERIC WIRE | AE56: AI | AF56: 26121500 | AG56: https://usa.databasesets.com/unspsc/commodity/26121614 | AI56: MATERIAL | AJ56: =VLOOKUP(A56,'Classification Test Result'!$A$2:$D$2428,4,FALSE) -> #N/A | AL56: =_xlfn.XLOOKUP($A56,Results!$A$2:$A$2256,Results!G$2:G$2256,"") | AM56: =_xlfn.XLOOKUP($A56,Results!$A$2:$A$2256,Results!H$2:H$2256,"") | AN56: =_xlfn.XLOOKUP($A56,Results!$A$2:$A$2256,Results!I$2:I$2256,"") | AO56: =_xlfn.XLOOKUP($A56,Results!$A$2:$A$2256,Results!J$2:J$2256,"") | AP56: =_xlfn.XLOOKUP($A56,Results!$A$2:$A$2256,Results!K$2:K$2256,"") | AQ56: =_xlfn.XLOOKUP($A56,Results!$A$2:$A$2256,Results!L$2:L$2256,"") | AR56: =_xlfn.XLOOKUP($A56,Results!$A$2:$A$2256,Results!M$2:M$2256,"") | AS56: =_xlfn.XLOOKUP($A56,Results!$A$2:$A$2256,Results!N$2:N$2256,"") | ... BE56: =_xlfn.XLOOKUP($A56,Results!$A$2:$A$2256,Results!Z$2:Z$2256,"")
A57: 905734 | B57: 281563 | C57: NULL | D57: S007844443.001 | E57: =VLOOKUP(F57,'RPA Vendor Data '!F48:$G$2418,2) -> INDEPENDENT ELECTRIC | F57: 14376 | G57: 1 | H57: WIC. HCFAP 5858-42-00 12/2 STR 250C BLK WHT GRN W/#10 ALUM BOND ALUM JKT - STOCK IN CHINO, CA (PLUS FREIGHT) - *Procured Item* | I57: 250 | J57: M | K57: E | L57: 1.29074 | M57: GENERIC WIRE | N57: HCFAP 5858-42-00 | O57: NULL | P57: NULL | Q57: NULL | R57: 322.69 | S57: 45744.46 | T57: PA_SRDC | U57: 45744.244 | V57: PAUSER | W57: NULL | X57: 0 | Y57: 201 | Z57: NULL | AA57: NULL | AB57: NULL | AC57: GENERIC WIRE | AD57: GENERIC WIRE | AE57: AI | AF57: 26121500 | AG57: https://usa.databasesets.com/unspsc/commodity/26121614 | AI57: MATERIAL | AJ57: =VLOOKUP(A57,'Classification Test Result'!$A$2:$D$2428,4,FALSE) -> #N/A | AL57: =_xlfn.XLOOKUP($A57,Results!$A$2:$A$2256,Results!G$2:G$2256,"") -> 336533 | AM57: =_xlfn.XLOOKUP($A57,Results!$A$2:$A$2256,Results!H$2:H$2256,"") -> 58584200 | AN57: =_xlfn.XLOOKUP($A57,Results!$A$2:$A$2256,Results!I$2:I$2256,"") -> AFC CABLE SYSTEMS | AO57: =_xlfn.XLOOKUP($A57,Results!$A$2:$A$2256,Results!J$2:J$2256,"") -> 077680259226 | AP57: =_xlfn.XLOOKUP($A57,Results!$A$2:$A$2256,Results!K$2:K$2256,"") -> 26121600 | AQ57: =_xlfn.XLOOKUP($A57,Results!$A$2:$A$2256,Results!L$2:L$2256,"") -> AK10085157 | AR57: =_xlfn.XLOOKUP($A57,Results!$A$2:$A$2256,Results!M$2:M$2256,"") -> 479872 | AS57: =_xlfn.XLOOKUP($A57,Results!$A$2:$A$2256,Results!N$2:N$2256,"") -> AFC 5858-42-00 12-2AWG AL CABLE | ... BE57: =_xlfn.XLOOKUP($A57,Results!$A$2:$A$2256,Results!Z$2:Z$2256,"") -> 0
A58: 905735 | B58: 281304 | C58: NULL | D58: S013864675.002 | E58: =VLOOKUP(F58,'RPA Vendor Data '!F49:$G$2418,2) -> CRAWFORD ELECTRIC SUPPLY | F58: 10895 | G58: 3 | H58: WIC. THHN 8 STR GRN MR | I58: 65 | J58: m | K58: M | L58: 543.33 | M58: GENERIC WIRE | N58: WIC THHN 8 STR GRN MR | O58: NULL | P58: NULL | Q58: 98010063143 | R58: 35.32 | S58: 45744.167 | T58: PA_SRDC | U58: 45743.956 | V58: PAUSER | W58: NULL | X58: 0 | Y58: 999 | Z58: NULL | AA58: NULL | AB58: NULL | AC58: GENERIC WIRE | AD58: GENERIC WIRE | AE58: AI | AF58: - | AG58: https://www.crawfordelectricsupply.com/product/detail/22882/thhn-wire-copper-wic-thhn-8-str-grn-mr | AI58: MATERIAL | AJ58: =VLOOKUP(A58,'Classification Test Result'!$A$2:$D$2428,4,FALSE) -> #N/A | AL58: =_xlfn.XLOOKUP($A58,Results!$A$2:$A$2256,Results!G$2:G$2256,"") | AM58: =_xlfn.XLOOKUP($A58,Results!$A$2:$A$2256,Results!H$2:H$2256,"") | AN58: =_xlfn.XLOOKUP($A58,Results!$A$2:$A$2256,Results!I$2:I$2256,"") | AO58: =_xlfn.XLOOKUP($A58,Results!$A$2:$A$2256,Results!J$2:J$2256,"") | AP58: =_xlfn.XLOOKUP($A58,Results!$A$2:$A$2256,Results!K$2:K$2256,"") | AQ58: =_xlfn.XLOOKUP($A58,Results!$A$2:$A$2256,Results!L$2:L$2256,"") | AR58: =_xlfn.XLOOKUP($A58,Results!$A$2:$A$2256,Results!M$2:M$2256,"") | AS58: =_xlfn.XLOOKUP($A58,Results!$A$2:$A$2256,Results!N$2:N$2256,"") | ... BE58: =_xlfn.XLOOKUP($A58,Results!$A$2:$A$2256,Results!Z$2:Z$2256,"")
A59: 905736 | B59: 281304 | C59: NULL | D59: S013864675.002 | E59: =VLOOKUP(F59,'RPA Vendor Data '!F50:$G$2418,2) -> CRAWFORD ELECTRIC SUPPLY | F59: 10895 | G59: 2 | H59: WIC. THHN 8 STR GRN MR | I59: 50 | J59: m | K59: M | L59: 543.33 | M59: GENERIC WIRE | N59: WIC THHN 8 STR GRN MR | O59: NULL | P59: NULL | Q59: 98010063143 | R59: 27.17 | S59: 45744.167 | T59: PA_SRDC | U59: 45743.956 | V59: PAUSER | W59: NULL | X59: 0 | Y59: 999 | Z59: NULL | AA59: NULL | AB59: NULL | AC59: GENERIC WIRE | AD59: GENERIC WIRE | AE59: AI | AF59: - | AG59: https://www.crawfordelectricsupply.com/product/detail/22882/thhn-wire-copper-wic-thhn-8-str-grn-mr | AI59: MATERIAL | AJ59: =VLOOKUP(A59,'Classification Test Result'!$A$2:$D$2428,4,FALSE) -> #N/A | AL59: =_xlfn.XLOOKUP($A59,Results!$A$2:$A$2256,Results!G$2:G$2256,"") | AM59: =_xlfn.XLOOKUP($A59,Results!$A$2:$A$2256,Results!H$2:H$2256,"") | AN59: =_xlfn.XLOOKUP($A59,Results!$A$2:$A$2256,Results!I$2:I$2256,"") | AO59: =_xlfn.XLOOKUP($A59,Results!$A$2:$A$2256,Results!J$2:J$2256,"") | AP59: =_xlfn.XLOOKUP($A59,Results!$A$2:$A$2256,Results!K$2:K$2256,"") | AQ59: =_xlfn.XLOOKUP($A59,Results!$A$2:$A$2256,Results!L$2:L$2256,"") | AR59: =_xlfn.XLOOKUP($A59,Results!$A$2:$A$2256,Results!M$2:M$2256,"") | AS59: =_xlfn.XLOOKUP($A59,Results!$A$2:$A$2256,Results!N$2:N$2256,"") | ... BE59: =_xlfn.XLOOKUP($A59,Results!$A$2:$A$2256,Results!Z$2:Z$2256,"")
A60: 905737 | B60: 281304 | C60: NULL | D60: S013864675.002 | E60: =VLOOKUP(F60,'RPA Vendor Data '!F51:$G$2418,2) -> CRAWFORD ELECTRIC SUPPLY | F60: 10895 | G60: 1 | H60: WIC. THHN 8 STR GRN MR | I60: 160 | J60: m | K60: M | L60: 543.33 | M60: GENERIC WIRE | N60: WIC THHN 8 STR GRN MR | O60: NULL | P60: NULL | Q60: 98010063143 | R60: 86.93 | S60: 45744.167 | T60: PA_SRDC | U60: 45743.956 | V60: PAUSER | W60: NULL | X60: 0 | Y60: 999 | Z60: NULL | AA60: NULL | AB60: NULL | AC60: GENERIC WIRE | AD60: GENERIC WIRE | AE60: AI | AF60: - | AG60: https://www.crawfordelectricsupply.com/product/detail/22882/thhn-wire-copper-wic-thhn-8-str-grn-mr | AI60: MATERIAL | AJ60: =VLOOKUP(A60,'Classification Test Result'!$A$2:$D$2428,4,FALSE) -> #N/A | AL60: =_xlfn.XLOOKUP($A60,Results!$A$2:$A$2256,Results!G$2:G$2256,"") | AM60: =_xlfn.XLOOKUP($A60,Results!$A$2:$A$2256,Results!H$2:H$2256,"") | AN60: =_xlfn.XLOOKUP($A60,Results!$A$2:$A$2256,Results!I$2:I$2256,"") | AO60: =_xlfn.XLOOKUP($A60,Results!$A$2:$A$2256,Results!J$2:J$2256,"") | AP60: =_xlfn.XLOOKUP($A60,Results!$A$2:$A$2256,Results!K$2:K$2256,"") | AQ60: =_xlfn.XLOOKUP($A60,Results!$A$2:$A$2256,Results!L$2:L$2256,"") | AR60: =_xlfn.XLOOKUP($A60,Results!$A$2:$A$2256,Results!M$2:M$2256,"") | AS60: =_xlfn.XLOOKUP($A60,Results!$A$2:$A$2256,Results!N$2:N$2256,"") | ... BE60: =_xlfn.XLOOKUP($A60,Results!$A$2:$A$2256,Results!Z$2:Z$2256,"")
A61: 905738 | B61: 281304 | C61: NULL | D61: S013864675.002 | E61: =VLOOKUP(F61,'RPA Vendor Data '!F52:$G$2418,2) -> CRAWFORD ELECTRIC SUPPLY | F61: 10895 | G61: 4 | H61: WIC. THHN 8 STR GRN MR | I61: 80 | J61: m | K61: M | L61: 543.33 | M61: GENERIC WIRE | N61: WIC THHN 8 STR GRN MR | O61: NULL | P61: NULL | Q61: 98010063143 | R61: 43.47 | S61: 45744.167 | T61: PA_SRDC | U61: 45743.956 | V61: PAUSER | W61: NULL | X61: 0 | Y61: 999 | Z61: NULL | AA61: NULL | AB61: NULL | AC61: GENERIC WIRE | AD61: GENERIC WIRE | AE61: AI | AF61: - | AG61: https://www.crawfordelectricsupply.com/product/detail/22882/thhn-wire-copper-wic-thhn-8-str-grn-mr | AI61: MATERIAL | AJ61: =VLOOKUP(A61,'Classification Test Result'!$A$2:$D$2428,4,FALSE) -> #N/A | AL61: =_xlfn.XLOOKUP($A61,Results!$A$2:$A$2256,Results!G$2:G$2256,"") | AM61: =_xlfn.XLOOKUP($A61,Results!$A$2:$A$2256,Results!H$2:H$2256,"") | AN61: =_xlfn.XLOOKUP($A61,Results!$A$2:$A$2256,Results!I$2:I$2256,"") | AO61: =_xlfn.XLOOKUP($A61,Results!$A$2:$A$2256,Results!J$2:J$2256,"") | AP61: =_xlfn.XLOOKUP($A61,Results!$A$2:$A$2256,Results!K$2:K$2256,"") | AQ61: =_xlfn.XLOOKUP($A61,Results!$A$2:$A$2256,Results!L$2:L$2256,"") | AR61: =_xlfn.XLOOKUP($A61,Results!$A$2:$A$2256,Results!M$2:M$2256,"") | AS61: =_xlfn.XLOOKUP($A61,Results!$A$2:$A$2256,Results!N$2:N$2256,"") | ... BE61: =_xlfn.XLOOKUP($A61,Results!$A$2:$A$2256,Results!Z$2:Z$2256,"")
A62: 905739 | B62: 281304 | C62: NULL | D62: S013864675.002 | E62: =VLOOKUP(F62,'RPA Vendor Data '!F53:$G$2418,2) -> CRAWFORD ELECTRIC SUPPLY | F62: 10895 | G62: 10 | H62: WIC. THHN 6 STR WHT MR | I62: 240 | J62: m | K62: M | L62: 835.94 | M62: GENERIC WIRE | N62: WIC THHN 6 STR WHT MR | O62: NULL | P62: NULL | Q62: 98010063162 | R62: 200.63 | S62: 45744.167 | T62: PA_SRDC | U62: 45743.956 | V62: PAUSER | W62: NULL | X62: 0 | Y62: 999 | Z62: NULL | AA62: NULL | AB62: NULL | AC62: GENERIC WIRE | AD62: GENERIC WIRE | AE62: AI | AF62: - | AG62: https://www.crawfordelectricsupply.com/product/detail/22881/thhn-wire-copper-wic-thhn-6-str-wht-mr | AI62: MATERIAL | AJ62: =VLOOKUP(A62,'Classification Test Result'!$A$2:$D$2428,4,FALSE) -> #N/A | AL62: =_xlfn.XLOOKUP($A62,Results!$A$2:$A$2256,Results!G$2:G$2256,"") -> 0 | AM62: =_xlfn.XLOOKUP($A62,Results!$A$2:$A$2256,Results!H$2:H$2256,"") -> 0 | AN62: =_xlfn.XLOOKUP($A62,Results!$A$2:$A$2256,Results!I$2:I$2256,"") -> 0 | AO62: =_xlfn.XLOOKUP($A62,Results!$A$2:$A$2256,Results!J$2:J$2256,"") -> 0 | AP62: =_xlfn.XLOOKUP($A62,Results!$A$2:$A$2256,Results!K$2:K$2256,"") -> 0 | AQ62: =_xlfn.XLOOKUP($A62,Results!$A$2:$A$2256,Results!L$2:L$2256,"") -> 0 | AR62: =_xlfn.XLOOKUP($A62,Results!$A$2:$A$2256,Results!M$2:M$2256,"") -> 0 | AS62: =_xlfn.XLOOKUP($A62,Results!$A$2:$A$2256,Results!N$2:N$2256,"") -> 0 | ... BE62: =_xlfn.XLOOKUP($A62,Results!$A$2:$A$2256,Results!Z$2:Z$2256,"") -> TRUE
A63: 905740 | B63: 281304 | C63: NULL | D63: S013864675.002 | E63: =VLOOKUP(F63,'RPA Vendor Data '!F54:$G$2418,2) -> CRAWFORD ELECTRIC SUPPLY | F63: 10895 | G63: 9 | H63: WIC. THHN 6 STR RED MR | I63: 240 | J63: m | K63: M | L63: 835.94 | M63: GENERIC WIRE | N63: WIC THHN 6 STR RED MR | O63: NULL | P63: NULL | Q63: 98010013170 | R63: 200.63 | S63: 45744.167 | T63: PA_SRDC | U63: 45743.956 | V63: PAUSER | W63: NULL | X63: 0 | Y63: 999 | Z63: NULL | AA63: NULL | AB63: NULL | AC63: GENERIC WIRE | AD63: GENERIC WIRE | AE63: AI | AF63: - | AG63: https://www.crawfordelectricsupply.com/product/detail/24631/thhn-wire-copper-wic-thhn-6-str-red-mr | AI63: MATERIAL | AJ63: =VLOOKUP(A63,'Classification Test Result'!$A$2:$D$2428,4,FALSE) -> #N/A | AL63: =_xlfn.XLOOKUP($A63,Results!$A$2:$A$2256,Results!G$2:G$2256,"") -> 0 | AM63: =_xlfn.XLOOKUP($A63,Results!$A$2:$A$2256,Results!H$2:H$2256,"") -> 0 | AN63: =_xlfn.XLOOKUP($A63,Results!$A$2:$A$2256,Results!I$2:I$2256,"") -> 0 | AO63: =_xlfn.XLOOKUP($A63,Results!$A$2:$A$2256,Results!J$2:J$2256,"") -> 0 | AP63: =_xlfn.XLOOKUP($A63,Results!$A$2:$A$2256,Results!K$2:K$2256,"") -> 0 | AQ63: =_xlfn.XLOOKUP($A63,Results!$A$2:$A$2256,Results!L$2:L$2256,"") -> 0 | AR63: =_xlfn.XLOOKUP($A63,Results!$A$2:$A$2256,Results!M$2:M$2256,"") -> 0 | AS63: =_xlfn.XLOOKUP($A63,Results!$A$2:$A$2256,Results!N$2:N$2256,"") -> 0 | ... BE63: =_xlfn.XLOOKUP($A63,Results!$A$2:$A$2256,Results!Z$2:Z$2256,"") -> TRUE
A64: 905741 | B64: 281304 | C64: NULL | D64: S013864675.002 | E64: =VLOOKUP(F64,'RPA Vendor Data '!F55:$G$2418,2) -> CRAWFORD ELECTRIC SUPPLY | F64: 10895 | G64: 8 | H64: WIC. THHN 6 STR BLK MR | I64: 240 | J64: m | K64: M | L64: 835.94 | M64: GENERIC WIRE | N64: WIC THHN 6 STR BLK MR | O64: NULL | P64: NULL | Q64: 98010013150 | R64: 200.63 | S64: 45744.167 | T64: PA_SRDC | U64: 45743.956 | V64: PAUSER | W64: NULL | X64: 0 | Y64: 999 | Z64: NULL | AA64: NULL | AB64: NULL | AC64: GENERIC WIRE | AD64: GENERIC WIRE | AE64: AI | AF64: - | AG64: https://www.crawfordelectricsupply.com/product/detail/22800/thhn-wire-copper-wic-thhn-6-str-blk-mr | AI64: MATERIAL | AJ64: =VLOOKUP(A64,'Classification Test Result'!$A$2:$D$2428,4,FALSE) -> #N/A | AL64: =_xlfn.XLOOKUP($A64,Results!$A$2:$A$2256,Results!G$2:G$2256,"") -> 0 | AM64: =_xlfn.XLOOKUP($A64,Results!$A$2:$A$2256,Results!H$2:H$2256,"") -> 0 | AN64: =_xlfn.XLOOKUP($A64,Results!$A$2:$A$2256,Results!I$2:I$2256,"") -> 0 | AO64: =_xlfn.XLOOKUP($A64,Results!$A$2:$A$2256,Results!J$2:J$2256,"") -> 0 | AP64: =_xlfn.XLOOKUP($A64,Results!$A$2:$A$2256,Results!K$2:K$2256,"") -> 0 | AQ64: =_xlfn.XLOOKUP($A64,Results!$A$2:$A$2256,Results!L$2:L$2256,"") -> 0 | AR64: =_xlfn.XLOOKUP($A64,Results!$A$2:$A$2256,Results!M$2:M$2256,"") -> 0 | AS64: =_xlfn.XLOOKUP($A64,Results!$A$2:$A$2256,Results!N$2:N$2256,"") -> 0 | ... BE64: =_xlfn.XLOOKUP($A64,Results!$A$2:$A$2256,Results!Z$2:Z$2256,"") -> TRUE
A65: 905742 | B65: 281304 | C65: NULL | D65: S013864675.002 | E65: =VLOOKUP(F65,'RPA Vendor Data '!F56:$G$2418,2) -> CRAWFORD ELECTRIC SUPPLY | F65: 10895 | G65: 19 | H65: WIC. THHN 2 STR WHT MR | I65: 80 | J65: m | K65: M | L65: 2018.71 | M65: GENERIC WIRE | N65: WIC THHN 2 STR WHT MR | O65: NULL | P65: NULL | Q65: 98010023313 | R65: 161.5 | S65: 45744.167 | T65: PA_SRDC | U65: 45743.956 | V65: PAUSER | W65: NULL | X65: 0 | Y65: 999 | Z65: NULL | AA65: NULL | AB65: NULL | AC65: GENERIC WIRE | AD65: GENERIC WIRE | AE65: AI | AF65: - | AG65: https://www.crawfordelectricsupply.com/product/detail/22763/thhn-wire-copper-wic-thhn-2-str-wht-mr | AI65: MATERIAL | AJ65: =VLOOKUP(A65,'Classification Test Result'!$A$2:$D$2428,4,FALSE) -> #N/A | AL65: =_xlfn.XLOOKUP($A65,Results!$A$2:$A$2256,Results!G$2:G$2256,"") -> 0 | AM65: =_xlfn.XLOOKUP($A65,Results!$A$2:$A$2256,Results!H$2:H$2256,"") -> 0 | AN65: =_xlfn.XLOOKUP($A65,Results!$A$2:$A$2256,Results!I$2:I$2256,"") -> 0 | AO65: =_xlfn.XLOOKUP($A65,Results!$A$2:$A$2256,Results!J$2:J$2256,"") -> 0 | AP65: =_xlfn.XLOOKUP($A65,Results!$A$2:$A$2256,Results!K$2:K$2256,"") -> 0 | AQ65: =_xlfn.XLOOKUP($A65,Results!$A$2:$A$2256,Results!L$2:L$2256,"") -> 0 | AR65: =_xlfn.XLOOKUP($A65,Results!$A$2:$A$2256,Results!M$2:M$2256,"") -> 0 | AS65: =_xlfn.XLOOKUP($A65,Results!$A$2:$A$2256,Results!N$2:N$2256,"") -> 0 | ... BE65: =_xlfn.XLOOKUP($A65,Results!$A$2:$A$2256,Results!Z$2:Z$2256,"") -> TRUE
A66: 905743 | B66: 281304 | C66: NULL | D66: S013864675.002 | E66: =VLOOKUP(F66,'RPA Vendor Data '!F57:$G$2418,2) -> CRAWFORD ELECTRIC SUPPLY | F66: 10895 | G66: 7 | H66: WIC. THHN 2 STR WHT MR | I66: 150 | J66: m | K66: M | L66: 2018.71 | M66: GENERIC WIRE | N66: WIC THHN 2 STR WHT MR | O66: NULL | P66: NULL | Q66: 98010023313 | R66: 302.81 | S66: 45744.167 | T66: PA_SRDC | U66: 45743.956 | V66: PAUSER | W66: NULL | X66: 0 | Y66: 999 | Z66: NULL | AA66: NULL | AB66: NULL | AC66: GENERIC WIRE | AD66: GENERIC WIRE | AE66: AI | AF66: - | AG66: https://www.crawfordelectricsupply.com/product/detail/22763/thhn-wire-copper-wic-thhn-2-str-wht-mr | AI66: MATERIAL | AJ66: =VLOOKUP(A66,'Classification Test Result'!$A$2:$D$2428,4,FALSE) -> #N/A | AL66: =_xlfn.XLOOKUP($A66,Results!$A$2:$A$2256,Results!G$2:G$2256,"") -> 0 | AM66: =_xlfn.XLOOKUP($A66,Results!$A$2:$A$2256,Results!H$2:H$2256,"") -> 0 | AN66: =_xlfn.XLOOKUP($A66,Results!$A$2:$A$2256,Results!I$2:I$2256,"") -> 0 | AO66: =_xlfn.XLOOKUP($A66,Results!$A$2:$A$2256,Results!J$2:J$2256,"") -> 0 | AP66: =_xlfn.XLOOKUP($A66,Results!$A$2:$A$2256,Results!K$2:K$2256,"") -> 0 | AQ66: =_xlfn.XLOOKUP($A66,Results!$A$2:$A$2256,Results!L$2:L$2256,"") -> 0 | AR66: =_xlfn.XLOOKUP($A66,Results!$A$2:$A$2256,Results!M$2:M$2256,"") -> 0 | AS66: =_xlfn.XLOOKUP($A66,Results!$A$2:$A$2256,Results!N$2:N$2256,"") -> 0 | ... BE66: =_xlfn.XLOOKUP($A66,Results!$A$2:$A$2256,Results!Z$2:Z$2256,"") -> TRUE
A67: 905744 | B67: 281304 | C67: NULL | D67: S013864675.002 | E67: =VLOOKUP(F67,'RPA Vendor Data '!F58:$G$2418,2) -> CRAWFORD ELECTRIC SUPPLY | F67: 10895 | G67: 16 | H67: WIC. THHN 2 STR WHT MR | I67: 65 | J67: EA | K67: M | L67: 2018.71 | M67: GENERIC WIRE | N67: WIC THHN 2 STR WHT MR | O67: NULL | P67: NULL | Q67: 98010023313 | R67: 131.22 | S67: 45744.167 | T67: PA_SRDC | U67: 45743.956 | V67: PAUSER | W67: NULL | X67: 0 | Y67: 999 | Z67: NULL | AA67: NULL | AB67: NULL | AC67: GENERIC WIRE | AD67: GENERIC WIRE | AE67: AI | AF67: - | AG67: https://www.crawfordelectricsupply.com/product/detail/22763/thhn-wire-copper-wic-thhn-2-str-wht-mr | AI67: MATERIAL | AJ67: =VLOOKUP(A67,'Classification Test Result'!$A$2:$D$2428,4,FALSE) -> #N/A | AL67: =_xlfn.XLOOKUP($A67,Results!$A$2:$A$2256,Results!G$2:G$2256,"") -> 0 | AM67: =_xlfn.XLOOKUP($A67,Results!$A$2:$A$2256,Results!H$2:H$2256,"") -> 0 | AN67: =_xlfn.XLOOKUP($A67,Results!$A$2:$A$2256,Results!I$2:I$2256,"") -> 0 | AO67: =_xlfn.XLOOKUP($A67,Results!$A$2:$A$2256,Results!J$2:J$2256,"") -> 0 | AP67: =_xlfn.XLOOKUP($A67,Results!$A$2:$A$2256,Results!K$2:K$2256,"") -> 0 | AQ67: =_xlfn.XLOOKUP($A67,Results!$A$2:$A$2256,Results!L$2:L$2256,"") -> 0 | AR67: =_xlfn.XLOOKUP($A67,Results!$A$2:$A$2256,Results!M$2:M$2256,"") -> 0 | AS67: =_xlfn.XLOOKUP($A67,Results!$A$2:$A$2256,Results!N$2:N$2256,"") -> 0 | ... BE67: =_xlfn.XLOOKUP($A67,Results!$A$2:$A$2256,Results!Z$2:Z$2256,"") -> TRUE
A68: 905745 | B68: 281304 | C68: NULL | D68: S013864675.002 | E68: =VLOOKUP(F68,'RPA Vendor Data '!F59:$G$2418,2) -> CRAWFORD ELECTRIC SUPPLY | F68: 10895 | G68: 13 | H68: WIC. THHN 2 STR WHT MR | I68: 50 | J68: m | K68: M | L68: 2018.71 | M68: GENERIC WIRE | N68: WIC THHN 2 STR WHT MR | O68: NULL | P68: NULL | Q68: 98010023313 | R68: 100.94 | S68: 45744.167 | T68: PA_SRDC | U68: 45743.956 | V68: PAUSER | W68: NULL | X68: 0 | Y68: 999 | Z68: NULL | AA68: NULL | AB68: NULL | AC68: GENERIC WIRE | AD68: GENERIC WIRE | AE68: AI | AF68: - | AG68: https://www.crawfordelectricsupply.com/product/detail/22763/thhn-wire-copper-wic-thhn-2-str-wht-mr | AI68: MATERIAL | AJ68: =VLOOKUP(A68,'Classification Test Result'!$A$2:$D$2428,4,FALSE) -> #N/A | AL68: =_xlfn.XLOOKUP($A68,Results!$A$2:$A$2256,Results!G$2:G$2256,"") -> 0 | AM68: =_xlfn.XLOOKUP($A68,Results!$A$2:$A$2256,Results!H$2:H$2256,"") -> 0 | AN68: =_xlfn.XLOOKUP($A68,Results!$A$2:$A$2256,Results!I$2:I$2256,"") -> 0 | AO68: =_xlfn.XLOOKUP($A68,Results!$A$2:$A$2256,Results!J$2:J$2256,"") -> 0 | AP68: =_xlfn.XLOOKUP($A68,Results!$A$2:$A$2256,Results!K$2:K$2256,"") -> 0 | AQ68: =_xlfn.XLOOKUP($A68,Results!$A$2:$A$2256,Results!L$2:L$2256,"") -> 0 | AR68: =_xlfn.XLOOKUP($A68,Results!$A$2:$A$2256,Results!M$2:M$2256,"") -> 0 | AS68: =_xlfn.XLOOKUP($A68,Results!$A$2:$A$2256,Results!N$2:N$2256,"") -> 0 | ... BE68: =_xlfn.XLOOKUP($A68,Results!$A$2:$A$2256,Results!Z$2:Z$2256,"") -> TRUE
A69: 905746 | B69: 281304 | C69: NULL | D69: S013864675.002 | E69: =VLOOKUP(F69,'RPA Vendor Data '!F60:$G$2418,2) -> CRAWFORD ELECTRIC SUPPLY | F69: 10895 | G69: 12 | H69: WIC. THHN 2 STR RED MR | I69: 50 | J69: m | K69: M | L69: 2018.71 | M69: GENERIC WIRE | N69: WIC THHN 2 STR RED MR | O69: NULL | P69: NULL | Q69: 98010023323 | R69: 100.94 | S69: 45744.167 | T69: PA_SRDC | U69: 45743.956 | V69: PAUSER | W69: NULL | X69: 0 | Y69: 999 | Z69: NULL | AA69: NULL | AB69: NULL | AC69: GENERIC WIRE | AD69: GENERIC WIRE | AE69: AI | AF69: - | AG69: https://www.crawfordelectricsupply.com/product/detail/22762/thhn-wire-copper-wic-thhn-2-str-red-mr | AI69: MATERIAL | AJ69: =VLOOKUP(A69,'Classification Test Result'!$A$2:$D$2428,4,FALSE) -> #N/A | AL69: =_xlfn.XLOOKUP($A69,Results!$A$2:$A$2256,Results!G$2:G$2256,"") -> 0 | AM69: =_xlfn.XLOOKUP($A69,Results!$A$2:$A$2256,Results!H$2:H$2256,"") -> 0 | AN69: =_xlfn.XLOOKUP($A69,Results!$A$2:$A$2256,Results!I$2:I$2256,"") -> 0 | AO69: =_xlfn.XLOOKUP($A69,Results!$A$2:$A$2256,Results!J$2:J$2256,"") -> 0 | AP69: =_xlfn.XLOOKUP($A69,Results!$A$2:$A$2256,Results!K$2:K$2256,"") -> 0 | AQ69: =_xlfn.XLOOKUP($A69,Results!$A$2:$A$2256,Results!L$2:L$2256,"") -> 0 | AR69: =_xlfn.XLOOKUP($A69,Results!$A$2:$A$2256,Results!M$2:M$2256,"") -> 0 | AS69: =_xlfn.XLOOKUP($A69,Results!$A$2:$A$2256,Results!N$2:N$2256,"") -> 0 | ... BE69: =_xlfn.XLOOKUP($A69,Results!$A$2:$A$2256,Results!Z$2:Z$2256,"") -> TRUE
A70: 905747 | B70: 281304 | C70: NULL | D70: S013864675.002 | E70: =VLOOKUP(F70,'RPA Vendor Data '!F65:$G$2418,2) -> CRAWFORD ELECTRIC SUPPLY | F70: 10895 | G70: 18 | H70: WIC. THHN 2 STR RED MR | I70: 80 | J70: m | K70: M | L70: 2018.71 | M70: GENERIC WIRE | N70: WIC THHN 2 STR RED MR | O70: NULL | P70: NULL | Q70: 98010023323 | R70: 161.5 | S70: 45744.167 | T70: PA_SRDC | U70: 45743.956 | V70: PAUSER | W70: NULL | X70: 0 | Y70: 999 | Z70: NULL | AA70: NULL | AB70: NULL | AC70: GENERIC WIRE | AD70: GENERIC WIRE | AE70: AI | AF70: - | AG70: https://www.crawfordelectricsupply.com/product/detail/22762/thhn-wire-copper-wic-thhn-2-str-red-mr | AI70: MATERIAL | AJ70: =VLOOKUP(A70,'Classification Test Result'!$A$2:$D$2428,4,FALSE) -> #N/A | AL70: =_xlfn.XLOOKUP($A70,Results!$A$2:$A$2256,Results!G$2:G$2256,"") -> 0 | AM70: =_xlfn.XLOOKUP($A70,Results!$A$2:$A$2256,Results!H$2:H$2256,"") -> 0 | AN70: =_xlfn.XLOOKUP($A70,Results!$A$2:$A$2256,Results!I$2:I$2256,"") -> 0 | AO70: =_xlfn.XLOOKUP($A70,Results!$A$2:$A$2256,Results!J$2:J$2256,"") -> 0 | AP70: =_xlfn.XLOOKUP($A70,Results!$A$2:$A$2256,Results!K$2:K$2256,"") -> 0 | AQ70: =_xlfn.XLOOKUP($A70,Results!$A$2:$A$2256,Results!L$2:L$2256,"") -> 0 | AR70: =_xlfn.XLOOKUP($A70,Results!$A$2:$A$2256,Results!M$2:M$2256,"") -> 0 | AS70: =_xlfn.XLOOKUP($A70,Results!$A$2:$A$2256,Results!N$2:N$2256,"") -> 0 | ... BE70: =_xlfn.XLOOKUP($A70,Results!$A$2:$A$2256,Results!Z$2:Z$2256,"") -> TRUE
A71: 905748 | B71: 281304 | C71: NULL | D71: S013864675.002 | E71: =VLOOKUP(F71,'RPA Vendor Data '!F66:$G$2418,2) -> CRAWFORD ELECTRIC SUPPLY | F71: 10895 | G71: 15 | H71: WIC. THHN 2 STR RED MR | I71: 65 | J71: m | K71: M | L71: 2018.71 | M71: GENERIC WIRE | N71: WIC THHN 2 STR RED MR | O71: NULL | P71: NULL | Q71: 98010023323 | R71: 131.22 | S71: 45744.167 | T71: PA_SRDC | U71: 45743.956 | V71: PAUSER | W71: NULL | X71: 0 | Y71: 999 | Z71: NULL | AA71: NULL | AB71: NULL | AC71: GENERIC WIRE | AD71: GENERIC WIRE | AE71: AI | AF71: - | AG71: https://www.crawfordelectricsupply.com/product/detail/22762/thhn-wire-copper-wic-thhn-2-str-red-mr | AI71: MATERIAL | AJ71: =VLOOKUP(A71,'Classification Test Result'!$A$2:$D$2428,4,FALSE) -> #N/A | AL71: =_xlfn.XLOOKUP($A71,Results!$A$2:$A$2256,Results!G$2:G$2256,"") -> 0 | AM71: =_xlfn.XLOOKUP($A71,Results!$A$2:$A$2256,Results!H$2:H$2256,"") -> 0 | AN71: =_xlfn.XLOOKUP($A71,Results!$A$2:$A$2256,Results!I$2:I$2256,"") -> 0 | AO71: =_xlfn.XLOOKUP($A71,Results!$A$2:$A$2256,Results!J$2:J$2256,"") -> 0 | AP71: =_xlfn.XLOOKUP($A71,Results!$A$2:$A$2256,Results!K$2:K$2256,"") -> 0 | AQ71: =_xlfn.XLOOKUP($A71,Results!$A$2:$A$2256,Results!L$2:L$2256,"") -> 0 | AR71: =_xlfn.XLOOKUP($A71,Results!$A$2:$A$2256,Results!M$2:M$2256,"") -> 0 | AS71: =_xlfn.XLOOKUP($A71,Results!$A$2:$A$2256,Results!N$2:N$2256,"") -> 0 | ... BE71: =_xlfn.XLOOKUP($A71,Results!$A$2:$A$2256,Results!Z$2:Z$2256,"") -> TRUE
A72: 905749 | B72: 281304 | C72: NULL | D72: S013864675.002 | E72: =VLOOKUP(F72,'RPA Vendor Data '!F67:$G$2418,2) -> CRAWFORD ELECTRIC SUPPLY | F72: 10895 | G72: 6 | H72: WIC. THHN 2 STR RED MR | I72: 150 | J72: m | K72: M | L72: 2018.71 | M72: GENERIC WIRE | N72: WIC THHN 2 STR RED MR | O72: NULL | P72: NULL | Q72: 98010023323 | R72: 302.81 | S72: 45744.167 | T72: PA_SRDC | U72: 45743.956 | V72: PAUSER | W72: NULL | X72: 0 | Y72: 999 | Z72: NULL | AA72: NULL | AB72: NULL | AC72: GENERIC WIRE | AD72: GENERIC WIRE | AE72: AI | AF72: - | AG72: https://www.crawfordelectricsupply.com/product/detail/22762/thhn-wire-copper-wic-thhn-2-str-red-mr | AI72: MATERIAL | AJ72: =VLOOKUP(A72,'Classification Test Result'!$A$2:$D$2428,4,FALSE) -> #N/A | AL72: =_xlfn.XLOOKUP($A72,Results!$A$2:$A$2256,Results!G$2:G$2256,"") -> 0 | AM72: =_xlfn.XLOOKUP($A72,Results!$A$2:$A$2256,Results!H$2:H$2256,"") -> 0 | AN72: =_xlfn.XLOOKUP($A72,Results!$A$2:$A$2256,Results!I$2:I$2256,"") -> 0 | AO72: =_xlfn.XLOOKUP($A72,Results!$A$2:$A$2256,Results!J$2:J$2256,"") -> 0 | AP72: =_xlfn.XLOOKUP($A72,Results!$A$2:$A$2256,Results!K$2:K$2256,"") -> 0 | AQ72: =_xlfn.XLOOKUP($A72,Results!$A$2:$A$2256,Results!L$2:L$2256,"") -> 0 | AR72: =_xlfn.XLOOKUP($A72,Results!$A$2:$A$2256,Results!M$2:M$2256,"") -> 0 | AS72: =_xlfn.XLOOKUP($A72,Results!$A$2:$A$2256,Results!N$2:N$2256,"") -> 0 | ... BE72: =_xlfn.XLOOKUP($A72,Results!$A$2:$A$2256,Results!Z$2:Z$2256,"") -> TRUE
A73: 905750 | B73: 281304 | C73: NULL | D73: S013864675.002 | E73: =VLOOKUP(F73,'RPA Vendor Data '!F68:$G$2418,2) -> CRAWFORD ELECTRIC SUPPLY | F73: 10895 | G73: 14 | H73: WIC. THHN 2 STR BLK MR | I73: 65 | J73: m | K73: M | L73: 2018.71 | M73: GENERIC WIRE | N73: WIC THHN 2 STR BLK MR | O73: NULL | P73: NULL | Q73: 98010023303 | R73: 131.22 | S73: 45744.167 | T73: PA_SRDC | U73: 45743.956 | V73: PAUSER | W73: NULL | X73: 0 | Y73: 999 | Z73: NULL | AA73: NULL | AB73: NULL | AC73: GENERIC WIRE | AD73: GENERIC WIRE | AE73: AI | AF73: - | AG73: https://www.crawfordelectricsupply.com/product/detail/22757/thhn-wire-copper-wic-thhn-2-str-blk-mr | AI73: MATERIAL | AJ73: =VLOOKUP(A73,'Classification Test Result'!$A$2:$D$2428,4,FALSE) -> #N/A | AL73: =_xlfn.XLOOKUP($A73,Results!$A$2:$A$2256,Results!G$2:G$2256,"") -> 0 | AM73: =_xlfn.XLOOKUP($A73,Results!$A$2:$A$2256,Results!H$2:H$2256,"") -> 0 | AN73: =_xlfn.XLOOKUP($A73,Results!$A$2:$A$2256,Results!I$2:I$2256,"") -> 0 | AO73: =_xlfn.XLOOKUP($A73,Results!$A$2:$A$2256,Results!J$2:J$2256,"") -> 0 | AP73: =_xlfn.XLOOKUP($A73,Results!$A$2:$A$2256,Results!K$2:K$2256,"") -> 0 | AQ73: =_xlfn.XLOOKUP($A73,Results!$A$2:$A$2256,Results!L$2:L$2256,"") -> 0 | AR73: =_xlfn.XLOOKUP($A73,Results!$A$2:$A$2256,Results!M$2:M$2256,"") -> 0 | AS73: =_xlfn.XLOOKUP($A73,Results!$A$2:$A$2256,Results!N$2:N$2256,"") -> 0 | ... BE73: =_xlfn.XLOOKUP($A73,Results!$A$2:$A$2256,Results!Z$2:Z$2256,"") -> TRUE
A74: 905751 | B74: 281304 | C74: NULL | D74: S013864675.002 | E74: =VLOOKUP(F74,'RPA Vendor Data '!F69:$G$2418,2) -> CRAWFORD ELECTRIC SUPPLY | F74: 10895 | G74: 17 | H74: WIC. THHN 2 STR BLK MR | I74: 80 | J74: m | K74: M | L74: 2018.71 | M74: GENERIC WIRE | N74: WIC THHN 2 STR BLK MR | O74: NULL | P74: NULL | Q74: 98010023303 | R74: 161.5 | S74: 45744.167 | T74: PA_SRDC | U74: 45743.956 | V74: PAUSER | W74: NULL | X74: 0 | Y74: 999 | Z74: NULL | AA74: NULL | AB74: NULL | AC74: GENERIC WIRE | AD74: GENERIC WIRE | AE74: AI | AF74: - | AG74: https://www.crawfordelectricsupply.com/product/detail/22757/thhn-wire-copper-wic-thhn-2-str-blk-mr | AI74: MATERIAL | AJ74: =VLOOKUP(A74,'Classification Test Result'!$A$2:$D$2428,4,FALSE) -> #N/A | AL74: =_xlfn.XLOOKUP($A74,Results!$A$2:$A$2256,Results!G$2:G$2256,"") -> 0 | AM74: =_xlfn.XLOOKUP($A74,Results!$A$2:$A$2256,Results!H$2:H$2256,"") -> 0 | AN74: =_xlfn.XLOOKUP($A74,Results!$A$2:$A$2256,Results!I$2:I$2256,"") -> 0 | AO74: =_xlfn.XLOOKUP($A74,Results!$A$2:$A$2256,Results!J$2:J$2256,"") -> 0 | AP74: =_xlfn.XLOOKUP($A74,Results!$A$2:$A$2256,Results!K$2:K$2256,"") -> 0 | AQ74: =_xlfn.XLOOKUP($A74,Results!$A$2:$A$2256,Results!L$2:L$2256,"") -> 0 | AR74: =_xlfn.XLOOKUP($A74,Results!$A$2:$A$2256,Results!M$2:M$2256,"") -> 0 | AS74: =_xlfn.XLOOKUP($A74,Results!$A$2:$A$2256,Results!N$2:N$2256,"") -> 0 | ... BE74: =_xlfn.XLOOKUP($A74,Results!$A$2:$A$2256,Results!Z$2:Z$2256,"") -> TRUE
A75: 905752 | B75: 281304 | C75: NULL | D75: S013864675.002 | E75: =VLOOKUP(F75,'RPA Vendor Data '!F71:$G$2418,2) -> CRAWFORD ELECTRIC SUPPLY | F75: 10895 | G75: 11 | H75: WIC. THHN 2 STR BLK MR | I75: 50 | J75: m | K75: M | L75: 2018.71 | M75: GENERIC WIRE | N75: WIC THHN 2 STR BLK MR | O75: NULL | P75: NULL | Q75: 98010023303 | R75: 100.94 | S75: 45744.167 | T75: PA_SRDC | U75: 45743.956 | V75: PAUSER | W75: NULL | X75: 0 | Y75: 999 | Z75: NULL | AA75: NULL | AB75: NULL | AC75: GENERIC WIRE | AD75: GENERIC WIRE | AE75: AI | AF75: - | AG75: https://www.crawfordelectricsupply.com/product/detail/22757/thhn-wire-copper-wic-thhn-2-str-blk-mr | AI75: MATERIAL | AJ75: =VLOOKUP(A75,'Classification Test Result'!$A$2:$D$2428,4,FALSE) -> #N/A | AL75: =_xlfn.XLOOKUP($A75,Results!$A$2:$A$2256,Results!G$2:G$2256,"") -> 0 | AM75: =_xlfn.XLOOKUP($A75,Results!$A$2:$A$2256,Results!H$2:H$2256,"") -> 0 | AN75: =_xlfn.XLOOKUP($A75,Results!$A$2:$A$2256,Results!I$2:I$2256,"") -> 0 | AO75: =_xlfn.XLOOKUP($A75,Results!$A$2:$A$2256,Results!J$2:J$2256,"") -> 0 | AP75: =_xlfn.XLOOKUP($A75,Results!$A$2:$A$2256,Results!K$2:K$2256,"") -> 0 | AQ75: =_xlfn.XLOOKUP($A75,Results!$A$2:$A$2256,Results!L$2:L$2256,"") -> 0 | AR75: =_xlfn.XLOOKUP($A75,Results!$A$2:$A$2256,Results!M$2:M$2256,"") -> 0 | AS75: =_xlfn.XLOOKUP($A75,Results!$A$2:$A$2256,Results!N$2:N$2256,"") -> 0 | ... BE75: =_xlfn.XLOOKUP($A75,Results!$A$2:$A$2256,Results!Z$2:Z$2256,"") -> TRUE
A76: 905753 | B76: 281304 | C76: NULL | D76: S013864675.002 | E76: =VLOOKUP(F76,'RPA Vendor Data '!F72:$G$2418,2) -> CRAWFORD ELECTRIC SUPPLY | F76: 10895 | G76: 5 | H76: WIC. THHN 2 STR BLK MR | I76: 150 | J76: m | K76: M | L76: 2018.71 | M76: GENERIC WIRE | N76: WIC THHN 2 STR BLK MR | O76: NULL | P76: NULL | Q76: 98010023303 | R76: 302.81 | S76: 45744.167 | T76: PA_SRDC | U76: 45743.956 | V76: PAUSER | W76: NULL | X76: 0 | Y76: 999 | Z76: NULL | AA76: NULL | AB76: NULL | AC76: GENERIC WIRE | AD76: GENERIC WIRE | AE76: AI | AF76: - | AG76: https://www.crawfordelectricsupply.com/product/detail/22757/thhn-wire-copper-wic-thhn-2-str-blk-mr | AI76: MATERIAL | AJ76: =VLOOKUP(A76,'Classification Test Result'!$A$2:$D$2428,4,FALSE) -> #N/A | AL76: =_xlfn.XLOOKUP($A76,Results!$A$2:$A$2256,Results!G$2:G$2256,"") -> 0 | AM76: =_xlfn.XLOOKUP($A76,Results!$A$2:$A$2256,Results!H$2:H$2256,"") -> 0 | AN76: =_xlfn.XLOOKUP($A76,Results!$A$2:$A$2256,Results!I$2:I$2256,"") -> 0 | AO76: =_xlfn.XLOOKUP($A76,Results!$A$2:$A$2256,Results!J$2:J$2256,"") -> 0 | AP76: =_xlfn.XLOOKUP($A76,Results!$A$2:$A$2256,Results!K$2:K$2256,"") -> 0 | AQ76: =_xlfn.XLOOKUP($A76,Results!$A$2:$A$2256,Results!L$2:L$2256,"") -> 0 | AR76: =_xlfn.XLOOKUP($A76,Results!$A$2:$A$2256,Results!M$2:M$2256,"") -> 0 | AS76: =_xlfn.XLOOKUP($A76,Results!$A$2:$A$2256,Results!N$2:N$2256,"") -> 0 | ... BE76: =_xlfn.XLOOKUP($A76,Results!$A$2:$A$2256,Results!Z$2:Z$2256,"") -> TRUE
A77: 905754 | B77: 281305 | C77: NULL | D77: S013850074.001 | E77: =VLOOKUP(F77,'RPA Vendor Data '!F73:$G$2418,2) -> CRAWFORD ELECTRIC SUPPLY | F77: 10895 | G77: 1 | H77: WIC MCS 12/2 SOL 250C STL ARM BLK WHT GRN | I77: 250 | J77: m | K77: M | L77: 630 | M77: GENERIC WIRE | N77: WIC MCS 12/2 SOL 250C | O77: NULL | P77: NULL | Q77: 980100S5473 | R77: 157.5 | S77: 45744.167 | T77: PA_SRDC | U77: 45743.956 | V77: PAUSER | W77: NULL | X77: 3 | Y77: 999 | Z77: NULL | AA77: NULL | AB77: NULL | AC77: GENERIC WIRE | AD77: GENERIC WIRE | AE77: AI | AF77: - | AG77: https://www.crawfordelectricsupply.com/product/detail/22433/mc-cable-copper-wic-mcs-12-2-sol-250c | AI77: MATERIAL | AJ77: =VLOOKUP(A77,'Classification Test Result'!$A$2:$D$2428,4,FALSE) -> #N/A | AL77: =_xlfn.XLOOKUP($A77,Results!$A$2:$A$2256,Results!G$2:G$2256,"") | AM77: =_xlfn.XLOOKUP($A77,Results!$A$2:$A$2256,Results!H$2:H$2256,"") | AN77: =_xlfn.XLOOKUP($A77,Results!$A$2:$A$2256,Results!I$2:I$2256,"") | AO77: =_xlfn.XLOOKUP($A77,Results!$A$2:$A$2256,Results!J$2:J$2256,"") | AP77: =_xlfn.XLOOKUP($A77,Results!$A$2:$A$2256,Results!K$2:K$2256,"") | AQ77: =_xlfn.XLOOKUP($A77,Results!$A$2:$A$2256,Results!L$2:L$2256,"") | AR77: =_xlfn.XLOOKUP($A77,Results!$A$2:$A$2256,Results!M$2:M$2256,"") | AS77: =_xlfn.XLOOKUP($A77,Results!$A$2:$A$2256,Results!N$2:N$2256,"") | ... BE77: =_xlfn.XLOOKUP($A77,Results!$A$2:$A$2256,Results!Z$2:Z$2256,"")
A78: 905755 | B78: 281738 | C78: NULL | D78: S007853783.001 | E78: =VLOOKUP(F78,'RPA Vendor Data '!F75:$G$2418,2) -> ONESOURCE DISTRIBUTORS | F78: 16089 | G78: 1 | H78: WIC MCA 12/3 STR LV 16/2 250C ALU ARM BLK RED WHT GRN/LV PUR PNK | I78: 500 | J78: M | K78: M | L78: 1846.87 | M78: GENERIC WIRE | N78: WIC MCA 12/3 STR LV 16/2 250C | O78: NULL | P78: NULL | Q78: NULL | R78: 923.44 | S78: 45744.543 | T78: PA_SRDC | U78: 45744.32 | V78: PAUSER | W78: NULL | X78: 0 | Y78: 201 | Z78: NULL | AA78: NULL | AB78: NULL | AC78: GENERIC WIRE | AD78: GENERIC WIRE | AE78: AI | AF78: - | AG78: https://www.1sourcedist.com/product/detail/5556548/mccable-wic-mca-12-3-str-lv-16-2-250c | AI78: MATERIAL | AJ78: =VLOOKUP(A78,'Classification Test Result'!$A$2:$D$2428,4,FALSE) -> #N/A | AL78: =_xlfn.XLOOKUP($A78,Results!$A$2:$A$2256,Results!G$2:G$2256,"") | AM78: =_xlfn.XLOOKUP($A78,Results!$A$2:$A$2256,Results!H$2:H$2256,"") | AN78: =_xlfn.XLOOKUP($A78,Results!$A$2:$A$2256,Results!I$2:I$2256,"") | AO78: =_xlfn.XLOOKUP($A78,Results!$A$2:$A$2256,Results!J$2:J$2256,"") | AP78: =_xlfn.XLOOKUP($A78,Results!$A$2:$A$2256,Results!K$2:K$2256,"") | AQ78: =_xlfn.XLOOKUP($A78,Results!$A$2:$A$2256,Results!L$2:L$2256,"") | AR78: =_xlfn.XLOOKUP($A78,Results!$A$2:$A$2256,Results!M$2:M$2256,"") | AS78: =_xlfn.XLOOKUP($A78,Results!$A$2:$A$2256,Results!N$2:N$2256,"") | ... BE78: =_xlfn.XLOOKUP($A78,Results!$A$2:$A$2256,Results!Z$2:Z$2256,"")
A79: 905756 | B79: 281715 | C79: NULL | D79: S007853243.001 | E79: =VLOOKUP(F79,'RPA Vendor Data '!F76:$G$2418,2) -> ONESOURCE DISTRIBUTORS | F79: 16089 | G79: 7 | H79: WIC 8 THHN STR YEL CUT REEL Cuts: 1 @ 185 ft | I79: 185 | J79: M | K79: M | L79: 428.6 | M79: GENERIC WIRE | N79: THHN-8-YEL-19STR-CU-5O00R | O79: NULL | P79: NULL | Q79: NULL | R79: 79.29 | S79: 45744.544 | T79: PA_SRDC | U79: 45744.314 | V79: PAUSER | W79: NULL | X79: 0 | Y79: 201 | Z79: NULL | AA79: NULL | AB79: NULL | AC79: GENERIC WIRE | AD79: GENERIC WIRE | AE79: AI | AF79: - | AG79: https://www.1sourcedist.com/product/detail/4461994/thhncu-thhn-8-yel-19str-cu-5o00r | AI79: MATERIAL | AJ79: =VLOOKUP(A79,'Classification Test Result'!$A$2:$D$2428,4,FALSE) -> #N/A | AL79: =_xlfn.XLOOKUP($A79,Results!$A$2:$A$2256,Results!G$2:G$2256,"") -> 0 | AM79: =_xlfn.XLOOKUP($A79,Results!$A$2:$A$2256,Results!H$2:H$2256,"") -> 0 | AN79: =_xlfn.XLOOKUP($A79,Results!$A$2:$A$2256,Results!I$2:I$2256,"") -> 0 | AO79: =_xlfn.XLOOKUP($A79,Results!$A$2:$A$2256,Results!J$2:J$2256,"") -> 0 | AP79: =_xlfn.XLOOKUP($A79,Results!$A$2:$A$2256,Results!K$2:K$2256,"") -> 0 | AQ79: =_xlfn.XLOOKUP($A79,Results!$A$2:$A$2256,Results!L$2:L$2256,"") -> 0 | AR79: =_xlfn.XLOOKUP($A79,Results!$A$2:$A$2256,Results!M$2:M$2256,"") -> 0 | AS79: =_xlfn.XLOOKUP($A79,Results!$A$2:$A$2256,Results!N$2:N$2256,"") -> 0 | ... BE79: =_xlfn.XLOOKUP($A79,Results!$A$2:$A$2256,Results!Z$2:Z$2256,"") -> 0
A80: 905757 | B80: 281707 | C80: NULL | D80: S007851494.001 | E80: =VLOOKUP(F80,'RPA Vendor Data '!F78:$G$2418,2) -> INDEPENDENT ELECTRIC | F80: 14376 | G80: 9 | H80: WIC 8 THHN STR WHT CUT REEL Cuts: 1 @ 500 ft | I80: 500 | J80: M | K80: M | L80: 431.61 | M80: GENERIC WIRE | N80: 8 THHN STR WHT CUT REEL | O80: NULL | P80: NULL | Q80: NULL | R80: 215.81 | S80: 45744.522 | T80: PA_SRDC | U80: 45744.312 | V80: PAUSER | W80: NULL | X80: 0 | Y80: 201 | Z80: NULL | AA80: NULL | AB80: NULL | AC80: GENERIC WIRE | AD80: GENERIC WIRE | AE80: AI | AF80: 26121500 | AG80: https://usa.databasesets.com/unspsc/commodity/26121614 | AI80: MATERIAL | AJ80: =VLOOKUP(A80,'Classification Test Result'!$A$2:$D$2428,4,FALSE) -> #N/A | AL80: =_xlfn.XLOOKUP($A80,Results!$A$2:$A$2256,Results!G$2:G$2256,"") -> 0 | AM80: =_xlfn.XLOOKUP($A80,Results!$A$2:$A$2256,Results!H$2:H$2256,"") -> 0 | AN80: =_xlfn.XLOOKUP($A80,Results!$A$2:$A$2256,Results!I$2:I$2256,"") -> 0 | AO80: =_xlfn.XLOOKUP($A80,Results!$A$2:$A$2256,Results!J$2:J$2256,"") -> 0 | AP80: =_xlfn.XLOOKUP($A80,Results!$A$2:$A$2256,Results!K$2:K$2256,"") -> 0 | AQ80: =_xlfn.XLOOKUP($A80,Results!$A$2:$A$2256,Results!L$2:L$2256,"") -> 0 | AR80: =_xlfn.XLOOKUP($A80,Results!$A$2:$A$2256,Results!M$2:M$2256,"") -> 0 | AS80: =_xlfn.XLOOKUP($A80,Results!$A$2:$A$2256,Results!N$2:N$2256,"") -> 0 | ... BE80: =_xlfn.XLOOKUP($A80,Results!$A$2:$A$2256,Results!Z$2:Z$2256,"") -> 0
A81: 905758 | B81: 281707 | C81: NULL | D81: S007851494.001 | E81: =VLOOKUP(F81,'RPA Vendor Data '!F79:$G$2418,2) -> INDEPENDENT ELECTRIC | F81: 14376 | G81: 4 | H81: WIC 8 THHN STR RED 500R | I81: 500 | J81: M | K81: M | L81: 431.61 | M81: GENERIC WIRE | N81: 8 THHN STR RED 500R | O81: NULL | P81: NULL | Q81: NULL | R81: 215.81 | S81: 45744.522 | T81: PA_SRDC | U81: 45744.312 | V81: PAUSER | W81: NULL | X81: 0 | Y81: 201 | Z81: NULL | AA81: NULL | AB81: NULL | AC81: GENERIC WIRE | AD81: GENERIC WIRE | AE81: AI | AF81: 26121500 | AG81: https://usa.databasesets.com/unspsc/commodity/26121614 | AI81: MATERIAL | AJ81: =VLOOKUP(A81,'Classification Test Result'!$A$2:$D$2428,4,FALSE) -> #N/A | AL81: =_xlfn.XLOOKUP($A81,Results!$A$2:$A$2256,Results!G$2:G$2256,"") -> 0 | AM81: =_xlfn.XLOOKUP($A81,Results!$A$2:$A$2256,Results!H$2:H$2256,"") -> 0 | AN81: =_xlfn.XLOOKUP($A81,Results!$A$2:$A$2256,Results!I$2:I$2256,"") -> 0 | AO81: =_xlfn.XLOOKUP($A81,Results!$A$2:$A$2256,Results!J$2:J$2256,"") -> 0 | AP81: =_xlfn.XLOOKUP($A81,Results!$A$2:$A$2256,Results!K$2:K$2256,"") -> 0 | AQ81: =_xlfn.XLOOKUP($A81,Results!$A$2:$A$2256,Results!L$2:L$2256,"") -> 0 | AR81: =_xlfn.XLOOKUP($A81,Results!$A$2:$A$2256,Results!M$2:M$2256,"") -> 0 | AS81: =_xlfn.XLOOKUP($A81,Results!$A$2:$A$2256,Results!N$2:N$2256,"") -> 0 | ... BE81: =_xlfn.XLOOKUP($A81,Results!$A$2:$A$2256,Results!Z$2:Z$2256,"") -> TRUE
A82: 905759 | B82: 281715 | C82: NULL | D82: S007853243.001 | E82: =VLOOKUP(F82,'RPA Vendor Data '!F80:$G$2418,2) -> ONESOURCE DISTRIBUTORS | F82: 16089 | G82: 6 | H82: WIC 8 THHN STR ORG CUT REEL Cuts: 1 @ 185 ft | I82: 185 | J82: M | K82: M | L82: 428.6 | M82: GENERIC WIRE | N82: THHN-8-ORG-19STR-CU-5000R | O82: NULL | P82: NULL | Q82: NULL | R82: 79.29 | S82: 45744.544 | T82: PA_SRDC | U82: 45744.314 | V82: PAUSER | W82: NULL | X82: 0 | Y82: 201 | Z82: NULL | AA82: NULL | AB82: NULL | AC82: GENERIC WIRE | AD82: GENERIC WIRE | AE82: AI | AF82: - | AG82: https://www.1sourcedist.com/product/detail/4082442/thhncu-thhn-8-org-19str-cu-5000r | AI82: MATERIAL | AJ82: =VLOOKUP(A82,'Classification Test Result'!$A$2:$D$2428,4,FALSE) -> #N/A | AL82: =_xlfn.XLOOKUP($A82,Results!$A$2:$A$2256,Results!G$2:G$2256,"") -> 0 | AM82: =_xlfn.XLOOKUP($A82,Results!$A$2:$A$2256,Results!H$2:H$2256,"") -> 0 | AN82: =_xlfn.XLOOKUP($A82,Results!$A$2:$A$2256,Results!I$2:I$2256,"") -> 0 | AO82: =_xlfn.XLOOKUP($A82,Results!$A$2:$A$2256,Results!J$2:J$2256,"") -> 0 | AP82: =_xlfn.XLOOKUP($A82,Results!$A$2:$A$2256,Results!K$2:K$2256,"") -> 0 | AQ82: =_xlfn.XLOOKUP($A82,Results!$A$2:$A$2256,Results!L$2:L$2256,"") -> 0 | AR82: =_xlfn.XLOOKUP($A82,Results!$A$2:$A$2256,Results!M$2:M$2256,"") -> 0 | AS82: =_xlfn.XLOOKUP($A82,Results!$A$2:$A$2256,Results!N$2:N$2256,"") -> 0 | ... BE82: =_xlfn.XLOOKUP($A82,Results!$A$2:$A$2256,Results!Z$2:Z$2256,"") -> TRUE
A83: 905760 | B83: 281715 | C83: NULL | D83: S007853243.001 | E83: =VLOOKUP(F83,'RPA Vendor Data '!F81:$G$2418,2) -> ONESOURCE DISTRIBUTORS | F83: 16089 | G83: 5 | H83: WIC 8 THHN STR BRN CUT REEL Cuts: 1 @ 185 ft | I83: 185 | J83: M | K83: M | L83: 428.6 | M83: GENERIC WIRE | N83: THHN-8-BRN-19STR-CU-5000R | O83: NULL | P83: NULL | Q83: NULL | R83: 79.29 | S83: 45744.544 | T83: PA_SRDC | U83: 45744.314 | V83: PAUSER | W83: NULL | X83: 0 | Y83: 201 | Z83: NULL | AA83: NULL | AB83: NULL | AC83: GENERIC WIRE | AD83: GENERIC WIRE | AE83: AI | AF83: - | AG83: https://www.1sourcedist.com/product/detail/4461138/thhncu-thhn-8-brn-19str-cu-5000r | AI83: MATERIAL | AJ83: =VLOOKUP(A83,'Classification Test Result'!$A$2:$D$2428,4,FALSE) -> #N/A | AL83: =_xlfn.XLOOKUP($A83,Results!$A$2:$A$2256,Results!G$2:G$2256,"") -> 0 | AM83: =_xlfn.XLOOKUP($A83,Results!$A$2:$A$2256,Results!H$2:H$2256,"") -> 0 | AN83: =_xlfn.XLOOKUP($A83,Results!$A$2:$A$2256,Results!I$2:I$2256,"") -> 0 | AO83: =_xlfn.XLOOKUP($A83,Results!$A$2:$A$2256,Results!J$2:J$2256,"") -> 0 | AP83: =_xlfn.XLOOKUP($A83,Results!$A$2:$A$2256,Results!K$2:K$2256,"") -> 0 | AQ83: =_xlfn.XLOOKUP($A83,Results!$A$2:$A$2256,Results!L$2:L$2256,"") -> 0 | AR83: =_xlfn.XLOOKUP($A83,Results!$A$2:$A$2256,Results!M$2:M$2256,"") -> 0 | AS83: =_xlfn.XLOOKUP($A83,Results!$A$2:$A$2256,Results!N$2:N$2256,"") -> 0 | ... BE83: =_xlfn.XLOOKUP($A83,Results!$A$2:$A$2256,Results!Z$2:Z$2256,"") -> TRUE
A84: 905761 | B84: 281707 | C84: NULL | D84: S007851494.001 | E84: =VLOOKUP(F84,'RPA Vendor Data '!F82:$G$2418,2) -> INDEPENDENT ELECTRIC | F84: 14376 | G84: 8 | H84: WIC 8 THHN STR BLK CUT REEL Cuts: 1 @ 500 ft | I84: 500 | J84: M | K84: M | L84: 431.61 | M84: GENERIC WIRE | N84: 8 THHN STR BLK CUT REEL | O84: NULL | P84: NULL | Q84: NULL | R84: 215.81 | S84: 45744.522 | T84: PA_SRDC | U84: 45744.312 | V84: PAUSER | W84: NULL | X84: 0 | Y84: 201 | Z84: NULL | AA84: NULL | AB84: NULL | AC84: GENERIC WIRE | AD84: GENERIC WIRE | AE84: AI | AF84: 26121500 | AG84: https://usa.databasesets.com/unspsc/commodity/26121614 | AI84: MATERIAL | AJ84: =VLOOKUP(A84,'Classification Test Result'!$A$2:$D$2428,4,FALSE) -> #N/A | AL84: =_xlfn.XLOOKUP($A84,Results!$A$2:$A$2256,Results!G$2:G$2256,"") -> 0 | AM84: =_xlfn.XLOOKUP($A84,Results!$A$2:$A$2256,Results!H$2:H$2256,"") -> 0 | AN84: =_xlfn.XLOOKUP($A84,Results!$A$2:$A$2256,Results!I$2:I$2256,"") -> 0 | AO84: =_xlfn.XLOOKUP($A84,Results!$A$2:$A$2256,Results!J$2:J$2256,"") -> 0 | AP84: =_xlfn.XLOOKUP($A84,Results!$A$2:$A$2256,Results!K$2:K$2256,"") -> 0 | AQ84: =_xlfn.XLOOKUP($A84,Results!$A$2:$A$2256,Results!L$2:L$2256,"") -> 0 | AR84: =_xlfn.XLOOKUP($A84,Results!$A$2:$A$2256,Results!M$2:M$2256,"") -> 0 | AS84: =_xlfn.XLOOKUP($A84,Results!$A$2:$A$2256,Results!N$2:N$2256,"") -> 0 | ... BE84: =_xlfn.XLOOKUP($A84,Results!$A$2:$A$2256,Results!Z$2:Z$2256,"") -> TRUE
A85: 905762 | B85: 281707 | C85: NULL | D85: S007851494.001 | E85: =VLOOKUP(F85,'RPA Vendor Data '!F83:$G$2418,2) -> INDEPENDENT ELECTRIC | F85: 14376 | G85: 6 | H85: WIC 6 THHN STR WHT 1000R | I85: 1000 | J85: M | K85: M | L85: 664.03 | M85: GENERIC WIRE | N85: 6 THHN STR WHT 1000R | O85: NULL | P85: NULL | Q85: NULL | R85: 664.03 | S85: 45744.522 | T85: PA_SRDC | U85: 45744.312 | V85: PAUSER | W85: NULL | X85: 0 | Y85: 201 | Z85: NULL | AA85: NULL | AB85: NULL | AC85: GENERIC WIRE | AD85: GENERIC WIRE | AE85: AI | AF85: 26121500 | AG85: https://usa.databasesets.com/unspsc/commodity/26121614 | AI85: MATERIAL | AJ85: =VLOOKUP(A85,'Classification Test Result'!$A$2:$D$2428,4,FALSE) -> #N/A | AL85: =_xlfn.XLOOKUP($A85,Results!$A$2:$A$2256,Results!G$2:G$2256,"") -> 0 | AM85: =_xlfn.XLOOKUP($A85,Results!$A$2:$A$2256,Results!H$2:H$2256,"") -> 0 | AN85: =_xlfn.XLOOKUP($A85,Results!$A$2:$A$2256,Results!I$2:I$2256,"") -> 0 | AO85: =_xlfn.XLOOKUP($A85,Results!$A$2:$A$2256,Results!J$2:J$2256,"") -> 0 | AP85: =_xlfn.XLOOKUP($A85,Results!$A$2:$A$2256,Results!K$2:K$2256,"") -> 0 | AQ85: =_xlfn.XLOOKUP($A85,Results!$A$2:$A$2256,Results!L$2:L$2256,"") -> 0 | AR85: =_xlfn.XLOOKUP($A85,Results!$A$2:$A$2256,Results!M$2:M$2256,"") -> 0 | AS85: =_xlfn.XLOOKUP($A85,Results!$A$2:$A$2256,Results!N$2:N$2256,"") -> 0 | ... BE85: =_xlfn.XLOOKUP($A85,Results!$A$2:$A$2256,Results!Z$2:Z$2256,"") -> TRUE
A86: 905763 | B86: 281707 | C86: NULL | D86: S007851494.001 | E86: =VLOOKUP(F86,'RPA Vendor Data '!F84:$G$2418,2) -> INDEPENDENT ELECTRIC | F86: 14376 | G86: 2 | H86: WIC 6 THHN STR RED CUT REEL Cuts: 1 @ 110 ft | I86: 110 | J86: M | K86: M | L86: 664.03 | M86: GENERIC WIRE | N86: 6 THHN STR RED CUT REEL | O86: NULL | P86: NULL | Q86: NULL | R86: 73.04 | S86: 45744.522 | T86: PA_SRDC | U86: 45744.312 | V86: PAUSER | W86: NULL | X86: 0 | Y86: 201 | Z86: NULL | AA86: NULL | AB86: NULL | AC86: GENERIC WIRE | AD86: GENERIC WIRE | AE86: AI | AF86: 26121500 | AG86: https://usa.databasesets.com/unspsc/commodity/26121614 | AI86: MATERIAL | AJ86: =VLOOKUP(A86,'Classification Test Result'!$A$2:$D$2428,4,FALSE) -> #N/A | AL86: =_xlfn.XLOOKUP($A86,Results!$A$2:$A$2256,Results!G$2:G$2256,"") -> 0 | AM86: =_xlfn.XLOOKUP($A86,Results!$A$2:$A$2256,Results!H$2:H$2256,"") -> 0 | AN86: =_xlfn.XLOOKUP($A86,Results!$A$2:$A$2256,Results!I$2:I$2256,"") -> 0 | AO86: =_xlfn.XLOOKUP($A86,Results!$A$2:$A$2256,Results!J$2:J$2256,"") -> 0 | AP86: =_xlfn.XLOOKUP($A86,Results!$A$2:$A$2256,Results!K$2:K$2256,"") -> 0 | AQ86: =_xlfn.XLOOKUP($A86,Results!$A$2:$A$2256,Results!L$2:L$2256,"") -> 0 | AR86: =_xlfn.XLOOKUP($A86,Results!$A$2:$A$2256,Results!M$2:M$2256,"") -> 0 | AS86: =_xlfn.XLOOKUP($A86,Results!$A$2:$A$2256,Results!N$2:N$2256,"") -> 0 | ... BE86: =_xlfn.XLOOKUP($A86,Results!$A$2:$A$2256,Results!Z$2:Z$2256,"") -> TRUE
A87: 905764 | B87: 281715 | C87: NULL | D87: S007853243.001 | E87: =VLOOKUP(F87,'RPA Vendor Data '!F85:$G$2418,2) -> ONESOURCE DISTRIBUTORS | F87: 16089 | G87: 4 | H87: WIC 6 THHN STR GRN CUT REEL Cuts: 1 @ 186 ft | I87: 186 | J87: M | K87: M | L87: 659.42 | M87: GENERIC WIRE | N87: THHN-6-GRN-19STR-CU-5000R | O87: NULL | P87: NULL | Q87: NULL | R87: 122.65 | S87: 45744.544 | T87: PA_SRDC | U87: 45744.314 | V87: PAUSER | W87: NULL | X87: 0 | Y87: 201 | Z87: NULL | AA87: NULL | AB87: NULL | AC87: GENERIC WIRE | AD87: GENERIC WIRE | AE87: AI | AF87: - | AG87: https://www.1sourcedist.com/product/detail/793085/thhncu-thhn-6-grn-19str-cu-5000r | AI87: MATERIAL | AJ87: =VLOOKUP(A87,'Classification Test Result'!$A$2:$D$2428,4,FALSE) -> #N/A | AL87: =_xlfn.XLOOKUP($A87,Results!$A$2:$A$2256,Results!G$2:G$2256,"") | AM87: =_xlfn.XLOOKUP($A87,Results!$A$2:$A$2256,Results!H$2:H$2256,"") | AN87: =_xlfn.XLOOKUP($A87,Results!$A$2:$A$2256,Results!I$2:I$2256,"") | AO87: =_xlfn.XLOOKUP($A87,Results!$A$2:$A$2256,Results!J$2:J$2256,"") | AP87: =_xlfn.XLOOKUP($A87,Results!$A$2:$A$2256,Results!K$2:K$2256,"") | AQ87: =_xlfn.XLOOKUP($A87,Results!$A$2:$A$2256,Results!L$2:L$2256,"") | AR87: =_xlfn.XLOOKUP($A87,Results!$A$2:$A$2256,Results!M$2:M$2256,"") | AS87: =_xlfn.XLOOKUP($A87,Results!$A$2:$A$2256,Results!N$2:N$2256,"") | ... BE87: =_xlfn.XLOOKUP($A87,Results!$A$2:$A$2256,Results!Z$2:Z$2256,"")
A88: 905765 | B88: 281707 | C88: NULL | D88: S007851494.001 | E88: =VLOOKUP(F88,'RPA Vendor Data '!F86:$G$2418,2) -> INDEPENDENT ELECTRIC | F88: 14376 | G88: 7 | H88: WIC 6 THHN STR GRN 1000R | I88: 1000 | J88: M | K88: M | L88: 664.03 | M88: GENERIC WIRE | N88: 6 THHN STR GRN 1000R | O88: NULL | P88: NULL | Q88: NULL | R88: 664.03 | S88: 45744.522 | T88: PA_SRDC | U88: 45744.312 | V88: PAUSER | W88: NULL | X88: 0 | Y88: 201 | Z88: NULL | AA88: NULL | AB88: NULL | AC88: GENERIC WIRE | AD88: GENERIC WIRE | AE88: AI | AF88: 26121500 | AG88: https://usa.databasesets.com/unspsc/commodity/26121614 | AI88: MATERIAL | AJ88: =VLOOKUP(A88,'Classification Test Result'!$A$2:$D$2428,4,FALSE) -> #N/A | AL88: =_xlfn.XLOOKUP($A88,Results!$A$2:$A$2256,Results!G$2:G$2256,"") | AM88: =_xlfn.XLOOKUP($A88,Results!$A$2:$A$2256,Results!H$2:H$2256,"") | AN88: =_xlfn.XLOOKUP($A88,Results!$A$2:$A$2256,Results!I$2:I$2256,"") | AO88: =_xlfn.XLOOKUP($A88,Results!$A$2:$A$2256,Results!J$2:J$2256,"") | AP88: =_xlfn.XLOOKUP($A88,Results!$A$2:$A$2256,Results!K$2:K$2256,"") | AQ88: =_xlfn.XLOOKUP($A88,Results!$A$2:$A$2256,Results!L$2:L$2256,"") | AR88: =_xlfn.XLOOKUP($A88,Results!$A$2:$A$2256,Results!M$2:M$2256,"") | AS88: =_xlfn.XLOOKUP($A88,Results!$A$2:$A$2256,Results!N$2:N$2256,"") | ... BE88: =_xlfn.XLOOKUP($A88,Results!$A$2:$A$2256,Results!Z$2:Z$2256,"")
A89: 905766 | B89: 281707 | C89: NULL | D89: S007851494.001 | E89: =VLOOKUP(F89,'RPA Vendor Data '!F87:$G$2418,2) -> INDEPENDENT ELECTRIC | F89: 14376 | G89: 3 | H89: WIC 6 THHN STR BLU CUT REEL Cuts: 1 @ 110 ft | I89: 110 | J89: M | K89: M | L89: 664.03 | M89: GENERIC WIRE | N89: 6 THHN STR BLU CUT REEL | O89: NULL | P89: NULL | Q89: NULL | R89: 73.04 | S89: 45744.522 | T89: PA_SRDC | U89: 45744.312 | V89: PAUSER | W89: NULL | X89: 0 | Y89: 201 | Z89: NULL | AA89: NULL | AB89: NULL | AC89: GENERIC WIRE | AD89: GENERIC WIRE | AE89: AI | AF89: 26121500 | AG89: https://usa.databasesets.com/unspsc/commodity/26121614 | AI89: MATERIAL | AJ89: =VLOOKUP(A89,'Classification Test Result'!$A$2:$D$2428,4,FALSE) -> #N/A | AL89: =_xlfn.XLOOKUP($A89,Results!$A$2:$A$2256,Results!G$2:G$2256,"") -> 0 | AM89: =_xlfn.XLOOKUP($A89,Results!$A$2:$A$2256,Results!H$2:H$2256,"") -> 0 | AN89: =_xlfn.XLOOKUP($A89,Results!$A$2:$A$2256,Results!I$2:I$2256,"") -> 0 | AO89: =_xlfn.XLOOKUP($A89,Results!$A$2:$A$2256,Results!J$2:J$2256,"") -> 0 | AP89: =_xlfn.XLOOKUP($A89,Results!$A$2:$A$2256,Results!K$2:K$2256,"") -> 0 | AQ89: =_xlfn.XLOOKUP($A89,Results!$A$2:$A$2256,Results!L$2:L$2256,"") -> 0 | AR89: =_xlfn.XLOOKUP($A89,Results!$A$2:$A$2256,Results!M$2:M$2256,"") -> 0 | AS89: =_xlfn.XLOOKUP($A89,Results!$A$2:$A$2256,Results!N$2:N$2256,"") -> 0 | ... BE89: =_xlfn.XLOOKUP($A89,Results!$A$2:$A$2256,Results!Z$2:Z$2256,"") -> TRUE
A90: 905767 | B90: 281707 | C90: NULL | D90: S007851494.001 | E90: =VLOOKUP(F90,'RPA Vendor Data '!F88:$G$2418,2) -> INDEPENDENT ELECTRIC | F90: 14376 | G90: 1 | H90: WIC 6 THHN STR BLK CUT REEL Cuts: 1 @ 110 ft | I90: 110 | J90: M | K90: M | L90: 664.03 | M90: GENERIC WIRE | N90: 6 THHN STR BLK CUT REEL | O90: NULL | P90: NULL | Q90: NULL | R90: 73.04 | S90: 45744.522 | T90: PA_SRDC | U90: 45744.312 | V90: PAUSER | W90: NULL | X90: 0 | Y90: 201 | Z90: NULL | AA90: NULL | AB90: NULL | AC90: GENERIC WIRE | AD90: GENERIC WIRE | AE90: AI | AF90: 26121500 | AG90: https://usa.databasesets.com/unspsc/commodity/26121614 | AI90: MATERIAL | AJ90: =VLOOKUP(A90,'Classification Test Result'!$A$2:$D$2428,4,FALSE) -> #N/A | AL90: =_xlfn.XLOOKUP($A90,Results!$A$2:$A$2256,Results!G$2:G$2256,"") -> 0 | AM90: =_xlfn.XLOOKUP($A90,Results!$A$2:$A$2256,Results!H$2:H$2256,"") -> 0 | AN90: =_xlfn.XLOOKUP($A90,Results!$A$2:$A$2256,Results!I$2:I$2256,"") -> 0 | AO90: =_xlfn.XLOOKUP($A90,Results!$A$2:$A$2256,Results!J$2:J$2256,"") -> 0 | AP90: =_xlfn.XLOOKUP($A90,Results!$A$2:$A$2256,Results!K$2:K$2256,"") -> 0 | AQ90: =_xlfn.XLOOKUP($A90,Results!$A$2:$A$2256,Results!L$2:L$2256,"") -> 0 | AR90: =_xlfn.XLOOKUP($A90,Results!$A$2:$A$2256,Results!M$2:M$2256,"") -> 0 | AS90: =_xlfn.XLOOKUP($A90,Results!$A$2:$A$2256,Results!N$2:N$2256,"") -> 0 | ... BE90: =_xlfn.XLOOKUP($A90,Results!$A$2:$A$2256,Results!Z$2:Z$2256,"") -> TRUE
A91: 905768 | B91: 281738 | C91: NULL | D91: S007853783.001 | E91: =VLOOKUP(F91,'RPA Vendor Data '!F89:$G$2418,2) -> ONESOURCE DISTRIBUTORS | F91: 16089 | G91: 2 | H91: WIC 12/2 CUMC STRND W/GRND ALUM JKT BLK/WHT 250 Coil | I91: 500 | J91: M | K91: M | L91: 845.45 | M91: GENERIC WIRE | N91: MC-STR-12/2 BLK/WHT 250' | O91: NULL | P91: NULL | Q91: NULL | R91: 422.73 | S91: 45744.543 | T91: PA_SRDC | U91: 45744.32 | V91: PAUSER | W91: NULL | X91: 0 | Y91: 201 | Z91: NULL | AA91: NULL | AB91: NULL | AC91: GENERIC WIRE | AD91: GENERIC WIRE | AE91: AI | AF91: - | AG91: https://www.1sourcedist.com/product/detail/4457297/mccable-mc-str-12-2-blk-wht-250 | AI91: MATERIAL | AJ91: =VLOOKUP(A91,'Classification Test Result'!$A$2:$D$2428,4,FALSE) -> #N/A | AL91: =_xlfn.XLOOKUP($A91,Results!$A$2:$A$2256,Results!G$2:G$2256,"") -> 0 | AM91: =_xlfn.XLOOKUP($A91,Results!$A$2:$A$2256,Results!H$2:H$2256,"") -> 0 | AN91: =_xlfn.XLOOKUP($A91,Results!$A$2:$A$2256,Results!I$2:I$2256,"") -> 0 | AO91: =_xlfn.XLOOKUP($A91,Results!$A$2:$A$2256,Results!J$2:J$2256,"") -> 0 | AP91: =_xlfn.XLOOKUP($A91,Results!$A$2:$A$2256,Results!K$2:K$2256,"") -> 0 | AQ91: =_xlfn.XLOOKUP($A91,Results!$A$2:$A$2256,Results!L$2:L$2256,"") -> 0 | AR91: =_xlfn.XLOOKUP($A91,Results!$A$2:$A$2256,Results!M$2:M$2256,"") -> 0 | AS91: =_xlfn.XLOOKUP($A91,Results!$A$2:$A$2256,Results!N$2:N$2256,"") -> 0 | ... BE91: =_xlfn.XLOOKUP($A91,Results!$A$2:$A$2256,Results!Z$2:Z$2256,"") -> TRUE
A92: 905769 | B92: 281715 | C92: NULL | D92: S007853243.001 | E92: =VLOOKUP(F92,'RPA Vendor Data '!F90:$G$2418,2) -> ONESOURCE DISTRIBUTORS | F92: 16089 | G92: 8 | H92: WIC 10 THHN STR GRN 500R | I92: 500 | J92: M | K92: M | L92: 230.91 | M92: GENERIC WIRE | N92: THHN-10-GRN-19STR-CU-500S/R | O92: NULL | P92: NULL | Q92: NULL | R92: 115.46 | S92: 45744.544 | T92: PA_SRDC | U92: 45744.314 | V92: PAUSER | W92: NULL | X92: 0 | Y92: 201 | Z92: NULL | AA92: NULL | AB92: NULL | AC92: GENERIC WIRE | AD92: GENERIC WIRE | AE92: AI | AF92: - | AG92: https://www.1sourcedist.com/product/detail/24184/thhncu-thhn-10-grn-19str-cu-500s-r | AI92: MATERIAL | AJ92: =VLOOKUP(A92,'Classification Test Result'!$A$2:$D$2428,4,FALSE) -> #N/A | AL92: =_xlfn.XLOOKUP($A92,Results!$A$2:$A$2256,Results!G$2:G$2256,"") | AM92: =_xlfn.XLOOKUP($A92,Results!$A$2:$A$2256,Results!H$2:H$2256,"") | AN92: =_xlfn.XLOOKUP($A92,Results!$A$2:$A$2256,Results!I$2:I$2256,"") | AO92: =_xlfn.XLOOKUP($A92,Results!$A$2:$A$2256,Results!J$2:J$2256,"") | AP92: =_xlfn.XLOOKUP($A92,Results!$A$2:$A$2256,Results!K$2:K$2256,"") | AQ92: =_xlfn.XLOOKUP($A92,Results!$A$2:$A$2256,Results!L$2:L$2256,"") | AR92: =_xlfn.XLOOKUP($A92,Results!$A$2:$A$2256,Results!M$2:M$2256,"") | AS92: =_xlfn.XLOOKUP($A92,Results!$A$2:$A$2256,Results!N$2:N$2256,"") | ... BE92: =_xlfn.XLOOKUP($A92,Results!$A$2:$A$2256,Results!Z$2:Z$2256,"")
A93: 905770 | B93: 281707 | C93: NULL | D93: S007851494.001 | E93: =VLOOKUP(F93,'RPA Vendor Data '!F91:$G$2418,2) -> INDEPENDENT ELECTRIC | F93: 14376 | G93: 5 | H93: WIC 10 THHN STR GRN 500R | I93: 500 | J93: M | K93: M | L93: 232.53 | M93: GENERIC WIRE | N93: 10 THHN STR GRN 500R | O93: NULL | P93: NULL | Q93: NULL | R93: 116.27 | S93: 45744.522 | T93: PA_SRDC | U93: 45744.312 | V93: PAUSER | W93: NULL | X93: 0 | Y93: 201 | Z93: NULL | AA93: NULL | AB93: NULL | AC93: GENERIC WIRE | AD93: GENERIC WIRE | AE93: AI | AF93: 26121500 | AG93: https://usa.databasesets.com/unspsc/commodity/26121614 | AI93: MATERIAL | AJ93: =VLOOKUP(A93,'Classification Test Result'!$A$2:$D$2428,4,FALSE) -> #N/A | AL93: =_xlfn.XLOOKUP($A93,Results!$A$2:$A$2256,Results!G$2:G$2256,"") | AM93: =_xlfn.XLOOKUP($A93,Results!$A$2:$A$2256,Results!H$2:H$2256,"") | AN93: =_xlfn.XLOOKUP($A93,Results!$A$2:$A$2256,Results!I$2:I$2256,"") | AO93: =_xlfn.XLOOKUP($A93,Results!$A$2:$A$2256,Results!J$2:J$2256,"") | AP93: =_xlfn.XLOOKUP($A93,Results!$A$2:$A$2256,Results!K$2:K$2256,"") | AQ93: =_xlfn.XLOOKUP($A93,Results!$A$2:$A$2256,Results!L$2:L$2256,"") | AR93: =_xlfn.XLOOKUP($A93,Results!$A$2:$A$2256,Results!M$2:M$2256,"") | AS93: =_xlfn.XLOOKUP($A93,Results!$A$2:$A$2256,Results!N$2:N$2256,"") | ... BE93: =_xlfn.XLOOKUP($A93,Results!$A$2:$A$2256,Results!Z$2:Z$2256,"")
A94: 905771 | B94: 281715 | C94: NULL | D94: S007853243.001 | E94: =VLOOKUP(F94,'RPA Vendor Data '!F92:$G$2418,2) -> ONESOURCE DISTRIBUTORS | F94: 16089 | G94: 3 | H94: WIC 1 THHN STR YEL CUT REEL Cuts: 1 @ 186 ft | I94: 186 | J94: M | K94: M | L94: 1775.24 | M94: GENERIC WIRE | N94: THHN-1-YEL-19STR-CU-2500R | O94: NULL | P94: NULL | Q94: NULL | R94: 330.19 | S94: 45744.544 | T94: PA_SRDC | U94: 45744.314 | V94: PAUSER | W94: NULL | X94: 0 | Y94: 201 | Z94: NULL | AA94: NULL | AB94: NULL | AC94: GENERIC WIRE | AD94: GENERIC WIRE | AE94: AI | AF94: - | AG94: https://www.1sourcedist.com/product/detail/4454659/thhncu-thhn-1-yel-19str-cu-2500r | AI94: MATERIAL | AJ94: =VLOOKUP(A94,'Classification Test Result'!$A$2:$D$2428,4,FALSE) -> #N/A | AL94: =_xlfn.XLOOKUP($A94,Results!$A$2:$A$2256,Results!G$2:G$2256,"") -> 0 | AM94: =_xlfn.XLOOKUP($A94,Results!$A$2:$A$2256,Results!H$2:H$2256,"") -> 0 | AN94: =_xlfn.XLOOKUP($A94,Results!$A$2:$A$2256,Results!I$2:I$2256,"") -> 0 | AO94: =_xlfn.XLOOKUP($A94,Results!$A$2:$A$2256,Results!J$2:J$2256,"") -> 0 | AP94: =_xlfn.XLOOKUP($A94,Results!$A$2:$A$2256,Results!K$2:K$2256,"") -> 0 | AQ94: =_xlfn.XLOOKUP($A94,Results!$A$2:$A$2256,Results!L$2:L$2256,"") -> 0 | AR94: =_xlfn.XLOOKUP($A94,Results!$A$2:$A$2256,Results!M$2:M$2256,"") -> 0 | AS94: =_xlfn.XLOOKUP($A94,Results!$A$2:$A$2256,Results!N$2:N$2256,"") -> 0 | ... BE94: =_xlfn.XLOOKUP($A94,Results!$A$2:$A$2256,Results!Z$2:Z$2256,"") -> 0
A95: 905772 | B95: 281715 | C95: NULL | D95: S007853243.001 | E95: =VLOOKUP(F95,'RPA Vendor Data '!F93:$G$2418,2) -> ONESOURCE DISTRIBUTORS | F95: 16089 | G95: 2 | H95: WIC 1 THHN STR ORG CUT REEL Cuts: 1 @ 186 ft | I95: 186 | J95: M | K95: M | L95: 1775.24 | M95: GENERIC WIRE | N95: THHN-1-ORG-19STR-CU-2500R | O95: NULL | P95: NULL | Q95: NULL | R95: 330.19 | S95: 45744.544 | T95: PA_SRDC | U95: 45744.314 | V95: PAUSER | W95: NULL | X95: 0 | Y95: 201 | Z95: NULL | AA95: NULL | AB95: NULL | AC95: GENERIC WIRE | AD95: GENERIC WIRE | AE95: AI | AF95: - | AG95: https://www.1sourcedist.com/product/detail/4452112/thhncu-thhn-1-org-19str-cu-2500r | AI95: MATERIAL | AJ95: =VLOOKUP(A95,'Classification Test Result'!$A$2:$D$2428,4,FALSE) -> #N/A | AL95: =_xlfn.XLOOKUP($A95,Results!$A$2:$A$2256,Results!G$2:G$2256,"") -> 0 | AM95: =_xlfn.XLOOKUP($A95,Results!$A$2:$A$2256,Results!H$2:H$2256,"") -> 0 | AN95: =_xlfn.XLOOKUP($A95,Results!$A$2:$A$2256,Results!I$2:I$2256,"") -> 0 | AO95: =_xlfn.XLOOKUP($A95,Results!$A$2:$A$2256,Results!J$2:J$2256,"") -> 0 | AP95: =_xlfn.XLOOKUP($A95,Results!$A$2:$A$2256,Results!K$2:K$2256,"") -> 0 | AQ95: =_xlfn.XLOOKUP($A95,Results!$A$2:$A$2256,Results!L$2:L$2256,"") -> 0 | AR95: =_xlfn.XLOOKUP($A95,Results!$A$2:$A$2256,Results!M$2:M$2256,"") -> 0 | AS95: =_xlfn.XLOOKUP($A95,Results!$A$2:$A$2256,Results!N$2:N$2256,"") -> 0 | ... BE95: =_xlfn.XLOOKUP($A95,Results!$A$2:$A$2256,Results!Z$2:Z$2256,"") -> 0
A96: 905773 | B96: 281715 | C96: NULL | D96: S007853243.001 | E96: =VLOOKUP(F96,'RPA Vendor Data '!F94:$G$2418,2) -> ONESOURCE DISTRIBUTORS | F96: 16089 | G96: 1 | H96: WIC 1 THHN STR BRN CUT REEL Cuts: 1 @ 186 ft | I96: 186 | J96: M | K96: M | L96: 1775.24 | M96: GENERIC WIRE | N96: THHN-1-BRN-19STR-CU-2500R | O96: NULL | P96: NULL | Q96: NULL | R96: 330.19 | S96: 45744.544 | T96: PA_SRDC | U96: 45744.314 | V96: PAUSER | W96: NULL | X96: 0 | Y96: 201 | Z96: NULL | AA96: NULL | AB96: NULL | AC96: GENERIC WIRE | AD96: GENERIC WIRE | AE96: AI | AF96: - | AG96: https://www.1sourcedist.com/product/detail/4455236/thhncu-thhn-1-brn-19str-cu-2500r | AI96: MATERIAL | AJ96: =VLOOKUP(A96,'Classification Test Result'!$A$2:$D$2428,4,FALSE) -> #N/A | AL96: =_xlfn.XLOOKUP($A96,Results!$A$2:$A$2256,Results!G$2:G$2256,"") -> 0 | AM96: =_xlfn.XLOOKUP($A96,Results!$A$2:$A$2256,Results!H$2:H$2256,"") -> 0 | AN96: =_xlfn.XLOOKUP($A96,Results!$A$2:$A$2256,Results!I$2:I$2256,"") -> 0 | AO96: =_xlfn.XLOOKUP($A96,Results!$A$2:$A$2256,Results!J$2:J$2256,"") -> 0 | AP96: =_xlfn.XLOOKUP($A96,Results!$A$2:$A$2256,Results!K$2:K$2256,"") -> 0 | AQ96: =_xlfn.XLOOKUP($A96,Results!$A$2:$A$2256,Results!L$2:L$2256,"") -> 0 | AR96: =_xlfn.XLOOKUP($A96,Results!$A$2:$A$2256,Results!M$2:M$2256,"") -> 0 | AS96: =_xlfn.XLOOKUP($A96,Results!$A$2:$A$2256,Results!N$2:N$2256,"") -> 0 | ... BE96: =_xlfn.XLOOKUP($A96,Results!$A$2:$A$2256,Results!Z$2:Z$2256,"") -> TRUE
A97: 905774 | B97: 281663 | C97: NULL | D97: S008995642.001 | E97: =VLOOKUP(F97,'RPA Vendor Data '!F95:$G$2418,2) -> VIKING ELECTRIC | F97: 13536 | G97: 1 | H97: WIA. 1 STR GRN MR XHHW 1 XHHW GREEN ALUMINUM WIRE | I97: 215 | J97: m | K97: M | L97: 376.11 | M97: Generic Wire | N97: XHHW 1 STR GRN MR | O97: NULL | P97: NULL | Q97: NULL | R97: 80.86 | S97: 45744.501 | T97: PA_SRDC | U97: 45744.281 | V97: PAUSER | W97: NULL | X97: 1 | Y97: 201 | Z97: NULL | AA97: NULL | AB97: NULL | AC97: GENERIC WIRE | AD97: GENERIC WIRE | AE97: AI | AF97: - | AG97: https://www.vikingelectric.com/product/detail/68857/xhhw-aluminum-xhhw-1-str-grn-mr | AI97: MATERIAL | AJ97: =VLOOKUP(A97,'Classification Test Result'!$A$2:$D$2428,4,FALSE) -> #N/A | AL97: =_xlfn.XLOOKUP($A97,Results!$A$2:$A$2256,Results!G$2:G$2256,"") -> 0 | AM97: =_xlfn.XLOOKUP($A97,Results!$A$2:$A$2256,Results!H$2:H$2256,"") -> 0 | AN97: =_xlfn.XLOOKUP($A97,Results!$A$2:$A$2256,Results!I$2:I$2256,"") -> 0 | AO97: =_xlfn.XLOOKUP($A97,Results!$A$2:$A$2256,Results!J$2:J$2256,"") -> 0 | AP97: =_xlfn.XLOOKUP($A97,Results!$A$2:$A$2256,Results!K$2:K$2256,"") -> 0 | AQ97: =_xlfn.XLOOKUP($A97,Results!$A$2:$A$2256,Results!L$2:L$2256,"") -> 0 | AR97: =_xlfn.XLOOKUP($A97,Results!$A$2:$A$2256,Results!M$2:M$2256,"") -> 0 | AS97: =_xlfn.XLOOKUP($A97,Results!$A$2:$A$2256,Results!N$2:N$2256,"") -> 0 | ... BE97: =_xlfn.XLOOKUP($A97,Results!$A$2:$A$2256,Results!Z$2:Z$2256,"") -> TRUE
A98: 905775 | B98: 281663 | C98: NULL | D98: S008995642.001 | E98: =VLOOKUP(F98,'RPA Vendor Data '!F96:$G$2418,2) -> VIKING ELECTRIC | F98: 13536 | G98: 4 | H98: WIA. XHHW 250MCM STR YEL MR 250 XHHW YELLOW ALUMINUM WIRE | I98: 100 | J98: m | K98: M | L98: 840.96 | M98: Generic Wire | N98: XHHW 250MCM STR YEL MR | O98: NULL | P98: NULL | Q98: NULL | R98: 84.1 | S98: 45744.501 | T98: PA_SRDC | U98: 45744.281 | V98: PAUSER | W98: NULL | X98: 1 | Y98: 201 | Z98: NULL | AA98: NULL | AB98: NULL | AC98: GENERIC WIRE | AD98: GENERIC WIRE | AE98: AI | AF98: - | AG98: https://www.vikingelectric.com/product/detail/68872/xhhw-aluminum-xhhw-250mcm-str-yel-mr | AI98: MATERIAL | AJ98: =VLOOKUP(A98,'Classification Test Result'!$A$2:$D$2428,4,FALSE) -> #N/A | AL98: =_xlfn.XLOOKUP($A98,Results!$A$2:$A$2256,Results!G$2:G$2256,"") -> 0 | AM98: =_xlfn.XLOOKUP($A98,Results!$A$2:$A$2256,Results!H$2:H$2256,"") -> 0 | AN98: =_xlfn.XLOOKUP($A98,Results!$A$2:$A$2256,Results!I$2:I$2256,"") -> 0 | AO98: =_xlfn.XLOOKUP($A98,Results!$A$2:$A$2256,Results!J$2:J$2256,"") -> 0 | AP98: =_xlfn.XLOOKUP($A98,Results!$A$2:$A$2256,Results!K$2:K$2256,"") -> 0 | AQ98: =_xlfn.XLOOKUP($A98,Results!$A$2:$A$2256,Results!L$2:L$2256,"") -> 0 | AR98: =_xlfn.XLOOKUP($A98,Results!$A$2:$A$2256,Results!M$2:M$2256,"") -> 0 | AS98: =_xlfn.XLOOKUP($A98,Results!$A$2:$A$2256,Results!N$2:N$2256,"") -> 0 | ... BE98: =_xlfn.XLOOKUP($A98,Results!$A$2:$A$2256,Results!Z$2:Z$2256,"") -> TRUE
A99: 905776 | B99: 281663 | C99: NULL | D99: S008995642.001 | E99: =VLOOKUP(F99,'RPA Vendor Data '!F97:$G$2418,2) -> VIKING ELECTRIC | F99: 13536 | G99: 3 | H99: WIA. XHHW 250MCM STR ORG MR 250 XHHW ORANGE ALUMINUM WIRE | I99: 100 | J99: m | K99: M | L99: 840.96 | M99: Generic Wire | N99: XHHW 250MCM STR ORG MR | O99: NULL | P99: NULL | Q99: NULL | R99: 84.1 | S99: 45744.501 | T99: PA_SRDC | U99: 45744.281 | V99: PAUSER | W99: NULL | X99: 1 | Y99: 201 | Z99: NULL | AA99: NULL | AB99: NULL | AC99: GENERIC WIRE | AD99: GENERIC WIRE | AE99: AI | AF99: - | AG99: https://www.vikingelectric.com/product/detail/68869/xhhw-aluminum-xhhw-250mcm-str-org-mr | AI99: MATERIAL | AJ99: =VLOOKUP(A99,'Classification Test Result'!$A$2:$D$2428,4,FALSE) -> #N/A | AL99: =_xlfn.XLOOKUP($A99,Results!$A$2:$A$2256,Results!G$2:G$2256,"") -> 0 | AM99: =_xlfn.XLOOKUP($A99,Results!$A$2:$A$2256,Results!H$2:H$2256,"") -> 0 | AN99: =_xlfn.XLOOKUP($A99,Results!$A$2:$A$2256,Results!I$2:I$2256,"") -> 0 | AO99: =_xlfn.XLOOKUP($A99,Results!$A$2:$A$2256,Results!J$2:J$2256,"") -> 0 | AP99: =_xlfn.XLOOKUP($A99,Results!$A$2:$A$2256,Results!K$2:K$2256,"") -> 0 | AQ99: =_xlfn.XLOOKUP($A99,Results!$A$2:$A$2256,Results!L$2:L$2256,"") -> 0 | AR99: =_xlfn.XLOOKUP($A99,Results!$A$2:$A$2256,Results!M$2:M$2256,"") -> 0 | AS99: =_xlfn.XLOOKUP($A99,Results!$A$2:$A$2256,Results!N$2:N$2256,"") -> 0 | ... BE99: =_xlfn.XLOOKUP($A99,Results!$A$2:$A$2256,Results!Z$2:Z$2256,"") -> TRUE
A100: 905777 | B100: 281663 | C100: NULL | D100: S008995642.001 | E100: =VLOOKUP(F100,'RPA Vendor Data '!F99:$G$2418,2) -> VIKING ELECTRIC | F100: 13536 | G100: 5 | H100: WIA. XHHW 250MCM STR GRY MR 250 XHHW GREY ALUMINUM WIRE | I100: 100 | J100: m | K100: M | L100: 840.96 | M100: Generic Wire | N100: XHHW 250MCM STR GRY MR | O100: NULL | P100: NULL | Q100: NULL | R100: 84.1 | S100: 45744.501 | T100: PA_SRDC | U100: 45744.281 | V100: PAUSER | W100: NULL | X100: 1 | Y100: 201 | Z100: NULL | AA100: NULL | AB100: NULL | AC100: GENERIC WIRE | AD100: GENERIC WIRE | AE100: AI | AF100: - | AG100: https://www.vikingelectric.com/product/detail/68868/xhhw-aluminum-xhhw-250mcm-str-gry-mr | AI100: MATERIAL | AJ100: =VLOOKUP(A100,'Classification Test Result'!$A$2:$D$2428,4,FALSE) -> #N/A | AL100: =_xlfn.XLOOKUP($A100,Results!$A$2:$A$2256,Results!G$2:G$2256,"") -> 0 | AM100: =_xlfn.XLOOKUP($A100,Results!$A$2:$A$2256,Results!H$2:H$2256,"") -> 0 | AN100: =_xlfn.XLOOKUP($A100,Results!$A$2:$A$2256,Results!I$2:I$2256,"") -> 0 | AO100: =_xlfn.XLOOKUP($A100,Results!$A$2:$A$2256,Results!J$2:J$2256,"") -> 0 | AP100: =_xlfn.XLOOKUP($A100,Results!$A$2:$A$2256,Results!K$2:K$2256,"") -> 0 | AQ100: =_xlfn.XLOOKUP($A100,Results!$A$2:$A$2256,Results!L$2:L$2256,"") -> 0 | AR100: =_xlfn.XLOOKUP($A100,Results!$A$2:$A$2256,Results!M$2:M$2256,"") -> 0 | AS100: =_xlfn.XLOOKUP($A100,Results!$A$2:$A$2256,Results!N$2:N$2256,"") -> 0 | ... BE100: =_xlfn.XLOOKUP($A100,Results!$A$2:$A$2256,Results!Z$2:Z$2256,"") -> TRUE
...

Sheet Results
A1: IVCE_DTL_UID | B1: ITM_LDSC | C1: MFR_NM | D1: MFR_PRT_NUM | E1: AKS_PRT_NUM | F1: UPC_CD | G1: ItemID | H1: MfrPartNum | I1: MfrName | J1: UPC | K1: UNSPSC | L1: AKPartNum | M1: DescriptionID | N1: ItemDescription | O1: CleanName | P1: UncleanName | Q1: MfrNameMatchType | R1: DescriptionSimilarity | S1: PartNumberConfidenceScore | T1: ManufacturerNameConfidenceScore | U1: UNSPSCConfidenceScore | V1: Semantic_MfrName | W1: Semantic_MfrNameConfidenceScore | X1: Semantic_UNSPSC | Y1: Semantic_UNSPSCConfidenceScore | Z1: Semantic_IsMfrClean
A2: 905679 | B2: YALE GP050VX 5,000# WAREHOUSE FORKLIFT | C2: YALE | D2: GP050VX
A3: 905680 | B3: X7 COOPER CROUSE-HINDS DIVISION CHICO CHICO X FIBER 1 LB AK10289128 | C3: CROUSE-HINDS | D3: CHICO X7 | E3: AK10289128 | O3: CROUSE HINDS | P3: COOPER CROUSE-HINDS DIVISION | Q3: SINGLE_MATCH | T3: 100
A4: 905681 | B4: X CLOSE GENERIC VENDOR-TUBPA 3/4 3/4 X CLOSE-GALVANIZED CONDUIT NIPPLE | C4: GENERIC CONDUIT/CONDUIT FITTINGS | D4: 3/4 X CLOSE | E4: AK10432182 | O4: GENERIC CONDUIT/CONDUIT FITTINGS | P4: GENERIC VENDOR-TUBPA | Q4: SINGLE_MATCH | T4: 100 | V4: SOUTHWIRE | W4: 78 | X4: 39131718 | Y4: 78 | Z4: TRUE
A5: 905682 | B5: WS LMRC-211 770734 DIGITAL V.2 SGLE RELAY RM CONTROLLER ON/OFF 0-10V DIMM | C5: WATTSTOPPER | D5: LMRC-211 | G5: 735909 | H5: LMRC211 | I5: WATTSTOPPER | J5: 754182929030 | K5: 45111808 | M5: 480852 | N5: WATT LMRC-211 ROOM CTRLR | O5: WATTSTOPPER | Q5: NO_MANUFACTURERS_FOUND | R5: 0.7024660648886563 | S5: 100 | T5: 100 | U5: 96 | V5: WATTSTOPPER | W5: 62 | Z5: TRUE
A6: 905683 | B6: WRMLD LOT 729287 * Item not returnable without RGA * (4) WD10W350-60 (8) CP10-S30 (8) WD10W350-ECS | C6: WIREMOLD | D6: LOT
A7: 905684 | B7: Wright 311 10PC Hex Bit Socket Set with 3/8 Drive Sizes 1/8 5/32 3/16 7/32 1/4 5/16 & 3/8, and 1/2 Drive Sizes 1/2 9/16 5/8 On Rail w/ 10 Clips | C7: WRIGHT TOOL | D7: 311 | F7: 76799003119 | O7: WRIGHT TOOL | P7: WRIGHT | Q7: SINGLE_MATCH | T7: 90 | X7: 27110000 | Y7: 78
A8: 905685 | B8: WIREMOLD CO SGC2-RT SINGLE GANG COMM PLATE ORTRONICS | C8: WIREMOLD | D8: SGC2-RT | O8: WIREMOLD | P8: WIREMOLD CO | Q8: MULTIPLE_MATCHES_ONE_VALID | T8: 50 | V8: ORBIT INDUSTRIES | W8: 77 | X8: 39120000 | Y8: 77 | Z8: TRUE
A9: 905686 | B9: WIREMOLD CO SGC2-ACT SINGLE GANG COMM PLT ACTIVATE | C9: WIREMOLD | D9: SGC2-ACT | O9: WIREMOLD | P9: WIREMOLD CO | Q9: SINGLE_MATCH | T9: 100
A10: 905687 | B10: WIREMOLD CO NP800C-10-2B NP800 ANOD POLE 10FT.2IN.L WBOX END | C10: WIREMOLD | D10: NP800C-10-2B | O10: WIREMOLD | P10: WIREMOLD CO | Q10: SINGLE_MATCH | T10: 100
A11: 905688 | B11: WS (Winter Service Charge - Nov 1 - Mar 31)
A12: 905689 | B12: WS (Winter Service Charge - Nov 1 - Mar 31)
A13: 905690 | B13: WS (Winter Service Charge - Nov 1 - Mar 31)
A14: 905691 | B14: WIRE-LINE 12550 1/2 STAPLE 500/BAG | C14: WIRE-LINE | D14: 12550 | F14: 60550512550 | O14: GENERIC WIRE | P14: WIRE | Q14: SINGLE_MATCH | T14: 75 | X14: 39121700 | Y14: 63
A15: 905692 | B15: WIRE-LINE 12550 1/2 STAPLE 500/BAG | C15: WIRE-LINE | D15: 12550 | F15: 60550512550 | O15: GENERIC WIRE | P15: WIRE | Q15: SINGLE_MATCH | T15: 75 | X15: 39121700 | Y15: 63
A16: 905693 | B16: WIRE-LINE 12550 1/2 STAPLE 500/BAG | C16: WIRE-LINE | D16: 12550 | F16: 60550512550 | O16: GENERIC WIRE | P16: WIRE | Q16: SINGLE_MATCH | T16: 75 | X16: 39121700 | Y16: 63
A17: 905694 | B17: WIRE-LINE 12550 1/2 STAPLE 500/BAG | C17: WIRE-LINE | D17: 12550 | F17: 60550512550 | O17: GENERIC WIRE | P17: WIRE | Q17: SINGLE_MATCH | T17: 75 | X17: 39121700 | Y17: 63
A18: 905695 | B18: WIRE THHN4-GRY-STR-CU CUT | C18: GENERIC WIRE | D18: THHN-4-STR19-GRY-CU | O18: GENERIC WIRE | P18: WIRE | Q18: SINGLE_MATCH | T18: 75 | V18: SOUTHWIRE | W18: 79 | X18: 26121614 | Y18: 79 | Z18: TRUE
A19: 905696 | B19: WIRE BARE-SD-6-SOL-CU-5000MSTR Cuts: 5 @ 1000 ft | C19: GENERIC WIRE | D19: BARE-CU-SD-6-SOL-CUT REEL | O19: GENERIC WIRE | P19: WIRE | Q19: SINGLE_MATCH | T19: 75 | V19: CAROLINA PRODUCTS | W19: 75 | X19: 26120000 | Y19: 75 | Z19: TRUE
A20: 905697 | B20: Wire 8 AWG Yellow THHN Stranded 500 Foot Reel 600 Volt Copper Wire | C20: GENERIC WIRE | D20: THHN-8-STR19-YEL-CU-500S/R | E20: AK10439071 | F20: 98010023125 | O20: GENERIC WIRE | P20: COPPER | Q20: SINGLE_MATCH | T20: 90 | X20: 26120000 | Y20: 77
A21: 905698 | B21: Wire 8 AWG Orange THHN Stranded 500 Foot Reel 600 Volt Copper Wire | C21: GENERIC WIRE | D21: THHN-8-STR19-ORN-CU-500S/R | E21: AK10439058 | F21: 98010023145 | O21: GENERIC WIRE | P21: COPPER | Q21: SINGLE_MATCH | T21: 90 | X21: 26120000 | Y21: 76
A22: 905699 | B22: Wire 8 AWG Brown THHN Stranded 500 Foot Reel 600 Volt Copper Wire | C22: GENERIC WIRE | D22: THHN-8-STR19-BRN-CU-500S/R | E22: AK10439049 | F22: 98010023115 | O22: GENERIC WIRE | P22: COPPER | Q22: SINGLE_MATCH | T22: 90 | V22: SOUTHWIRE | W22: 77 | X22: 26121614 | Y22: 77 | Z22: TRUE
A23: 905700 | B23: Wire 12 AWG White THHN Stranded 500 Foot Reel 600 Volt Copper Wire | C23: GENERIC WIRE | D23: THHN-12-STR19-WHT-CU-500S/R | O23: GENERIC WIRE | P23: COPPER | Q23: SINGLE_MATCH | T23: 90 | X23: 26120000 | Y23: 77
A24: 905701 | B24: Wire 12 AWG White THHN Stranded 500 Foot Reel 600 Volt Copper Wire | C24: GENERIC WIRE | D24: THHN-12-STR19-WHT-CU-500S/R | E24: AK10438370 | F24: 98010022910 | O24: GENERIC WIRE | P24: COPPER | Q24: SINGLE_MATCH | T24: 90 | X24: 26120000 | Y24: 77
A25: 905702 | B25: Wire 12 AWG Green THHN Stranded 500 Foot Reel 600 Volt Copper Wire | C25: GENERIC WIRE | D25: THHN-12-STR19-GRN-CU-500S/R | E25: AK10438370 | F25: 98010022910 | O25: GENERIC WIRE | P25: COPPER | Q25: SINGLE_MATCH | T25: 90 | X25: 26120000 | Y25: 78
A26: 905703 | B26: Wire 12 AWG Green THHN Stranded 500 Foot Reel 600 Volt Copper Wire | C26: GENERIC WIRE | D26: THHN-12-STR19-GRN-CU-500S/R | E26: AK10438354 | F26: 98010022940 | O26: GENERIC WIRE | P26: COPPER | Q26: SINGLE_MATCH | T26: 90 | X26: 26120000 | Y26: 78
A27: 905704 | B27: Wire 12 AWG Blue THHN Stranded 500 Foot Reel 600 Volt Copper Wire | C27: GENERIC WIRE | D27: THHN-12-STR19-BLU-CU-500S/R | E27: AK10438350 | F27: 98010022930 | O27: GENERIC WIRE | P27: COPPER | Q27: SINGLE_MATCH | T27: 90 | V27: SOUTHWIRE | W27: 62 | X27: 26120000 | Y27: 77 | Z27: TRUE
A28: 905705 | B28: Wire 12 AWG Black THHN Stranded 500 Foot Reel 600 Volt Copper Wire | C28: GENERIC WIRE | D28: THHN-12-STR19-BLK-CU-500S/R | E28: AK10438348 | F28: 98010022900 | O28: GENERIC WIRE | P28: COPPER | Q28: SINGLE_MATCH | T28: 90 | X28: 26120000 | Y28: 77
A29: 905706 | B29: Wire 10 AWG Green THHN Stranded 500 Foot Reel 600 Volt Copper Wire | C29: GENERIC WIRE | D29: THHN-10-STR19-GRN-CU-500S/R | E29: AK10438157 | F29: 98010023040 | O29: GENERIC WIRE | P29: COPPER | Q29: SINGLE_MATCH | T29: 90 | X29: 26120000 | Y29: 78
A30: 905707 | B30: Wire 10 AWG Green THHN Stranded 500 Foot Reel 600 Volt Copper Wire | C30: GENERIC WIRE | D30: THHN-10-STR19-GRN-CU-500S/R | E30: AK10438157 | F30: 98010023040 | O30: GENERIC WIRE | P30: COPPER | Q30: SINGLE_MATCH | T30: 90 | X30: 26120000 | Y30: 78
A31: 905708 | B31: Wire 10 AWG Blue THHN Stranded 500 Foot Reel 600 Volt Copper Wire | C31: GENERIC WIRE | D31: THHN-10-STR19-BLU-CU-500S/R | E31: AK10438148 | F31: 98010023030 | O31: GENERIC WIRE | P31: COPPER | Q31: SINGLE_MATCH | T31: 90 | X31: 26120000 | Y31: 76
A32: 905709 | B32: WIR FPBTCBK 234591 FLOORPORT FLANGED BLANK TOP BK | C32: WIREMOLD | D32: FPBTCBK | E32: AK10565407 | F32: 78677615201 | X32: 39121300 | Y32: 76
A33: 905710 | B33: WINTER SERVICE CHARGE
A34: 905711 | B34: WINTER SERVICE
A35: 905712 | B35: WINTER SERVICE
A36: 905713 | B36: WINTER SERVICE
A37: 905714 | B37: WINTER SERVICE
A38: 905715 | B38: WINTER SERVICE
A39: 905716 | B39: WIEGMANN SCF1010 FLUSH SCREW COVER ONLY PAINTED N1 | C39: WIEGMANN | D39: SCF1010 | F39: 78672531352 | G39: 1112794 | H39: SCF1010 | I39: WIEGMANN | J39: 786725313525 | K39: 39121302 | M39: 101789 | N39: WIEG SCF1010 NM1 FLUSH CVR F/SC BX | O39: WIEGMANN | P39: WIEGMANN | Q39: SINGLE_MATCH | R39: 0.7284102740093518 | S39: 100 | T39: 100 | U39: 100 | V39: WIEGMANN | W39: 79 | X39: 39121300 | Y39: 64 | Z39: TRUE
A40: 905717 | B40: WIEG SC121204NK SCPB 12X12X4 NO KO | C40: WIEGMANN | D40: SC121204NK | E40: AK10519466 | G40: 341754 | H40: SC121204NK | I40: WIEGMANN | J40: 786725313914 | K40: 39121332 | L40: AK10519466 | M40: 387559 | N40: WIEG SC121204NK NEMA1 SC BOX-NO KO | O40: WIEGMANN | P40: WIEG | Q40: SINGLE_MATCH | R40: 0.8481143428560945 | S40: 100 | T40: 100 | U40: 100 | V40: WIEGMANN | W40: 87 | X40: 39121300 | Y40: 87 | Z40: TRUE
A41: 905718 | B41: WIEG SC080804NK SCPB 8X8X4 NO KO | C41: WIEGMANN | D41: SC080804NK | E41: AK10519457 | G41: 341749 | H41: SC080804NK | I41: WIEGMANN | J41: 786725312917 | K41: 39121332 | L41: AK10519457 | M41: 597551 | N41: WIEG SC080804NK NEMA1 SC BOX-NO KO | O41: WIEGMANN | P41: WIEG | Q41: SINGLE_MATCH | R41: 0.8265624 | S41: 100 | T41: 100 | U41: 100 | V41: WIEGMANN | W41: 85 | X41: 39121300 | Y41: 85 | Z41: TRUE
A42: 905719 | B42: WIEG SC060604NK SCPB 6X6X4 NO KO | C42: WIEGMANN | D42: SC060604NK | E42: AK10519452 | G42: 341746 | H42: SC060604NK | I42: WIEGMANN | J42: 786725312313 | K42: 39121332 | L42: AK10519452 | M42: 169683 | N42: WIEG SC060604NK NEMA1 SC BOX-NO KO | O42: WIEGMANN | P42: WIEG | Q42: SINGLE_MATCH | R42: 0.8339175684548591 | S42: 100 | T42: 100 | U42: 100 | V42: WIEGMANN | W42: 86 | X42: 39121300 | Y42: 86 | Z42: TRUE
A43: 905720 | B43: WIEG HS882NK N1 WIREWAY 8X8X2FT NO KO | C43: WIEGMANN | D43: HS882NK | G43: 745686 | H43: HS882NK | I43: WIEGMANN | J43: 786725610754 | K43: 39131710 | M43: 341557 | N43: WIEG HS882NK NM1 HNG/SC WWY-NO KO | O43: WIEGMANN | P43: WIEG | Q43: SINGLE_MATCH | R43: 0.7418263535195936 | S43: 100 | T43: 100 | U43: 100 | V43: WIEGMANN | W43: 89 | X43: 39131710 | Y43: 89 | Z43: TRUE
A44: 905721 | B44: WIEG E0808NK N1 WIREWAY ENDCAP 8IN NO KO | C44: WIEGMANN | D44: E0808NK | E44: AK10519193 | G44: 341710 | H44: E0808NK | I44: WIEGMANN | J44: 786725860906 | K44: 39131711 | L44: AK10519193 | M44: 234588 | N44: WIEG E0808NK NK N18X8 CAP END | O44: WIEGMANN | P44: WIEG | Q44: SINGLE_MATCH | R44: 0.7847836780355778 | S44: 100 | T44: 100 | U44: 100 | V44: WIEGMANN | W44: 90 | X44: 39131711 | Y44: 90 | Z44: TRUE
A45: 905723 | B45: WIC. THHN 3/0 STR YEL MR | C45: GENERIC WIRE | D45: THHN 3/0 STR YEL MR | O45: GENERIC WIRE | P45: WIC | Q45: SINGLE_MATCH | T45: 60 | V45: PRIORITY WIRE & CABLE | W45: 79 | X45: 26121500 | Y45: 79 | Z45: TRUE
A46: 905724 | B46: WIC. THHN 3/0 STR ORG MR | C46: GENERIC WIRE | D46: THHN 3/0 STR ORG MR | O46: GENERIC WIRE | P46: WIC | Q46: SINGLE_MATCH | T46: 60 | V46: PRIORITY WIRE & CABLE | W46: 63 | X46: 26120000 | Y46: 80 | Z46: TRUE
A47: 905725 | B47: WIC. THHN 3/0 STR BRN MR | C47: GENERIC WIRE | D47: THHN 3/0 STR BRN MR | O47: GENERIC WIRE | P47: WIC | Q47: SINGLE_MATCH | T47: 60 | V47: PRIORITY WIRE & CABLE | W47: 80 | X47: 26121500 | Y47: 80 | Z47: TRUE
A48: 905726 | B48: WIC. THHN 3/0 STR BLK MR | C48: GENERIC WIRE | D48: WIC. THHN 3/0 STR BLK MR | F48: 98010063411 | O48: GENERIC WIRE | P48: WIC | Q48: SINGLE_MATCH | T48: 60 | V48: PRIORITY WIRE & CABLE | W48: 81 | X48: 26121500 | Y48: 81 | Z48: TRUE
A49: 905727 | B49: WIC. THHN 1 STR WHT MR | C49: GENERIC WIRE | D49: THHN 1 STR WHT MR | O49: GENERIC WIRE | P49: WIC | Q49: SINGLE_MATCH | T49: 60 | V49: SOUTHWIRE | W49: 62 | X49: 26120000 | Y49: 78 | Z49: TRUE
A50: 905728 | B50: WIC. THHN 1 STR RED MR | C50: GENERIC WIRE | D50: THHN 1 STR RED MR | O50: GENERIC WIRE | P50: WIC | Q50: SINGLE_MATCH | T50: 60 | X50: 26120000 | Y50: 79
A51: 905729 | B51: WIC. THHN 1 STR BLU MR | C51: GENERIC WIRE | D51: THHN 1 STR BLU MR | O51: GENERIC WIRE | P51: WIC | Q51: SINGLE_MATCH | T51: 60 | V51: PRIORITY WIRE & CABLE | W51: 79 | X51: 26121500 | Y51: 79 | Z51: TRUE
A52: 905730 | B52: WIC. THHN 1 STR BLK MR | C52: GENERIC WIRE | D52: THHN 1 STR BLK MR | E52: AK10438561 | O52: GENERIC WIRE | P52: WIC | Q52: SINGLE_MATCH | T52: 60 | V52: PRIORITY WIRE & CABLE | W52: 80 | X52: 26121500 | Y52: 80 | Z52: TRUE
A53: 905734 | B53: WIC. HCFAP 5858-42-00 12/2 STR 250C BLK WHT GRN W/#10 ALUM BOND ALUM JKT - STOCK IN CHINO, CA (PLUS FREIGHT) - *Procured Item* | C53: GENERIC WIRE | D53: HCFAP 5858-42-00 | G53: 336533 | H53: 58584200 | I53: AFC CABLE SYSTEMS | J53: 077680259226 | K53: 26121600 | L53: AK10085157 | M53: 479872 | N53: AFC 5858-42-00 12-2AWG AL CABLE | O53: AFC CABLE SYSTEMS | Q53: NO_VALID_MATCHES | R53: 0.5636987681416159 | S53: 82 | T53: 64 | U53: 56
A54: 905739 | B54: WIC. THHN 6 STR WHT MR | C54: GENERIC WIRE | D54: WIC THHN 6 STR WHT MR | F54: 98010063162 | O54: GENERIC WIRE | P54: WIC | Q54: SINGLE_MATCH | T54: 60 | V54: SOUTHWIRE | W54: 62 | X54: 26120000 | Y54: 79 | Z54: TRUE
A55: 905740 | B55: WIC. THHN 6 STR RED MR | C55: GENERIC WIRE | D55: WIC THHN 6 STR RED MR | F55: 98010013170 | O55: GENERIC WIRE | P55: WIC | Q55: SINGLE_MATCH | T55: 60 | V55: SOUTHWIRE | W55: 61 | X55: 26120000 | Y55: 80 | Z55: TRUE
A56: 905741 | B56: WIC. THHN 6 STR BLK MR | C56: GENERIC WIRE | D56: WIC THHN 6 STR BLK MR | F56: 98010013150 | O56: GENERIC WIRE | P56: WIC | Q56: SINGLE_MATCH | T56: 60 | V56: PRIORITY WIRE & CABLE | W56: 66 | X56: 26120000 | Y56: 80 | Z56: TRUE
A57: 905742 | B57: WIC. THHN 2 STR WHT MR | C57: GENERIC WIRE | D57: WIC THHN 2 STR WHT MR | F57: 98010023313 | O57: GENERIC WIRE | P57: WIC | Q57: SINGLE_MATCH | T57: 60 | V57: SOUTHWIRE | W57: 78 | X57: 26121614 | Y57: 78 | Z57: TRUE
A58: 905743 | B58: WIC. THHN 2 STR WHT MR | C58: GENERIC WIRE | D58: WIC THHN 2 STR WHT MR | F58: 98010023313 | O58: GENERIC WIRE | P58: WIC | Q58: SINGLE_MATCH | T58: 60 | V58: SOUTHWIRE | W58: 78 | X58: 26121614 | Y58: 78 | Z58: TRUE
A59: 905744 | B59: WIC. THHN 2 STR WHT MR | C59: GENERIC WIRE | D59: WIC THHN 2 STR WHT MR | F59: 98010023313 | O59: GENERIC WIRE | P59: WIC | Q59: SINGLE_MATCH | T59: 60 | V59: SOUTHWIRE | W59: 78 | X59: 26121614 | Y59: 78 | Z59: TRUE
A60: 905745 | B60: WIC. THHN 2 STR WHT MR | C60: GENERIC WIRE | D60: WIC THHN 2 STR WHT MR | F60: 98010023313 | O60: GENERIC WIRE | P60: WIC | Q60: SINGLE_MATCH | T60: 60 | V60: SOUTHWIRE | W60: 78 | X60: 26121614 | Y60: 78 | Z60: TRUE
A61: 905746 | B61: WIC. THHN 2 STR RED MR | C61: GENERIC WIRE | D61: WIC THHN 2 STR RED MR | F61: 98010023323 | O61: GENERIC WIRE | P61: WIC | Q61: SINGLE_MATCH | T61: 60 | V61: SOUTHWIRE | W61: 62 | X61: 26120000 | Y61: 78 | Z61: TRUE
A62: 905747 | B62: WIC. THHN 2 STR RED MR | C62: GENERIC WIRE | D62: WIC THHN 2 STR RED MR | F62: 98010023323 | O62: GENERIC WIRE | P62: WIC | Q62: SINGLE_MATCH | T62: 60 | V62: SOUTHWIRE | W62: 62 | X62: 26120000 | Y62: 78 | Z62: TRUE
A63: 905748 | B63: WIC. THHN 2 STR RED MR | C63: GENERIC WIRE | D63: WIC THHN 2 STR RED MR | F63: 98010023323 | O63: GENERIC WIRE | P63: WIC | Q63: SINGLE_MATCH | T63: 60 | V63: SOUTHWIRE | W63: 62 | X63: 26120000 | Y63: 78 | Z63: TRUE
A64: 905749 | B64: WIC. THHN 2 STR RED MR | C64: GENERIC WIRE | D64: WIC THHN 2 STR RED MR | F64: 98010023323 | O64: GENERIC WIRE | P64: WIC | Q64: SINGLE_MATCH | T64: 60 | V64: SOUTHWIRE | W64: 62 | X64: 26120000 | Y64: 78 | Z64: TRUE
A65: 905750 | B65: WIC. THHN 2 STR BLK MR | C65: GENERIC WIRE | D65: WIC THHN 2 STR BLK MR | F65: 98010023303 | O65: GENERIC WIRE | P65: WIC | Q65: SINGLE_MATCH | T65: 60 | V65: PRIORITY WIRE & CABLE | W65: 79 | X65: 26121500 | Y65: 79 | Z65: TRUE
... A68: 905753 | B68: WIC. THHN 2 STR BLK MR | C68: GENERIC WIRE | D68: WIC THHN 2 STR BLK MR | F68: 98010023303 | O68: GENERIC WIRE | P68: WIC | Q68: SINGLE_MATCH | T68: 60 | V68: PRIORITY WIRE & CABLE | W68: 79 | X68: 26121500 | Y68: 79 | Z68: TRUE
A69: 905756 | B69: WIC 8 THHN STR YEL CUT REEL Cuts: 1 @ 185 ft | C69: GENERIC WIRE | D69: THHN-8-YEL-19STR-CU-5O00R | O69: GENERIC WIRE | P69: WIC | Q69: SINGLE_MATCH | T69: 60
A70: 905757 | B70: WIC 8 THHN STR WHT CUT REEL Cuts: 1 @ 500 ft | C70: GENERIC WIRE | D70: 8 THHN STR WHT CUT REEL | O70: GENERIC WIRE | P70: WIC | Q70: SINGLE_MATCH | T70: 60 | X70: 26120000 | Y70: 75
A71: 905758 | B71: WIC 8 THHN STR RED 500R | C71: GENERIC WIRE | D71: 8 THHN STR RED 500R | O71: GENERIC WIRE | P71: WIC | Q71: SINGLE_MATCH | T71: 60 | V71: SOUTHWIRE | W71: 64 | X71: 26120000 | Y71: 81 | Z71: TRUE
A72: 905759 | B72: WIC 8 THHN STR ORG CUT REEL Cuts: 1 @ 185 ft | C72: GENERIC WIRE | D72: THHN-8-ORG-19STR-CU-5000R | O72: GENERIC WIRE | P72: WIC | Q72: SINGLE_MATCH | T72: 60 | V72: SOUTHWIRE | W72: 75 | X72: 26121614 | Y72: 75 | Z72: TRUE
A73: 905760 | B73: WIC 8 THHN STR BRN CUT REEL Cuts: 1 @ 185 ft | C73: GENERIC WIRE | D73: THHN-8-BRN-19STR-CU-5000R | O73: GENERIC WIRE | P73: WIC | Q73: SINGLE_MATCH | T73: 60 | V73: SOUTHWIRE | W73: 76 | X73: 26121614 | Y73: 76 | Z73: TRUE
A74: 905761 | B74: WIC 8 THHN STR BLK CUT REEL Cuts: 1 @ 500 ft | C74: GENERIC WIRE | D74: 8 THHN STR BLK CUT REEL | O74: GENERIC WIRE | P74: WIC | Q74: SINGLE_MATCH | T74: 60 | V74: CAROLINA PRODUCTS | W74: 78 | X74: 26120000 | Y74: 78 | Z74: TRUE
A75: 905762 | B75: WIC 6 THHN STR WHT 1000R | C75: GENERIC WIRE | D75: 6 THHN STR WHT 1000R | O75: GENERIC WIRE | P75: WIC | Q75: SINGLE_MATCH | T75: 60 | V75: SOUTHWIRE | W75: 64 | X75: 26120000 | Y75: 80 | Z75: TRUE
A76: 905763 | B76: WIC 6 THHN STR RED CUT REEL Cuts: 1 @ 110 ft | C76: GENERIC WIRE | D76: 6 THHN STR RED CUT REEL | O76: GENERIC WIRE | P76: WIC | Q76: SINGLE_MATCH | T76: 60 | V76: SOUTHWIRE | W76: 77 | X76: 26121614 | Y76: 77 | Z76: TRUE
A77: 905766 | B77: WIC 6 THHN STR BLU CUT REEL Cuts: 1 @ 110 ft | C77: GENERIC WIRE | D77: 6 THHN STR BLU CUT REEL | O77: GENERIC WIRE | P77: WIC | Q77: SINGLE_MATCH | T77: 60 | V77: SOUTHWIRE | W77: 76 | X77: 26121614 | Y77: 76 | Z77: TRUE
A78: 905767 | B78: WIC 6 THHN STR BLK CUT REEL Cuts: 1 @ 110 ft | C78: GENERIC WIRE | D78: 6 THHN STR BLK CUT REEL | O78: GENERIC WIRE | P78: WIC | Q78: SINGLE_MATCH | T78: 60 | V78: SOUTHWIRE | W78: 76 | X78: 26121614 | Y78: 76 | Z78: TRUE
A79: 905768 | B79: WIC 12/2 CUMC STRND W/GRND ALUM JKT BLK/WHT 250 Coil | C79: GENERIC WIRE | D79: MC-STR-12/2 BLK/WHT 250' | O79: GENERIC WIRE | P79: WIC | Q79: SINGLE_MATCH | T79: 60 | V79: PRIORITY WIRE & CABLE | W79: 61 | X79: 26120000 | Y79: 76 | Z79: TRUE
A80: 905771 | B80: WIC 1 THHN STR YEL CUT REEL Cuts: 1 @ 186 ft | C80: GENERIC WIRE | D80: THHN-1-YEL-19STR-CU-2500R | O80: GENERIC WIRE | P80: WIC | Q80: SINGLE_MATCH | T80: 60
A81: 905772 | B81: WIC 1 THHN STR ORG CUT REEL Cuts: 1 @ 186 ft | C81: GENERIC WIRE | D81: THHN-1-ORG-19STR-CU-2500R | O81: GENERIC WIRE | P81: WIC | Q81: SINGLE_MATCH | T81: 60
A82: 905773 | B82: WIC 1 THHN STR BRN CUT REEL Cuts: 1 @ 186 ft | C82: GENERIC WIRE | D82: THHN-1-BRN-19STR-CU-2500R | O82: GENERIC WIRE | P82: WIC | Q82: SINGLE_MATCH | T82: 60 | V82: SOUTHWIRE | W82: 75 | X82: 26121614 | Y82: 75 | Z82: TRUE
A83: 905774 | B83: WIA. 1 STR GRN MR XHHW 1 XHHW GREEN ALUMINUM WIRE | C83: Generic Wire | D83: XHHW 1 STR GRN MR | O83: GENERIC WIRE | P83: ALUMINUM WIRE | Q83: MULTIPLE_MATCHES_ONE_VALID | T83: 50 | V83: SOUTHWIRE | W83: 78 | X83: 26121614 | Y83: 78 | Z83: TRUE
A84: 905775 | B84: WIA. XHHW 250MCM STR YEL MR 250 XHHW YELLOW ALUMINUM WIRE | C84: Generic Wire | D84: XHHW 250MCM STR YEL MR | O84: GENERIC WIRE | P84: ALUMINUM WIRE | Q84: SINGLE_MATCH | T84: 100 | V84: SOUTHWIRE | W84: 65 | X84: 26120000 | Y84: 80 | Z84: TRUE
A85: 905776 | B85: WIA. XHHW 250MCM STR ORG MR 250 XHHW ORANGE ALUMINUM WIRE | C85: Generic Wire | D85: XHHW 250MCM STR ORG MR | O85: GENERIC WIRE | P85: ALUMINUM WIRE | Q85: SINGLE_MATCH | T85: 100 | V85: SOUTHWIRE | W85: 63 | X85: 26120000 | Y85: 80 | Z85: TRUE
A86: 905777 | B86: WIA. XHHW 250MCM STR GRY MR 250 XHHW GREY ALUMINUM WIRE | C86: Generic Wire | D86: XHHW 250MCM STR GRY MR | O86: GENERIC WIRE | P86: ALUMINUM WIRE | Q86: SINGLE_MATCH | T86: 100 | V86: SOUTHWIRE | W86: 64 | X86: 26120000 | Y86: 80 | Z86: TRUE
A87: 905778 | B87: WIA. XHHW 250MCM STR BRN MR 250 XHHW BROWN ALUMINUM WIRE | C87: Generic Wire | D87: XHHW 250MCM STR BRN MR | O87: GENERIC WIRE | P87: ALUMINUM WIRE | Q87: SINGLE_MATCH | T87: 100 | V87: SOUTHWIRE | W87: 79 | X87: 26121614 | Y87: 79 | Z87: TRUE
A88: 905779 | B88: WI TGB50/3 BEANO WI 2G 2-3/16" DEEP BOX 3X1/2" H | C88: CENTAUR | D88: WI TGB50/3 | V88: WESTGATE MANUFACTURING | W88: 62 | X88: 39121300 | Y88: 77 | Z88: TRUE
A89: 905780 | B89: WI MES-760 WI STL SET SCREW CPLG 1/2" | C89: Madison Electric | D89: MES-760 | G89: 99042 | H89: MES760 | I89: SOUTHWIRE | J89: 784297200205 | K89: 39131707 | M89: 897429 | N89: MADISON MES-760 1/2 STL S/S CPLG | O89: SOUTHWIRE | Q89: NO_MANUFACTURERS_FOUND | R89: 0.7468297490912793 | S89: 100 | T89: 93 | U89: 94
A90: 905781 | B90: WI MES-750 WI STL SET SCREW CONN 1/2" | C90: Madison Electric | D90: MES-750 | G90: 102618 | H90: MES750 | I90: SOUTHWIRE | J90: 784297200007 | K90: 39121434 | M90: 498938 | N90: MADISON MES-750 1/2 STL S/S CONN | O90: SOUTHWIRE | Q90: NO_MANUFACTURERS_FOUND | R90: 0.7188088860276622 | S90: 100 | T90: 91 | U90: 90 | V90: M & W ELECTRIC MANUFACTURING CO | W90: 67 | X90: 39121434 | Y90: 81 | Z90: TRUE
A91: 905782 | B91: WI BP20 STEEL | C91: CENTAUR | D91: WI BP20
A92: 905783 | B92: WI 1/2-WBA WI 1/2 EMT CONDUIT HANGER | C92: CENTAUR | D92: WI 1 1/2-WBA | O92: GENERIC CONDUIT/CONDUIT FITTINGS | P92: CONDUIT | Q92: SINGLE_MATCH | T92: 95 | X92: 39121700 | Y92: 64
A93: 905784 | B93: WHTL ZI12-158 3643017 HS BTB PG10 1-5/8 STRT WHEATLND | C93: Wheatland Tube | D93: ZI12-158 | G93: 1063756 | H93: 12158 | I93: FASTENING SPECIALISTS | J93: 746071121588 | K93: 31161504 | M93: 548250 | N93: FAS 12158 5/8-11X3 SCREW | O93: FASTENING SPECIALISTS | Q93: NO_MANUFACTURERS_FOUND | R93: 0.5321772463794754 | S93: 54 | T93: 54 | U93: 39
A94: 905785 | B94: WGO 51204473 650195 *773-164/K194-4045 WALL-NUTS 4W PUSHW ORANGE 100/BOX | C94: WAGO | D94: 51204473 | E94: AK10985736 | F94: 4545474964
A95: 905786 | B95: WFP1_WEST WFP1 | C95: WEST
A96: 905787 | B96: WESTERN 20TCG-UR-12VFHK 11376278 Serial: 22001605 | C96: Western Global | D96: 20TCG-UR-12VFHK
A97: 905788 | B97: WEST KCDPFB150 | C97: WEST | D97: KCDPFB150
A98: 905789 | B98: WERNER L6208 LEANSAFE 8' STEPLADDER FIBERGLASS TYPE 1A 300LB. DUTY RATING LEANING LADDER ORANGE WITH YELLOW BACK RAIL Pn: 289802 | C98: WERNER | D98: L6208 | G98: 855657 | H98: L6208 | I98: WERNER COMPANY | J98: 051751129540 | K98: 30191506 | M98: 90080 | N98: WER L6208 8FT STEP LADDER | O98: WERNER COMPANY | P98: WERNER | Q98: SINGLE_MATCH | R98: 0.78812254 | S98: 100 | T98: 100 | U98: 100 | V98: WERNER COMPANY | W98: 83 | X98: 30191506 | Y98: 83 | Z98: TRUE
A99: 905790 | B99: WDM 1010100000 GRD TERM BLK 22-10AWG WPE4 | C99: Weidmuller | D99: 1010100000 | F99: 1010100000
A100: 905791 | B100: WDM 0514500000 1 PIECE IS 2 METERS 35X7.5 2-METER STEEL SLOTTED 2M DIN RAIL W/ SLOTS 1/EA = 2METERS | C100: Weidmuller | D100: 0514500000
A101: 905792 | B101: WBT4X6 4" DEEP X 6" WIDE X 10' SHIP WITHIN 30 DAYS LONG MUST BILL AND 4-5 WEEK LEADTIME | C101: WBT | D101: WBT4X6
A102: 905793 | B102: WBT4X6 4" DEEP X 6" WIDE X 10' LONG MUST BILL AND SHIP WITHIN 30 DAYS | C102: WBT | D102: WBT4X6
...

Sheet RPA Vendor Data 
F1: Vendor Number | G1: Vendor Name
F2: 130 | G2: ZENITH SYSTEMS LLC
F3: 10000 | G3: 0198 CUBESMART AZ TEMPE S
F4: 10006 | G4: 3451 PARTNERS LLP
F5: 10007 | G5: 3DREAMTEAM, INC.
F6: 10012 | G6: A & A COMMUNICATIONS
F7: 10013 | G7: A & A TRANSFER CO INC
F8: 10018 | G8: A.W. KUETTEL & SONS INC
F9: 10022 | G9: A-1 RENTAL SERVICES INC
F10: 10026 | G10: AAIM MANAGEMENT ASSOC.
F11: 10027 | G11: AARCH CASTER AND EQUIP.
F12: 10030 | G12: ABB INC
F13: 10031 | G13: ABB MOTORS AND MECHANICAL
... F86: 10203 | G86: ANDERSON ENGINEERING
F87: 10207 | G87: ANIXTER, INC. | H87: https://www.anixter.com/en_us.html
F88: 10210 | G88: ANNOINTED HANDS CLEANING
F89: 10211 | G89: ANOKA COUNTY
F90: 10213 | G90: ANRITSU AMERICAS SALES CO
F91: 10214 | G91: ANTHONY KEMPKER TRUCKING
F92: 10217 | G92: APEX
F93: 10218 | G93: API SUPPLY INC
F94: 10224 | G94: APPLIED ENGINEERING
F95: 10226 | G95: APPLIED PRODUCTS INC
F96: 10228 | G96: APS ENERGY SYSTEMS LLC
F97: 10230 | G97: AR DEPT OF LABOR-BOARD OF
F98: 10232 | G98: ARAMARK UNIFORM SERVICES
F99: 10233 | G99: ARC DOCUMENT SOLUTIONS
... F2161: 16592 | G2161: BEAR SCAFFOLD AND SERVICE
F2162: 16595 | G2162: BELL ELECTRICAL SUPPLY | H2162: https://www.bell-electrical.com/Welcome
F2163: 16602 | G2163: BIGGE CRANE AND RIGGING C
F2164: 16604 | G2164: BIG JOE CALIFORNIA INC.
F2165: 16610 | G2165: B.M. TONKIN INC.
F2166: 16618 | G2166: BRANDVIA ALLIANCE INC.
F2167: 16622 | G2167: BRIGHTVIEW DESIGN GROUP
F2168: 16625 | G2168: BSK ASSOCIATES
F2169: 16626 | G2169: BT LASER INC.
F2170: 16627 | G2170: BUCKLES-SMITH CORPORATION
F2171: 16628 | G2171: BUILDINGPOINT PACIFIC
F2172: 16629 | G2172: BUILDING ROBOTICS INC.
F2173: 16633 | G2173: BUTTE COUNTY OFF. OF EDUC
F2174: 16641 | G2174: CALIFORNIA SERVICE TOOL I
... F2418: 81964 | G2418: NATHAN D. POTTER

Sheet Sheet1
A1: MATERIAL
A2: TAX
A3: FREIGHT
A4: LABOR
A5: FEE
A10: Row Range | B10: Person Responsible
A11: 2- 349 | B11: Etna Z
A12: 350 - 643 | B12: Pallavi N
A13: 644- 989 | B13: Tyler Z
A14: 990- 1359 | B14: Senthil R
A15: 1360- 1729 | B15: Nandheni K
A16: 1730 - 2099 | B16: Wayne B
A17: 2100-2427 | B17: Swetha S

Sheet Classification
A1: FEE | B1: FREIGHT | C1: LABOR
A2: ENV ENVIRONMENTAL FEE | B2: _ MISC Freight Butler | C2: COE-GENERAL LABOR
A3: $25 MFR_SMALL ORDER FEE $25 MFR | B3: MISC Freight Butler | C3: COE-TRAVEL LABOR
A4: /CREDIT CARD FEE3.5% Fee3.5% CC FEE IF PAID BY CREDIT CARD | B4: MISC_MISC Freight Butler | C4: Labor
A5: $25 SMALL ORDER FEE | B5: COURIER FREIGHT CHARGE | C5: Labor - Oiler Overtime
A6: $25_MFR SMALL ORDER FEE $25 | B6: FREIGHT | C6: Labor - Oiler Overtime plus dinner
A7: ^ENGINEERING FEE Seismic bracing design for applicable overhead Electrical systems. | B7: Freight - Line Item | C7: Labor - Oiler Overtime plus lunch
A8: /CREDIT CARD FEE3.5% Fee3.5% CREDIT CARD FEE | B8: FREIGHT CHARGES | C8: Labor - Operator Overtime
A9: /EXPEDITE1 DAY EXPEDITE FEE | B9: FREIGHT Freight Out | C9: Labor - Operator Overtime plus dinner
A10: ^ENGINEERING FEE Seismic bracing design for applicable overhead Electrical systems. Pn: 21678FEESeismic & Gravity | B10: FREIGHT_FREIGHT Freight Out | C10: Labor - Operator Overtime plus lunch
A11: ^ENGINEERING 21678 FEE Seismic bracing design for applicable overhead Electrical systems. | B11: FRT FREIGHT CHARGE | C11: Labor - Rigger
A12: 310129 Fee | B12: FRT FREIGHT | C12: Labor - Rigger Overtime plus dinner
... A16: 9999204TRUCK RENTALAdmin Fee | B16: Shipping Shipping TBD | C16: OT LABOR
A17: ^ENGINEERING FEE Seismic bracing design for applicable overhead Electrical systems. *NS* * NON RETURNABLE* | B17: Standard shipping | C17: 45670
A18: ^Rental Fee for 1 Week UPC : | B18: S&H | C18: T&M PROGRAMMING LABOR
A19: CCH-04U CORNING OPTICAL COMMUNICATIONS CLOSET CONN HSG 4U F/12 PNLSRestocking Fee 15 % | B19: Delivery | C19: T&M_T&M PROGRAMMING LABOR
A20: CCH-04U CORNING OPTICAL COMMUNICATIONS CLOSET CONN HSG 4U F/12 PNLSRestocking Fee 15 %-42.31 | B20: Delivery - PER TRIP -Taxable | C20: TOTAL LABOR
A21: CDCSRV 1/0-1000MCM: 4 CONDUCTORS PARALLEL FEE | B21: DELIVERY CHARGE | C21: Dismantle Labor
A22: ^Rental Fee for 2 Weeks UPC : | B22: DELIVERY CHARGE DELIVERY CHARGE | C22: Erection Labor
A23: 0200 ENV FEE | B23: DELIVERY CHARGE DELIVERY CHARGE/FUEL SURCHARGE | C23: Alarm and Detection Regular Labor
A24: COLOR WASH OUT FEE | B24: DELIVERY FEE | C24: General Labor
A25: CUT CHARGE FEE *PRIORITY PRIME CUT FEE * | B25: Delivery Haulage | C25: Travel Labor
A26: CYL TRACKING SERVICE FEE | B26: Delivery Our Truck | C26: Labor Hours
A27: DIAGNOSTIC FEE DIAGNOSTIC FEE, FLUKE 1520 SN 87440053 SI 1017779 PN 25B ACCESSORIES: TEST LEADS INSIDE BLACK SOFT CASE | B27: FUEL DELIVERY SURCHARGE | C27: Installation Labor
A28: 0200 ENV FEE SERVICE WORK ORDER | B28: Shipping/Box Charge | C28: Labor for Repair
A29: Dispatch Fee Pre-Engineered PO# 80676933 | B29: FR PARTS FREIGHT ON PARTS UPS GROUND | C29: Labor Planned Maintenance
... A316: 2 TOTAL FSC - FUEL FEE | B316: EmergencyFee_ +EMERGENCYFEE Emergency Fee After Hours | C316: Labor ActivitiesService, Overtime
A317: 25% RESTOCK FEE | C317: LABOR BDenningLabor15 Minute Unit - B. Denning
A318: Environmental Fee (CZ Automatic Transfer Switch) MiscellaneousU42011 | C318: Labor Design/Eng. Serv .- Patton, D.
A319: 80683977_3_HANDLING_HANDLING FEE | C319: LABOR DIAMOND CORING TOOLS
A320: 80696524_3_HOFFMAN_HOFFMAN EXPEDITE FEE | C320: LABOR DIRECT FAST. LIGHT
A321: 9999204 TRUCK RENTAL Admin fee | C321: Labor Erect (Service) - HVAC Service
A322: Admin Fee9999204TRUCK RENTAL Road Service Fee | C322: Labor for November
A323: Environmental Fees | C323: LABOR FOR REPAIR
A324: BELOW MIN ORDER BELOW MIN ORDER FEE FROM LEVITON | C324: LABOR FOR THE ABOVE
A325: Business Prime Annual Membership Fee - Small | C325: LABOR HOURS (RT) DATA - TRAVEL
A326: Business Prime Membership Fee | C326: LABOR HOURS (RT) DATA-TRAVEL
A327: CANCELLATION FEE EX-WAY(UL) 2000A 3P3W+GE AL-AL, INDOOR | C327: LABOR INVOICE TOTAL
A328: CANCELLATION FEE OF BARE GROUND WIRE | C328: LABOR Labor Hours (shop)
... A331: ENVIRONMENTALCHARGE EPA CHARGE/WASTE FEES | C331: LABOR SPRINKLER - (2) TECHS AT 8 HRS EACH
A332: EPA CHARGE/WASTE FEES | C332: LABOR SPRINKLER - 3/4 (2) TECHS AT 4 HRS EACH | AD332: =VLOOKUP(G332,'Classification'!A2
A333: CHARGE FEE *Priority Prime Cut Fee * | C333: LABOR SPRINKLER -03/21 (2) TECHS AT 8 HRS EACH
A334: Cleaning/Maintenance Fee | C334: LABOR START TEST LABOR
A335: COLOR CLEAN OUT FEE | C335: LABOR TO DISMANTLE
A336: Consumer_Consumer Goods Fee | C336: Project Management Pro
A337: EXPEDITE FEE FOR DESIGN PROJECTS | C337: Labor Unpack, untape, repack, sort, count, recycle
A338: Dispatch Fee Alarm PO# p80672014 | C338: Labor_Labor - SM Labor
A339: Dispatch Fee Pre-Engineered | C339: LABOR_LABOR FOR THE ABOVE
A340: Dispatch Fee Pre-Engineered PO# 80700328 | C340: LABOR1201 LABOR FOR REPAIR
A341: FUEL PUMP OUT FEE | C341: LABOR1201_ LABOR1201 LABOR FOR REPAIR
A342: Fuel Surcharge Fee | C342: LABOR1801 LABOR FOR REPAIR
A343: ENGINEERING FEE | C343: LABOR301 LABOR FOR REPAIR
A344: HANDLING FEE | C344: LABOR501 LABOR FOR REPAIR
... A358: ZSVC WH100 SVC FEE STORAGE PICK PACK RECEIVE | C358: Parts, Labor and Misc
C359: Skirting: Installation- Union Labor
C360: PROGRAMMING LABOR
C361: PROJECT-LABOR: Project Labor
C362: REG LABOR
C363: Rental-Quoted w/Labor SystemScaffold
C364: Service Labor
C365: Service Labor Alarm PO# p80672014
C366: Service Tech 1 Labor (2/8/24)
C367: Service Tech 1 Labor 1/21/25
C368: Service Tech 1 Labor 1/28/25
C369: Service Tech 1 Labor 12/30/24
C370: Service Tech 1 Labor 2/3/25
... C394: TOOL REPAIR labor CHARGE

Sheet Classification Test Result
A1: IVCE_DTL_UID | B1: ITM_LDSC_CLEAN | C1: GT_CLASS | D1: CLASS | E1: CONFIDENCE
A2: 912106 | B2: erc 115 f20 alloy - cu-cu and cu-st me | C2: =IFERROR(INDEX(invoice_test_data!AI:AI, MATCH('Classification Test Result'!A2, invoice_test_data!A:A, 0)), "") | D2: MATERIAL | E2: 1
A3: 912107 | B3: ozg 5400s 4-in s/scr emt cplg 4 in emt sscr cplg coupling | C3: =IFERROR(INDEX(invoice_test_data!AI:AI, MATCH('Classification Test Result'!A3, invoice_test_data!A:A, 0)), "") | D3: MATERIAL | E3: 1
A4: 912108 | B4: thhs12gy-r2500 wire thhn-12-gry-sol-cu-2500 ft reel | C4: =IFERROR(INDEX(invoice_test_data!AI:AI, MATCH('Classification Test Result'!A4, invoice_test_data!A:A, 0)), "") | D4: MATERIAL | E4: 1
A5: 912109 | B5: thhs12we-r2500 wire thhn-12-wht-sol-cu-2500 ft reel | C5: =IFERROR(INDEX(invoice_test_data!AI:AI, MATCH('Classification Test Result'!A5, invoice_test_data!A:A, 0)), "") | D5: MATERIAL | E5: 1
A6: 912117 | B6: x10198 3x10 traffic mat | C6: =IFERROR(INDEX(invoice_test_data!AI:AI, MATCH('Classification Test Result'!A6, invoice_test_data!A:A, 0)), "") | D6: MATERIAL | E6: 1
A7: 912116 | B7: x10197 4x6 traffic mat | C7: =IFERROR(INDEX(invoice_test_data!AI:AI, MATCH('Classification Test Result'!A7, invoice_test_data!A:A, 0)), "") | D7: MATERIAL | E7: 1
A8: 912115 | B8: x10184 3x5 active scraper | C8: =IFERROR(INDEX(invoice_test_data!AI:AI, MATCH('Classification Test Result'!A8, invoice_test_data!A:A, 0)), "") | D8: MATERIAL | E8: 1
A9: 912114 | B9: x27069 sig soap svc | C9: =IFERROR(INDEX(invoice_test_data!AI:AI, MATCH('Classification Test Result'!A9, invoice_test_data!A:A, 0)), "") | D9: MATERIAL | E9: 1
A10: 912111 | B10: x10197 4x6 traffic mat | C10: =IFERROR(INDEX(invoice_test_data!AI:AI, MATCH('Classification Test Result'!A10, invoice_test_data!A:A, 0)), "") | D10: MATERIAL | E10: 1
A11: 912110 | B11: x10184 3x5 active scraper | C11: =IFERROR(INDEX(invoice_test_data!AI:AI, MATCH('Classification Test Result'!A11, invoice_test_data!A:A, 0)), "") | D11: MATERIAL | E11: 1
A12: 912113 | B12: x27026 sig air svc | C12: =IFERROR(INDEX(invoice_test_data!AI:AI, MATCH('Classification Test Result'!A12, invoice_test_data!A:A, 0)), "") | D12: MATERIAL | E12: 1
A13: 912112 | B13: x10198 3x10 traffic mat | C13: =IFERROR(INDEX(invoice_test_data!AI:AI, MATCH('Classification Test Result'!A13, invoice_test_data!A:A, 0)), "") | D13: MATERIAL | E13: 1
... A359: 911764 | B359: sh nl american electric div atbm p30 mvolt r2 4b p7 led cobra 4000k 4-bolt mnt nema label | C359: =IFERROR(INDEX(invoice_test_data!AI:AI, MATCH('Classification Test Result'!A359, invoice_test_data!A:A, 0)), "") | D359: BAD | E359: 1
A360: 911779 | B360: 43017427 | C360: =IFERROR(INDEX(invoice_test_data!AI:AI, MATCH('Classification Test Result'!A360, invoice_test_data!A:A, 0)), "") | D360: BAD | E360: 1
A361: 911778 | B361: 43017415 | C361: =IFERROR(INDEX(invoice_test_data!AI:AI, MATCH('Classification Test Result'!A361, invoice_test_data!A:A, 0)), "") | D361: BAD | E361: 1
A362: 911781 | B362: w winter service charge - nov 1 - mar 31 | C362: =IFERROR(INDEX(invoice_test_data!AI:AI, MATCH('Classification Test Result'!A362, invoice_test_data!A:A, 0)), "") | D362: BAD | E362: 1
A363: 911780 | B363: 30cnapgn 3000 psi pea-gravel mix no air | C363: =IFERROR(INDEX(invoice_test_data!AI:AI, MATCH('Classification Test Result'!A363, invoice_test_data!A:A, 0)), "") | D363: MATERIAL | E363: 1
A364: 911782 | B364: envsch environmental surcharge | C364: =IFERROR(INDEX(invoice_test_data!AI:AI, MATCH('Classification Test Result'!A364, invoice_test_data!A:A, 0)), "") | D364: FEE | E364: 1
A365: 911783 | B365: 6130 prime ns13835 pink 100ft 12/3 ext cord | C365: =IFERROR(INDEX(invoice_test_data!AI:AI, MATCH('Classification Test Result'!A365, invoice_test_data!A:A, 0)), "") | D365: MATERIAL | E365: 1
A366: 911752 | B366: ul 891 2019 ed 12 - switchboard | C366: =IFERROR(INDEX(invoice_test_data!AI:AI, MATCH('Classification Test Result'!A366, invoice_test_data!A:A, 0)), "") | D366: BAD | E366: 1
A367: 911754 | B367: b0cllm3zf8 1/4-20 x 1-1/4" flanged hex head bolt flange hexagon screw stainless steel 304 fully threaded 25 pc | C367: =IFERROR(INDEX(invoice_test_data!AI:AI, MATCH('Classification Test Result'!A367, invoice_test_data!A:A, 0)), "") | D367: MATERIAL | E367: 1
A368: 911753 | B368: b07bb7hgyl 25 1/4-20" x 1-1/2" serrated flange head bolt grade 5 zinc plated | C368: =IFERROR(INDEX(invoice_test_data!AI:AI, MATCH('Classification Test Result'!A368, invoice_test_data!A:A, 0)), "") | D368: MATERIAL | E368: 1
A369: 911755 | B369: b071kg9x11 penta socket with a 3/8" drive 13/16" - 5-point impact grade utility socket - lineworker tool made by rauckman utility product in the united state of america | C369: =IFERROR(INDEX(invoice_test_data!AI:AI, MATCH('Classification Test Result'!A369, invoice_test_data!A:A, 0)), "") | D369: BAD | E369: 1
A370: 911756 | B370: adv-rdr-aio-1y genetec advantage for 1 synergis reader - 1 year 2025/04/28 - 2026/02/28 genetec reference id gsc-181228-085044 | C370: =IFERROR(INDEX(invoice_test_data!AI:AI, MATCH('Classification Test Result'!A370, invoice_test_data!A:A, 0)), "") | D370: BAD | E370: 1
A371: 911723 | B371: b000crdkvc b000crdkvc gate 27008 fuel line/pcv/eec hose-25' length inner diameter 5/8" | C371: =IFERROR(INDEX(invoice_test_data!AI:AI, MATCH('Classification Test Result'!A371, invoice_test_data!A:A, 0)), "") | D371: MATERIAL | E371: 1
A372: 911724 | B372: return - 40 unit | C372: =IFERROR(INDEX(invoice_test_data!AI:AI, MATCH('Classification Test Result'!A372, invoice_test_data!A:A, 0)), "") | D372: BAD | E372: 1
A373: 911725 | B373: return - fuel surcharge | C373: =IFERROR(INDEX(invoice_test_data!AI:AI, MATCH('Classification Test Result'!A373, invoice_test_data!A:A, 0)), "") | D373: FEE | E373: 1
... A1835: 910245 | B1835: 6644-1 436455 resistor pack 2-1k 1/8 watt 1 percent | C1835: =IFERROR(INDEX(invoice_test_data!AI:AI, MATCH('Classification Test Result'!A1835, invoice_test_data!A:A, 0)), "") | D1835: MATERIAL | E1835: 1
A1836: 910247 | B1836: 262466 | C1836: =IFERROR(INDEX(invoice_test_data!AI:AI, MATCH('Classification Test Result'!A1836, invoice_test_data!A:A, 0)), "") | D1836: BAD | E1836: 1
A1837: 910246 | B1837: 5029-034 485556 t8003 ps57 power supply for the axis t8640 coax over ethernet adapter | C1837: =IFERROR(INDEX(invoice_test_data!AI:AI, MATCH('Classification Test Result'!A1837, invoice_test_data!A:A, 0)), "") | D1837: MATERIAL | E1837: 1
A1838: 910249 | B1838: freight | C1838: =IFERROR(INDEX(invoice_test_data!AI:AI, MATCH('Classification Test Result'!A1838, invoice_test_data!A:A, 0)), "") | D1838: FREIGHT | E1838: 1
A1839: 910248 | B1839: 6644-1 436455 resistor pack 2-1k 1/8 watt 1 percent | C1839: =IFERROR(INDEX(invoice_test_data!AI:AI, MATCH('Classification Test Result'!A1839, invoice_test_data!A:A, 0)), "") | D1839: MATERIAL | E1839: 1
A1840: 910250 | B1840: 8845-200-hp00-0 amz-00004-gso | C1840: =IFERROR(INDEX(invoice_test_data!AI:AI, MATCH('Classification Test Result'!A1840, invoice_test_data!A:A, 0)), "") | D1840: MATERIAL | E1840: 1
A1841: 910251 | B1841: hdj6-36 480055 hd jack cat6 clarity t568a/b - 8pos blue 180deg | C1841: =IFERROR(INDEX(invoice_test_data!AI:AI, MATCH('Classification Test Result'!A1841, invoice_test_data!A:A, 0)), "") | D1841: MATERIAL | E1841: 1
A1842: 910252 | B1842: 8845-200-hp00-0 amz-00004-gso | C1842: =IFERROR(INDEX(invoice_test_data!AI:AI, MATCH('Classification Test Result'!A1842, invoice_test_data!A:A, 0)), "") | D1842: MATERIAL | E1842: 1
A1843: 910253 | B1843: k-dl38a k-dl38a cs806638 armor door loop 3/8"id flex 18 | C1843: =IFERROR(INDEX(invoice_test_data!AI:AI, MATCH('Classification Test Result'!A1843, invoice_test_data!A:A, 0)), "") | D1843: MATERIAL | E1843: 1
A1844: 910254 | B1844: 8845-200-hp00-0 amz-00004-gso iot sensor wallmount enterprise reader hf-only amazon gso | C1844: =IFERROR(INDEX(invoice_test_data!AI:AI, MATCH('Classification Test Result'!A1844, invoice_test_data!A:A, 0)), "") | D1844: MATERIAL | E1844: 1
A1845: 910255 | B1845: 8845-200-hp00-0 amz-00004-gso iot sensor wallmount enterprise reader hf-only amazon gso | C1845: =IFERROR(INDEX(invoice_test_data!AI:AI, MATCH('Classification Test Result'!A1845, invoice_test_data!A:A, 0)), "") | D1845: MATERIAL | E1845: 1
A1846: 910281 | B1846: plt2s-c702y 324867 cable tie 7.4" 50lb 1.88" bundle diameter halar 100/pk rohs | C1846: =IFERROR(INDEX(invoice_test_data!AI:AI, MATCH('Classification Test Result'!A1846, invoice_test_data!A:A, 0)), "") | D1846: MATERIAL | E1846: 1
A1847: 910279 | B1847: 6200ue 877u1000 b6200ue-u1000 16-2c str bc lspvc lspvc jkt nat cmp 75c 1000' box | C1847: =IFERROR(INDEX(invoice_test_data!AI:AI, MATCH('Classification Test Result'!A1847, invoice_test_data!A:A, 0)), "") | D1847: MATERIAL | E1847: 1
A1848: 910277 | B1848: 6304fe 8771000 b6304fe-1000 18-6c str bc frpvc foil shd frpvc jkt nat cmp 75c 1000' reel | C1848: =IFERROR(INDEX(invoice_test_data!AI:AI, MATCH('Classification Test Result'!A1848, invoice_test_data!A:A, 0)), "") | D1848: MATERIAL | E1848: 1
... A2428: 909707 | B2428: freight | C2428: =IFERROR(INDEX(invoice_test_data!AI:AI, MATCH('Classification Test Result'!A2428, invoice_test_data!A:A, 0)), "") | D2428: FREIGHT | E2428: 1

Sheet Accuracy Results
B1: Categories AI CLASSIFIED | J1: True Positives | K1: False Positives | L1: False Negatives | M1: Precision | N1: Recall | O1: F1 Score
A2: CATEGORIES HUMAN VALIDATED | B2: BAD | C2: FEE | D2: FREIGHT | E2: LABOR | F2: MATERIAL | G2: TAX | I2: BAD | J2: =B3 -> 0 | K2: =SUM(B3:B8)-B3 -> 0 | L2: =SUM(B3:G3)-B3 -> 0 | M2: =J2/(J2+K2) -> #DIV/0! | N2: =J2/(J2+L2) -> #DIV/0! | O2: =2*M2*N2/SUM(M2:N2) -> #DIV/0!
A3: BAD | B3: =COUNTIFS(invoice_test_data!$AI:$AI, "BAD", invoice_test_data!$AJ:$AJ, "BAD") -> 0 | C3: =COUNTIFS(invoice_test_data!$AI:$AI, "BAD", invoice_test_data!$AJ:$AJ, "FEE") -> 0 | D3: =COUNTIFS(invoice_test_data!$AI:$AI, "BAD", invoice_test_data!$AJ:$AJ, "FREIGHT") -> 0 | E3: =COUNTIFS(invoice_test_data!$AI:$AI, "BAD", invoice_test_data!$AJ:$AJ, "LABOR") -> 0 | F3: =COUNTIFS(invoice_test_data!$AI:$AI, "BAD", invoice_test_data!$AJ:$AJ, "MATERIAL") -> 0 | G3: =COUNTIFS(invoice_test_data!$AI:$AI, "BAD", invoice_test_data!$AJ:$AJ, "TAX") -> 0 | I3: FEE | J3: =C4 -> 0 | K3: =SUM(C3:C8)-C4 -> 0 | L3: =SUM(B4:G4)-C4 -> 0 | M3: =J3/(J3+K3) -> #DIV/0! | N3: =J3/(J3+L3) -> #DIV/0! | O3: =2*M3*N3/SUM(M3:N3) -> #DIV/0!
A4: FEE | B4: =COUNTIFS(invoice_test_data!$AI:$AI, "FEE", invoice_test_data!$AJ:$AJ, "BAD") -> 0 | C4: =COUNTIFS(invoice_test_data!$AI:$AI, "FEE", invoice_test_data!$AJ:$AJ, "FEE") -> 0 | D4: =COUNTIFS(invoice_test_data!$AI:$AI, "FEE", invoice_test_data!$AJ:$AJ, "FREIGHT") -> 0 | E4: =COUNTIFS(invoice_test_data!$AI:$AI, "FEE", invoice_test_data!$AJ:$AJ, "LABOR") -> 0 | F4: =COUNTIFS(invoice_test_data!$AI:$AI, "FEE", invoice_test_data!$AJ:$AJ, "MATERIAL") -> 0 | G4: =COUNTIFS(invoice_test_data!$AI:$AI, "FEE", invoice_test_data!$AJ:$AJ, "TAX") -> 0 | I4: FREIGHT | J4: =D5 -> 0 | K4: =SUM(D3:D8)-D5 -> 0 | L4: =SUM(B5:G5)-D5 -> 0 | M4: =J4/(J4+K4) -> #DIV/0! | N4: =J4/(J4+L4) -> #DIV/0! | O4: =2*M4*N4/SUM(M4:N4) -> #DIV/0!
A5: FREIGHT | B5: =COUNTIFS(invoice_test_data!$AI:$AI, "FREIGHT", invoice_test_data!$AJ:$AJ, "BAD") -> 0 | C5: =COUNTIFS(invoice_test_data!$AI:$AI, "FREIGHT", invoice_test_data!$AJ:$AJ, "FEE") -> 0 | D5: =COUNTIFS(invoice_test_data!$AI:$AI, "FREIGHT", invoice_test_data!$AJ:$AJ, "FREIGHT") -> 0 | E5: =COUNTIFS(invoice_test_data!$AI:$AI, "FREIGHT", invoice_test_data!$AJ:$AJ, "LABOR") -> 0 | F5: =COUNTIFS(invoice_test_data!$AI:$AI, "FREIGHT", invoice_test_data!$AJ:$AJ, "MATERIAL") -> 0 | G5: =COUNTIFS(invoice_test_data!$AI:$AI, "FREIGHT", invoice_test_data!$AJ:$AJ, "TAX") -> 0 | I5: LABOR | J5: =E6 -> 0 | K5: =SUM(E3:E8)-E6 -> 0 | L5: =SUM(B6:G6)-E6 -> 0 | M5: =J5/(J5+K5) -> #DIV/0! | N5: =J5/(J5+L5) -> #DIV/0! | O5: =2*M5*N5/SUM(M5:N5) -> #DIV/0!
A6: LABOR | B6: =COUNTIFS(invoice_test_data!$AI:$AI, "LABOR", invoice_test_data!$AJ:$AJ, "BAD") -> 0 | C6: =COUNTIFS(invoice_test_data!$AI:$AI, "LABOR", invoice_test_data!$AJ:$AJ, "FEE") -> 0 | D6: =COUNTIFS(invoice_test_data!$AI:$AI, "LABOR", invoice_test_data!$AJ:$AJ, "FREIGHT") -> 0 | E6: =COUNTIFS(invoice_test_data!$AI:$AI, "LABOR", invoice_test_data!$AJ:$AJ, "LABOR") -> 0 | F6: =COUNTIFS(invoice_test_data!$AI:$AI, "LABOR", invoice_test_data!$AJ:$AJ, "MATERIAL") -> 0 | G6: =COUNTIFS(invoice_test_data!$AI:$AI, "LABOR", invoice_test_data!$AJ:$AJ, "TAX") -> 0 | I6: MATERIAL | J6: =F7 -> 0 | K6: =SUM(F3:F8)-F7 -> 0 | L6: =SUM(B7:G7)-F7 -> 0 | M6: =J6/(J6+K6) -> #DIV/0! | N6: =J6/(J6+L6) -> #DIV/0! | O6: =2*M6*N6/SUM(M6:N6) -> #DIV/0!
A7: MATERIAL | B7: =COUNTIFS(invoice_test_data!$AI:$AI, "MATERIAL", invoice_test_data!$AJ:$AJ, "BAD") -> 0 | C7: =COUNTIFS(invoice_test_data!$AI:$AI, "MATERIAL", invoice_test_data!$AJ:$AJ, "FEE") -> 0 | D7: =COUNTIFS(invoice_test_data!$AI:$AI, "MATERIAL", invoice_test_data!$AJ:$AJ, "FREIGHT") -> 0 | E7: =COUNTIFS(invoice_test_data!$AI:$AI, "MATERIAL", invoice_test_data!$AJ:$AJ, "LABOR") -> 0 | F7: =COUNTIFS(invoice_test_data!$AI:$AI, "MATERIAL", invoice_test_data!$AJ:$AJ, "MATERIAL") -> 0 | G7: =COUNTIFS(invoice_test_data!$AI:$AI, "MATERIAL", invoice_test_data!$AJ:$AJ, "TAX") -> 0 | I7: TAX | J7: =G8 -> 0 | K7: =SUM(G3:G8)-G8 -> 0 | L7: =SUM(B8:G8)-G8 -> 0 | M7: =J7/(J7+K7) -> #DIV/0! | N7: =J7/(J7+L7) -> #DIV/0! | O7: =2*M7*N7/SUM(M7:N7) -> #DIV/0!
A8: TAX | B8: =COUNTIFS(invoice_test_data!$AI:$AI, "TAX", invoice_test_data!$AJ:$AJ, "BAD") -> 0 | C8: =COUNTIFS(invoice_test_data!$AI:$AI, "TAX", invoice_test_data!$AJ:$AJ, "FEE") -> 0 | D8: =COUNTIFS(invoice_test_data!$AI:$AI, "TAX", invoice_test_data!$AJ:$AJ, "FREIGHT") -> 0 | E8: =COUNTIFS(invoice_test_data!$AI:$AI, "TAX", invoice_test_data!$AJ:$AJ, "LABOR") -> 0 | F8: =COUNTIFS(invoice_test_data!$AI:$AI, "TAX", invoice_test_data!$AJ:$AJ, "MATERIAL") -> 0 | G8: =COUNTIFS(invoice_test_data!$AI:$AI, "TAX", invoice_test_data!$AJ:$AJ, "TAX") -> 0
A9: TOTAL | B9: =SUM(B3:B8) -> 0 | C9: =SUM(C3:C8) -> 0 | D9: =SUM(D3:D8) -> 0 | E9: =SUM(E3:E8) -> 0 | F9: =SUM(F3:F8) -> 0 | G9: =SUM(G3:G8) -> 0 | I9: Definitions:
I10: True Positive: Correct Classification
I11: False Positives: Items that were incorrectly classified into a category when they actually belong to another category.
A12: OVERALL ACCURACY: SUM OF CORRECT CLASSIFICATION/ TOTAL DATA SET | I12: False Negatives: Items that should have been classified into a category, but were incorrectly classified into another category.
B13: BAD | C13: FEE | D13: FREIGHT | E13: LABOR | F13: MATERIAL | G13: TAX | I13: Precision = True Positives / (True Positives + False Positives)
A14: CORRECT CLASSIFICATION | B14: =B3 -> 0 | C14: =C4 -> 0 | D14: =D5 -> 0 | E14: =E6 -> 0 | F14: =F7 -> 0 | G14: =G8 -> 0 | I14: Recall = True Positives /(True Positives + False Negatives)
A15: TOTAL DATA SET | B15: 2413
A16: OVERALL ACCURACY | B16: =SUM(B14:G14)/B15 -> 0
A19: ACCURACY BY CATEGORY: CORRECT CLASSIFICATION/ TOTAL BY CATEGORY
B20: BAD | C20: FEE | D20: FREIGHT | E20: LABOR | F20: MATERIAL | G20: TAX
A21: CORRECT CLASSIFICATION | B21: =B3 -> 0 | C21: =C4 -> 0 | D21: =D5 -> 0 | E21: =E6 -> 0 | F21: =F7 -> 0 | G21: =G8 -> 0
A22: TOTAL BY CATEGORY by AI | B22: =B9 -> 0 | C22: =C9 -> 0 | D22: =D9 -> 0 | E22: =E9 -> 0 | F22: =F9 -> 0 | G22: =G9 -> 0
A23: ACCURACY BY CATEGORY | B23: =B21/B22 -> #DIV/0! | C23: =C21/C22 -> #DIV/0! | D23: =D21/D22 -> #DIV/0! | E23: =E21/E22 -> #DIV/0! | F23: =F21/F22 -> #DIV/0! | G23: =G21/G22 -> #DIV/0!
